Workbook

Sheet README
C1: FAMILY JOINT FINANCES — 30-YEAR PROJECTION, 2026 TO 2055 (version 2)
C3: Rebuilt with workplace and employer pension contributions, the 8%-to-2% return glidepath, the 19-year mortgage, maternity leave, self-sizing Junior ISAs, and contributions that are DERIVED from what is actually affordable rather than assumed. Every number is a live formula.
C5: START HERE
C6: 1. Analysis — the written answers.
C7: 2. Analysis_DM_Exit — when DM can stop, base case: three rungs, and a year-by-year sweep behind them.
C8: 3. Analysis_Exit_3rd — the same question with a third child.
C9: 4. Assumptions — every input. Blue cells are yours to change; yellow ones matter most.
C11: THE SHEETS
C12: README — This page.
C13: Analysis — The written analysis and recommendations.
C14: Assumptions — Every input: inflation, salaries, base salaries, pension percentages, balances, expenses, children's dates, tax parameters, maternity leave, and the definitions of the three tests.
C15: Tax_Bands — UK tax thresholds and allowances year by year — frozen in cash terms to 2030/31, then uprated with inflation.
... C62: This is a planning model, not regulated financial advice. With pensions on track to pass £12m, take advice on the lump sum allowance (£268,275 each) and on inheritance tax before acting on any of it.

Sheet Analysis
C1: ANALYSIS — WHEN CAN DM STOP WORKING?
C3: THE HEADLINE: THE ANSWER HAS MOVED A LONG WAY, AND IN YOUR FAVOUR
C4: On the numbers you have now given, DM does not have a date so much as a choice. Even with DM earning nothing at all from the business, the household is solvent all the way to retirement if he stops at the end of THIS year.
C5: Three things moved it. (1) A correction: version 1 treated a £1 gross SIPP contribution as £1 of cash leaving the household, when relief at source means it costs 80p — that alone was worth about £24,000 a year. (2) Employer pension contributions of £29,600 a year are money you were previously funding yourselves. (3) The mortgage ends in 2044, not 2055.
C6: Pulling the other way: the return assumption has come down from a flat 10% to your 8% glidepath, which by 2055 has DM's pension earning 2.0% and the joint ISA 2.5%.
C8: THE LADDER — PICK YOUR RUNG
C9: DM's last full working year | D9: Base case | E9: DM's age | F9: Third child | G9: DM's age
C10: RUNG 1 — DM stops and the family lives partly off savings until MM's pension unlocks. This is the test you asked for: 'we can tap into earnings to cover expenses.' | D10: =Analysis_DM_Exit!$C$115 -> 2026 | E10: =Analysis_DM_Exit!$C$116 -> 44 | F10: =Analysis_Exit_3rd!$C$115 -> 2027 | G10: =Analysis_Exit_3rd!$C$116 -> 45
C11: RUNG 2 — DM stops and MM's pay alone covers everything, with no drawdown at all, ever. | D11: =Analysis_DM_Exit!$C$117 -> 2031 | E11: =Analysis_DM_Exit!$C$118 -> 49 | F11: =Analysis_Exit_3rd!$C$117 -> 2033 | G11: =Analysis_Exit_3rd!$C$118 -> 51
C12: RUNG 3 — as Rung 2, but with a 20% comfort margin on top. | D12: =Analysis_DM_Exit!$C$119 -> 2033 | E12: =Analysis_DM_Exit!$C$120 -> 51 | F12: =Analysis_Exit_3rd!$C$119 -> 2044 | G12: =Analysis_Exit_3rd!$C$120 -> 62
C14: Read that as: he could go now and be fine; he could go at 49 and never touch savings; he could go at 51 with room to spare.
C15: With a third child the same three rungs are 2027 (age 45), 2033 (age 51) and 2044 (age 62). The third rung jumps a long way because your post-maternity income of £180,000 is, in real terms, BELOW the £170,000 path it replaces — by 2034 MM's pay covers 1.17x of household spending, just under the 1.20x bar, and it only clears once the mortgage ends in 2045.
C17: WHAT 'ENOUGH' MEANS NOW (all three must pass — Assumptions rows 111 to 115)
C18: TEST 1 — SURVIVAL. From the year DM stops until MM turns 57 in 2048 and the pensions unlock, liquid savings must never fall below 12 months of household spending. This is the test that lets you live off savings.
C19: TEST 2 — BUFFER AT THE DOOR. On the day he stops: 12 months of spending PLUS £100,000 of business capital he could lose entirely.
C20: TEST 3 — RETIREMENT. With no further contributions from DM and only MM's contractual workplace pension continuing, the pensions must reach 25x adult-only spending by 2048, grossed up for tax on withdrawal.
C21: Test 3 is never close: the required pot is £2.76m and the projection lands at £7.6m even if DM stops in 2026. Test 2 passes from the start. Test 1 is the only one that ever fails, and only in the third-child case if DM goes in 2026.
C23: What Rung 1 actually looks like — DM stops at the end of 2026, no business income at all:
C24: Liquid savings dip from £302,000 to a low of £264,000 in 2028, then climb back. The annual gap is £45,000 in 2027 and £47,000 in 2028, narrowing to £14,000 by 2029 as EM's nursery ends and to nothing by 2032. From 2034 the nannies stop and the household is adding £26,000 a year again. The floor is £130,000 — the worst margin over it is £140,000, in 2028.
C26: THE JUNIOR ISAs — HOW MUCH, AND WHEN TO STOP
C27: Each pot is sized to cover three years of university PLUS the year of London living after graduation, and the model turns the £9,000 off the moment the pot on its own will get there. The target is the cost stream discounted back at 8%.
C28: Child | D28: Target fund | E28: Needed by | F28: £9,000 payments | G28: Total paid in | H28: Left over at 21
C29: VM (already has £15,000) | D29: =Children!$C$20 -> 121358.18 | E29: 2039 | F29: 4 — 2026 to 2029 | G29: 36000 | H29: =Children!$AF$26 -> 1871.5495
C30: EM (starting from zero) | D30: =Children!$C$32 -> 128786.27 | E30: 2042 | F30: 6 — 2026 to 2031 | G30: 54000 | H30: =Children!$AF$38 -> 40395.843
C31: Child 3 (scenario) | D31: =Children!$C$44 -> 136669.02 | E31: 2045 | F31: 6 — 2028 to 2033 | G31: 54000 | H31: =Children!$AF$50 -> 40275.844
C33: So the whole education bill is settled with £90,000 of Junior ISA contributions spread over six years, all finished by 2031 — and £144,000 over eight years if there is a third child. That is far less than the £9,000-a-year-forever plan in version 1, which would have put £324,000 into EM's pot alone.
C34: VM lands almost exactly on target (£1,872 spare). EM and Child 3 overshoot by about £40,000 each, because the last £9,000 payment tips them past the line — the rule you asked for is £9,000 or nothing. If you would rather land exactly, make the final payment a part payment; it saves roughly £7,000 of contribution in each case.
C36: Junior ISA rules that matter
C37: • £9,000 a year per child, entirely separate from your own £20,000 ISA allowances. Frozen at £9,000 until April 2031.
C38: • Nothing can be withdrawn before 18 — not by you, not by them.
C39: • At 18 the account becomes an adult ISA in the child's name. They control it, and they can spend it on anything. That is the real risk in over-funding, and the reason to stop once the pot is big enough.
C40: • Growth and withdrawals are free of income tax and capital gains tax.
C41: • Timing: VM turns 18 in December 2038 and starts university in October 2039 — clean. EM turns 18 on 14 December 2042 but starts in October 2042, so budget to fund his first term from household cash.
C43: CAN YOU MAX OUT THE PENSIONS AND ISAs? MOSTLY YES
C44: Base case: BOTH £60,000 pension allowances are filled every single year of the projection. In 2026 that is £52,200 of workplace contributions (yours plus your employers') and £67,800 of personal SIPP on top.
C45: The ISAs are the only thing that gets squeezed, and only at the start: £21,400 of the £40,000 in 2026 and £25,000 in 2027, because EM's nursery and both Junior ISAs are running at the same time. From 2028 both £20,000 allowances are filled every year.
C47: Third child: this is where it bites. The pension allowances CANNOT be filled in 2027, 2028 and 2029.
C48: Year | D48: Cash available | E48: SIPP headroom | F48: Actually paid in | G48: Allowance lost | H48: ISA
C49: 2027 | D49: =Scen_3rd_Child!D$36 -> 39608.6 | E49: =Scen_3rd_Child!D$38 -> 64452 | F49: =Scen_3rd_Child!D$41+Scen_3rd_Child!D$42 -> 49510.75 | G49: =Scen_3rd_Child!D$38-Scen_3rd_Child!D$41-Scen_3rd_Child!D$42 -> 14941.25 | H49: =Scen_3rd_Child!D$58 -> 15045.565
C50: 2028 | D50: =Scen_3rd_Child!E$36 -> 28520.652 | E50: =Scen_3rd_Child!E$38 -> 62230.08 | F50: =Scen_3rd_Child!E$41+Scen_3rd_Child!E$42 -> 35650.815 | G50: =Scen_3rd_Child!E$38-Scen_3rd_Child!E$41-Scen_3rd_Child!E$42 -> 26579.265 | H50: =Scen_3rd_Child!E$58 -> 9663.9321
C51: 2029 | D51: =Scen_3rd_Child!F$36 -> 46053.359 | E51: =Scen_3rd_Child!F$38 -> 61074.682 | F51: =Scen_3rd_Child!F$41+Scen_3rd_Child!F$42 -> 57566.699 | G51: =Scen_3rd_Child!F$38-Scen_3rd_Child!F$41-Scen_3rd_Child!F$42 -> 3507.9828 | H51: =Scen_3rd_Child!F$58 -> 14391.675
C53: £45,000 of pension allowance goes unused across those three years, and the ISAs drop to £9,700–£15,000. Nothing goes into deficit — the model cuts the saving, not the spending. Two things soften it: carry-forward of unused annual allowance from the previous three tax years is not modelled here and would let you recover most of that £45,000 later; and if either workplace scheme uses salary sacrifice the cash position is slightly better than shown.
C55: THE BASE CASE IN NUMBERS
C56: In the money of the day unless stated | D56: 2026 | E56: 2031 | F56: 2033 | G56: 2040 | H56: 2048 | I56: 2055
C57: Total net pay | D57: =Household_Base!C$10 -> 201942.8 | E57: =Household_Base!H$10 -> 228522.86 | F57: =Household_Base!J$10 -> 237755.18 | G57: =Household_Base!Q$10 -> 273105.97 | H57: =Household_Base!Y$10 -> 319987.17 | I57: =Household_Base!AF$10 -> 367564.67
C58: Total household expenses | D58: =Household_Base!C$22 -> 125400 | E58: =Household_Base!H$22 -> 106745.64 | F58: =Household_Base!J$22 -> 111058.16 | G58: =Household_Base!Q$22 -> 102879.77 | H58: =Household_Base!Y$22 -> 82931.556 | I58: =Household_Base!AF$22 -> 95262.29
C59: memo: expenses in 2026 money | D59: =Household_Base!C$23 -> 125400 | E59: =Household_Base!H$23 -> 93000 | F59: =Household_Base!J$23 -> 93000 | G59: =Household_Base!Q$23 -> 75000 | H59: =Household_Base!Y$23 -> 51600 | I59: =Household_Base!AF$23 -> 51600
C60: Into pensions this year | D60: =Household_Base!C$46 -> 120000 | E60: =Household_Base!H$46 -> 122400 | F60: =Household_Base!J$46 -> 127344.96 | G60: =Household_Base!Q$46 -> 146279.33 | H60: =Household_Base!Y$46 -> 171389.55 | I60: =Household_Base!AF$46 -> 196872.72
C61: Into ISAs this year | D61: =Household_Base!C$47 -> 21423.8 | E61: =Household_Base!H$47 -> 40800 | F61: =Household_Base!J$47 -> 42448.32 | G61: =Household_Base!Q$47 -> 48759.777 | H61: =Household_Base!Y$47 -> 57129.85 | I61: =Household_Base!AF$47 -> 65624.24
C62: Into Junior ISAs this year | D62: =Household_Base!C$48 -> 18000 | E62: =Household_Base!H$48 -> 9000 | F62: =Household_Base!J$48 -> 0 | G62: =Household_Base!Q$48 -> 0 | H62: =Household_Base!Y$48 -> 0 | I62: =Household_Base!AF$48 -> 0
C63: Net cash flow left over | D63: =Household_Base!C$44 -> 0 | E63: =Household_Base!H$44 -> 38375.463 | F63: =Household_Base!J$44 -> 49289.431 | G63: =Household_Base!Q$44 -> 81309.209 | H63: =Household_Base!Y$44 -> 132875.19 | I63: =Household_Base!AF$44 -> 152631.83
C64: Liquid savings (ISA + taxable) | D64: =Household_Base!C$65 -> 302223.8 | E64: =Household_Base!H$65 -> 766849.01 | F64: =Household_Base!J$65 -> 1079132.8 | G64: =Household_Base!Q$65 -> 2813841.8 | H64: =Household_Base!Y$65 -> 5656937.8 | I64: =Household_Base!AF$65 -> 8364525.9
C65: Pensions | D65: =Household_Base!C$64 -> 1459200 | E65: =Household_Base!H$64 -> 2850435.6 | F65: =Household_Base!J$64 -> 3581404.2 | G65: =Household_Base!Q$64 -> 7000311.5 | H65: =Household_Base!Y$64 -> 12322229 | I65: =Household_Base!AF$64 -> 17166514
C66: Total net worth, excluding the house | D66: =Household_Base!C$66 -> 1761423.8 | E66: =Household_Base!H$66 -> 3617284.7 | F66: =Household_Base!J$66 -> 4660537 | G66: =Household_Base!Q$66 -> 9814153.3 | H66: =Household_Base!Y$66 -> 17979166 | I66: =Household_Base!AF$66 -> 25531040
C67: memo: net worth in 2026 money | D67: =Household_Base!C$67 -> 1761423.8 | E67: =Household_Base!H$67 -> 3151486.8 | F67: =Household_Base!J$67 -> 3902729.2 | G67: =Household_Base!Q$67 -> 7154579.2 | H67: =Household_Base!Y$67 -> 11186634 | I67: =Household_Base!AF$67 -> 13829204
C68: MM's pay ÷ household outgoings | D68: =Analysis_DM_Exit!C$8 -> 0.6836569 | E68: =Analysis_DM_Exit!H$8 -> 0.95697044 | F68: =Analysis_DM_Exit!J$8 -> 1.0376551 | G68: =Analysis_DM_Exit!Q$8 -> 1.2866923 | H68: =Analysis_DM_Exit!Y$8 -> 1.8701923 | I68: =Analysis_DM_Exit!AF$8 -> 1.8701923
C70: WHAT WE WOULD ACTUALLY DO
C71: • Do not read Rung 1 as 'quit tomorrow'. It says the ARITHMETIC works. What it does not say is that it is comfortable: for six years the family would be spending more than it earns, and by 2028 you would have £264,000 of accessible money against £1.7m locked in pensions neither of you can touch until 2039 and 2048 respectively.
C72: • If DM wants to go early, divert cash from the SIPP to the ISA for two or three years first. The model fills the SIPP before the ISA because the relief is worth roughly 50p in the pound for MM in the £100k–£125k band. That is the right call while you both work — it is the wrong call in the two years before a planned income cliff.
C73: • Rung 2 — DM's last working year 2031, age 49 — is the one we would aim at. Nothing is being drawn down, EM's nursery is long gone, both Junior ISAs are finished, and there is still £767,000 liquid plus £2.85m of pensions behind it.
C74: • MM's income protection and life cover are now the most important policies you own. From the moment DM stops, one salary carries a family of four or five for up to two decades. Check the sum insured and the deferred period.
C75: • Watch the pension total. On these assumptions you reach £12.3m by 2048. The lifetime allowance is gone, but the tax-free lump sum is capped at £268,275 each — everything above that is taxed as income on the way out. At some point the marginal £1 into a SIPP stops being obviously better than the same £1 into an ISA. Worth advice well before then.
C77: WHAT WOULD CHANGE THE ANSWER
C78: • The glidepath. It does not affect Rungs 2 and 3 at all — those are pure income-versus-spending tests with no investment return in them. It affects Rung 1 and Test 3, both of which pass with enormous room.
C79: • DM earning anything from the business. Assumed to be zero for thirty years. Every £1 of profit moves all three rungs earlier.
C80: • The mortgage. £1,950 a month is inflated in line with everything else because that is what you asked for. A fixed repayment mortgage would not be — that makes this projection pessimistic by a growing amount, and the mortgage is the single biggest line in the adult budget until it ends in 2044.
C81: • MM keeping her personal SIPP going after DM stops. The sweep assumes she stops it and keeps only the workplace scheme. If she carried on contributing, Rung 1 would move later and the pensions would be larger still.
C82: • Carry-forward of unused pension allowance — not modelled, and worth about £45,000 in the third-child case.
... C92: This is a planning model, not regulated financial advice.

Sheet Assumptions
A1: FAMILY JOINT FINANCES — 30-YEAR PROJECTION | ASSUMPTIONS (v2)
A2: Model years are CALENDAR years. Tax parameters use the UK tax year beginning in April of that year. School and university years begin in the September of that year. 2026 figures are as supplied by the family.
A3: COLOUR KEY: blue = an input you can change | black = formula | green = link to another sheet | yellow fill = key assumption
A5: 1. TIMELINE, INFLATION AND AGES
B6: Year | C6: 2026 | D6: 2027 | E6: 2028 | F6: 2029 | G6: 2030 | H6: 2031 | I6: 2032 | J6: 2033 | K6: 2034 | L6: 2035 | M6: 2036 | N6: 2037 | O6: 2038 | P6: 2039 | Q6: 2040 | R6: 2041 | S6: 2042 | T6: 2043 | U6: 2044 | V6: 2045 | W6: 2046 | X6: 2047 | Y6: 2048 | Z6: 2049 | AA6: 2050 | AB6: 2051 | AC6: 2052 | AD6: 2053 | AE6: 2054 | AF6: 2055
B7: Projection year | C7: 1 | D7: =C7+1 -> 2 | E7: =D7+1 -> 3 | F7: =E7+1 -> 4 | G7: =F7+1 -> 5 | H7: =G7+1 -> 6 | I7: =H7+1 -> 7 | J7: =I7+1 -> 8 | K7: =J7+1 -> 9 | ... AF7: =AE7+1 -> 30
B8: Inflation rate (applied to the prior year) | C8: 0 | D8: 0.04 | E8: 0.04 | F8: 0.02 | G8: 0.02 | H8: 0.02 | I8: 0.02 | J8: 0.02 | K8: 0.02 | L8: 0.02 | M8: 0.02 | N8: 0.02 | O8: 0.02 | P8: 0.02 | Q8: 0.02 | R8: 0.02 | S8: 0.02 | T8: 0.02 | U8: 0.02 | V8: 0.02 | W8: 0.02 | X8: 0.02 | Y8: 0.02 | Z8: 0.02 | AA8: 0.02 | AB8: 0.02 | AC8: 0.02 | AD8: 0.02 | AE8: 0.02 | AF8: 0.02 | AI8: User instruction: 4% for two years, then 2% to perpetuity.
B9: Inflation index (2026 = 1.000) | C9: 1 | D9: =C9*(1+D8) -> 1.04 | E9: =D9*(1+E8) -> 1.0816 | F9: =E9*(1+F8) -> 1.103232 | G9: =F9*(1+G8) -> 1.1252966 | H9: =G9*(1+H8) -> 1.1478026 | I9: =H9*(1+I8) -> 1.1707586 | J9: =I9*(1+J8) -> 1.1941738 | K9: =J9*(1+K8) -> 1.2180573 | ... AF9: =AE9*(1+AF8) -> 1.8461684
B10: Tax / allowance threshold uprating | C10: 0 | D10: 0 | E10: 0 | F10: 0 | G10: 0 | H10: =H8 -> 0.02 | I10: =I8 -> 0.02 | J10: =J8 -> 0.02 | K10: =K8 -> 0.02 | L10: =L8 -> 0.02 | M10: =M8 -> 0.02 | N10: =N8 -> 0.02 | O10: =O8 -> 0.02 | ... AF10: =AF8 -> 0.02 | AI10: Income-tax thresholds, the personal allowance and the pension / ISA / JISA allowances are frozen in cash terms to 2030/31 under current UK policy, then assumed to rise with inflation.
B11: Tax threshold index (2026 = 1.000) | C11: 1 | D11: =C11*(1+D10) -> 1 | E11: =D11*(1+E10) -> 1 | F11: =E11*(1+F10) -> 1 | G11: =F11*(1+G10) -> 1 | H11: =G11*(1+H10) -> 1.02 | I11: =H11*(1+I10) -> 1.0404 | J11: =I11*(1+J10) -> 1.061208 | K11: =J11*(1+K10) -> 1.0824322 | ... AF11: =AE11*(1+AF10) -> 1.640606
B12: MM age (at 31 December) | C12: 35 | D12: =C12+1 -> 36 | E12: =D12+1 -> 37 | F12: =E12+1 -> 38 | G12: =F12+1 -> 39 | H12: =G12+1 -> 40 | I12: =H12+1 -> 41 | J12: =I12+1 -> 42 | K12: =J12+1 -> 43 | ... AF12: =AE12+1 -> 64
B13: DM age (at 31 December) | C13: 44 | D13: =C13+1 -> 45 | E13: =D13+1 -> 46 | F13: =E13+1 -> 47 | G13: =F13+1 -> 48 | H13: =G13+1 -> 49 | I13: =H13+1 -> 50 | J13: =I13+1 -> 51 | K13: =J13+1 -> 52 | ... AF13: =AE13+1 -> 73
B14: Average age of MM and DM (drives the joint ISA glidepath) | C14: =(C12+C13)/2 -> 39.5 | D14: =(D12+D13)/2 -> 40.5 | E14: =(E12+E13)/2 -> 41.5 | F14: =(F12+F13)/2 -> 42.5 | G14: =(G12+G13)/2 -> 43.5 | H14: =(H12+H13)/2 -> 44.5 | I14: =(I12+I13)/2 -> 45.5 | J14: =(J12+J13)/2 -> 46.5 | ... AF14: =(AF12+AF13)/2 -> 68.5
B15: VM age | C15: 6 | D15: =C15+1 -> 7 | E15: =D15+1 -> 8 | F15: =E15+1 -> 9 | G15: =F15+1 -> 10 | H15: =G15+1 -> 11 | I15: =H15+1 -> 12 | J15: =I15+1 -> 13 | K15: =J15+1 -> 14 | ... AF15: =AE15+1 -> 35
B16: EM age | C16: 3 | D16: =C16+1 -> 4 | E16: =D16+1 -> 5 | F16: =E16+1 -> 6 | G16: =F16+1 -> 7 | H16: =G16+1 -> 8 | I16: =H16+1 -> 9 | J16: =I16+1 -> 10 | K16: =J16+1 -> 11 | ... AF16: =AE16+1 -> 32
B17: Child 3 age (scenario only) | C17: =IF(C6<2027,"",C6-2027) | D17: =IF(D6<2027,"",D6-2027) -> 0 | E17: =IF(E6<2027,"",E6-2027) -> 1 | F17: =IF(F6<2027,"",F6-2027) -> 2 | G17: =IF(G6<2027,"",G6-2027) -> 3 | H17: =IF(H6<2027,"",H6-2027) -> 4 | I17: =IF(I6<2027,"",I6-2027) -> 5 | J17: =IF(J6<2027,"",J6-2027) -> 6 | ... AF17: =IF(AF6<2027,"",AF6-2027) -> 28
A19: 2. THE TWO EARNERS — POSITION AT THE START OF 2026
C20: MM | D20: DM | E20: Source / note
B21: Total gross income (£/yr) | C21: 170000 | D21: 190000 | E21: Supplied by the family.
B22: Base salary in 2026 (£/yr) | C22: 100000 | D22: 130000 | E22: Supplied by the family. Base salary drives the workplace pension percentages.
B23: Base salary in 2027 (£/yr) — MM only | C23: 110000 | D23: 0 | E23: Supplied by the family. Set to 0 for DM, whose base simply grows with inflation.
B24: Age at 31 December 2026 | C24: 35 | D24: 44 | E24: Supplied by the family.
B25: ISA balance (£) | C25: 80000 | D25: 180000 | E25: Supplied by the family. The model runs these as ONE joint household pot.
B26: Pension balance (£) | C26: 480000 | D26: 760000 | E26: Supplied by the family.
B27: Personal expenses (£/month, 2026 prices) | C27: 1000 | D27: 800 | E27: Supplied by the family.
B28: Employee workplace pension (% of base salary) | C28: 0.07 | D28: 0.12 | E28: Supplied by the family.
B29: Employer workplace pension (% of base salary) | C29: 0.14 | D29: 0.12 | E29: Supplied by the family. Employer contributions count towards the £60,000 annual allowance.
A31: 3. INVESTMENT RETURNS
B32: Junior ISA return (flat, all years) | C32: 0.08 | E32: User instruction: Junior ISA return changed to 8%.
B33: Glidepath — return before the taper begins | C33: 0.08 | E33: User instruction: 'tapers from 8% to 2%'.
B34: Glidepath — age at which the taper begins | C34: 50 | E34: User instruction.
B35: Glidepath — return once the taper is complete | C35: 0.02 | E35: User instruction.
B36: Glidepath — age at which the taper is complete | C36: 70 | E36: User instruction.
B37: Tax drag on taxable (non-ISA) savings | C37: 0.015 | E37: Assumed dividend tax and CGT cost on a general investment account. Not supplied.
B38: Floor on the taxable-savings return | C38: 0.005 | E38: Stops the drag pushing the net return below zero late in the projection.
B39: Apply the glidepath to PENSIONS as well? (1 = yes) | C39: 1 | E39: YOU ONLY SPECIFIED THE ISA. Leaving pensions at a flat 8% while the ISA tapers would be inconsistent, so the same age glidepath is applied to each person's pension, using their own age. Set to 0 to hold pensions flat at the rate in C33.
A41: 4. CONTRIBUTION ALLOWANCES (2026/27 level, uprated by the threshold index)
B42: Pension annual allowance (each) | C42: 60000 | E42: £60,000 for 2026/27. Covers EMPLOYEE + EMPLOYER workplace contributions AND any personal SIPP contribution.
B43: ISA allowance (each) | C43: 20000 | E43: £20,000 for 2026/27.
B44: Junior ISA allowance (per child) | C44: 9000 | E44: £9,000 for 2026/27, separate from the adult ISA allowance and frozen until April 2031.
B45: Pension taper — adjusted income threshold | C45: 260000 | E45: Annual allowance falls by £1 for every £2 of adjusted income above this. Adjusted income includes employer contributions.
B46: Pension taper — minimum annual allowance | C46: 10000 | E46: Floor on the tapered annual allowance.
A48: 5. UK TAX PARAMETERS (England & Wales, 2026/27)
B49: Personal allowance | C49: 12570 | E49: Published 2026/27 England & Wales rates and thresholds.
B50: Personal allowance taper starts | C50: 100000
B51: Basic rate limit (taxable income) | C51: 37700
B52: Additional rate threshold (taxable income) | C52: 125140
B53: Basic rate | C53: 0.2 | E53: Workplace pension contributions are modelled as a NET PAY arrangement: they reduce taxable pay but not National Insurance. Personal SIPP contributions are relief at source: 20% is added by HMRC and the bands are extended by the gross contribution.
B54: Higher rate | C54: 0.4
B55: Additional rate | C55: 0.45
B56: National Insurance primary threshold | C56: 12570
B57: National Insurance upper earnings limit | C57: 50270
B58: National Insurance main rate | C58: 0.08
B59: National Insurance upper rate | C59: 0.02
A61: 6. HOUSEHOLD EXPENSES (2026 prices — every line is inflated year by year)
B62: Mortgage (£/month) | C62: 1950 | E62: Supplied by the family.
B63: Mortgage term remaining as at 2026 (years) | C63: 19 | E63: Supplied by the family.
B64: Final year of mortgage payments | C64: =$C$6+$C$63-1 -> 2044 | E64: Calculated: 19 years starting 2026.
B65: General family spending (£/month) | C65: 2000 | E65: Supplied by the family.
B66: Nannies (£/month, both together) | C66: 1500 | E66: Supplied by the family.
B67: Last full year of nanny costs | C67: 2033 | E67: EM turns 10 on 14 December 2033.
B68: Nursery (£/month, per child) | C68: 2700 | E68: Supplied by the family.
B69: Travel — China (£/yr) | C69: 3000 | E69: Supplied by the family, 2026 prices.
B70: Travel — Italy (£/yr) | C70: 1000 | E70: Supplied by the family, 2026 prices.
B71: Travel — family holiday (£/yr) | C71: 2000 | E71: Supplied by the family, 2026 prices.
B72: Extra general spending per additional child (£/month) | C72: 500 | E72: NOT SUPPLIED — assumption used only in the third-child scenario.
A74: 7. UNIVERSITY AND THE POST-GRADUATION YEAR (2026/27 prices)
B75: Tuition fee (£/yr) | C75: 9790 | E75: England home-fee cap for 2026/27. Source: Higher Education (Fee Limits) Regulations, House of Commons Library CBP-10155.
B76: Accommodation and living at university (£/yr) | C76: 15660 | E76: Cambridge's own 2026-27 estimate for a student in Cambridge all year round. Source: undergraduate.study.cam.ac.uk/fees-funding/living-costs.
B77: Length of undergraduate course (years) | C77: 3 | E77: Standard English three-year degree.
B78: One year of London living after graduation (£/yr) | C78: 30000 | E78: NOT SUPPLIED as a number. Graduate house-share level: rent plus bills, food, travel and personal spending. A single professional in London needs roughly £44,000 gross (~£34,000 net) for a place of their own; students budget nearer £25,000. £30,000 sits between the two. Sources: thesqua.re and movingtotheuk.co.uk London cost-of-living guides, 2026.
A80: 8. CHILDREN — DATES AND JUNIOR ISAs
C81: VM | D81: EM | E81: Child 3 (scenario) | F81: Note
B82: Date of birth | C82: 27/12/2020 | D82: 14/12/2023 | E82: 01/07/2027 | F82: Supplied. Child 3 assumed born July 2027.
B83: Starts Reception (September of) | C83: 2025 | D83: 2028 | E83: 2031 | F83: English school year runs Sept-Aug.
B84: Nursery — first year of fees | C84: 0 | D84: 2026 | E84: 2028 | F84: VM is already at school.
B85: Nursery — months charged in that first year | C85: 0 | D85: 12 | E85: 4 | F85: Child 3: September to December 2028.
B86: Nursery — last year of fees | C86: 0 | D86: 2028 | E86: 2031 | F86: Fees stop at Reception.
B87: Nursery — months charged in that last year | C87: 0 | D87: 8 | E87: 8 | F87: January to August.
B88: Turns 18 (Junior ISA matures into an adult ISA) | C88: 2038 | D88: 2042 | E88: 2045 | F88: A JISA converts automatically at 18 and the child then controls it.
B89: First university year (starts September of) | C89: 2039 | D89: 2042 | E89: 2045 | F89: After Year 13.
B90: Year of the funded post-graduation London year | C90: 2042 | D90: 2045 | E90: 2048 | F90: The year after the three-year degree ends.
B91: Junior ISA balance at the start of 2026 (£) | C91: 15000 | D91: 0 | E91: 0 | F91: Supplied by the family.
B92: Junior ISA contribution while still needed (£/yr) | C92: 9000 | D92: 9000 | E92: 9000 | F92: User instruction: max out at £9,000 a year, then stop once the pot is big enough.
B93: Junior ISA — earliest contribution year | C93: 2026 | D93: 2026 | E93: 2028 | F93: Child 3 assumed to start in the first full year after birth.
B94: Junior ISA — latest contribution year | C94: 2038 | D94: 2041 | E94: 2044 | F94: Contributions must stop on the child's 18th birthday.
A96: 9. MATERNITY LEAVE (third-child scenario only)
B97: Months of leave MM takes | C97: 9 | E97: Supplied by the family.
B98: Leave begins | C98: 2027 | E98: Child 3 born July 2027.
B99: Month of the year leave begins (1 = January) | C99: 7 | E99: July.
B100: Months of leave paid at full base salary | C100: 6 | E100: Pension contributions (both employee and employer) are modelled on FULL base salary throughout the leave. UK rules require the employer to keep contributing at the full rate during paid leave; holding the employee side at the full rate too is a small simplification worth about £1,000.
B101: Base salary rate used for maternity pay (£/yr) | C101: 110000 | E101: Supplied by the family: 'assume at £110k'.
B102: Months of leave paid at half pay | C102: 3 | E102: Supplied by the family.
B103: MM total income on returning to work (£/yr, nominal) | C103: 180000 | E103: Supplied by the family: 'after maternity leave, assume that her income starts at £180k'. Treated as the rate at the point of return in 2028, growing with inflation thereafter.
B104: Year MM returns to work | C104: 2028 | E104: Nine months from July 2027 is April 2028.
B105: Months worked in the year she returns | C105: 9 | E105: April to December 2028.
A107: 10. DEFINITION OF 'ENOUGH' FOR DM TO STOP WORKING
B108: Pension access age | C108: 57 | E108: Normal minimum pension age is 57 from April 2028.
B109: Year MM reaches pension access age | C109: =$C$6+($C$108-$C$24) -> 2048 | E109: The point at which the household can unlock its pensions.
B110: Year DM reaches pension access age | C110: =$C$6+($C$108-$D$24) -> 2039 | E110: Calculated.
...

Sheet Tax_Bands
A1: UK TAX AND ALLOWANCE THRESHOLDS BY YEAR
A2: 2026/27 statutory figures, frozen in cash terms to 2030/31 (current UK policy) then uprated with inflation.
A4: THRESHOLDS AND RATES
B5: Year | C5: 2026 | D5: 2027 | E5: 2028 | F5: 2029 | G5: 2030 | H5: 2031 | I5: 2032 | J5: 2033 | K5: 2034 | L5: 2035 | M5: 2036 | N5: 2037 | O5: 2038 | P5: 2039 | Q5: 2040 | R5: 2041 | S5: 2042 | T5: 2043 | U5: 2044 | V5: 2045 | W5: 2046 | X5: 2047 | Y5: 2048 | Z5: 2049 | AA5: 2050 | AB5: 2051 | AC5: 2052 | AD5: 2053 | AE5: 2054 | AF5: 2055
B6: Threshold uprating index (2026 = 1.000) | C6: =Assumptions!C$11 -> 1 | D6: =Assumptions!D$11 -> 1 | E6: =Assumptions!E$11 -> 1 | F6: =Assumptions!F$11 -> 1 | G6: =Assumptions!G$11 -> 1 | H6: =Assumptions!H$11 -> 1.02 | I6: =Assumptions!I$11 -> 1.0404 | J6: =Assumptions!J$11 -> 1.061208 | ... AF6: =Assumptions!AF$11 -> 1.640606
B7: Personal allowance | C7: =Assumptions!$C$49*C$6 -> 12570 | D7: =Assumptions!$C$49*D$6 -> 12570 | E7: =Assumptions!$C$49*E$6 -> 12570 | F7: =Assumptions!$C$49*F$6 -> 12570 | G7: =Assumptions!$C$49*G$6 -> 12570 | H7: =Assumptions!$C$49*H$6 -> 12821.4 | I7: =Assumptions!$C$49*I$6 -> 13077.828 | J7: =Assumptions!$C$49*J$6 -> 13339.385 | ... AF7: =Assumptions!$C$49*AF$6 -> 20622.417
B8: Personal allowance taper starts | C8: =Assumptions!$C$50*C$6 -> 100000 | D8: =Assumptions!$C$50*D$6 -> 100000 | E8: =Assumptions!$C$50*E$6 -> 100000 | F8: =Assumptions!$C$50*F$6 -> 100000 | G8: =Assumptions!$C$50*G$6 -> 100000 | H8: =Assumptions!$C$50*H$6 -> 102000 | I8: =Assumptions!$C$50*I$6 -> 104040 | J8: =Assumptions!$C$50*J$6 -> 106120.8 | ... AF8: =Assumptions!$C$50*AF$6 -> 164060.6
B9: Basic rate limit (taxable income) | C9: =Assumptions!$C$51*C$6 -> 37700 | D9: =Assumptions!$C$51*D$6 -> 37700 | E9: =Assumptions!$C$51*E$6 -> 37700 | F9: =Assumptions!$C$51*F$6 -> 37700 | G9: =Assumptions!$C$51*G$6 -> 37700 | H9: =Assumptions!$C$51*H$6 -> 38454 | I9: =Assumptions!$C$51*I$6 -> 39223.08 | J9: =Assumptions!$C$51*J$6 -> 40007.542 | ... AF9: =Assumptions!$C$51*AF$6 -> 61850.846
B10: Additional rate threshold (taxable income) | C10: =Assumptions!$C$52*C$6 -> 125140 | D10: =Assumptions!$C$52*D$6 -> 125140 | E10: =Assumptions!$C$52*E$6 -> 125140 | F10: =Assumptions!$C$52*F$6 -> 125140 | G10: =Assumptions!$C$52*G$6 -> 125140 | H10: =Assumptions!$C$52*H$6 -> 127642.8 | I10: =Assumptions!$C$52*I$6 -> 130195.66 | J10: =Assumptions!$C$52*J$6 -> 132799.57 | ... AF10: =Assumptions!$C$52*AF$6 -> 205305.43
B11: National Insurance primary threshold | C11: =Assumptions!$C$56*C$6 -> 12570 | D11: =Assumptions!$C$56*D$6 -> 12570 | E11: =Assumptions!$C$56*E$6 -> 12570 | F11: =Assumptions!$C$56*F$6 -> 12570 | G11: =Assumptions!$C$56*G$6 -> 12570 | H11: =Assumptions!$C$56*H$6 -> 12821.4 | I11: =Assumptions!$C$56*I$6 -> 13077.828 | J11: =Assumptions!$C$56*J$6 -> 13339.385 | ... AF11: =Assumptions!$C$56*AF$6 -> 20622.417
B12: National Insurance upper earnings limit | C12: =Assumptions!$C$57*C$6 -> 50270 | D12: =Assumptions!$C$57*D$6 -> 50270 | E12: =Assumptions!$C$57*E$6 -> 50270 | F12: =Assumptions!$C$57*F$6 -> 50270 | G12: =Assumptions!$C$57*G$6 -> 50270 | H12: =Assumptions!$C$57*H$6 -> 51275.4 | I12: =Assumptions!$C$57*I$6 -> 52300.908 | J12: =Assumptions!$C$57*J$6 -> 53346.926 | ... AF12: =Assumptions!$C$57*AF$6 -> 82473.263
B13: Pension annual allowance (each) | C13: =Assumptions!$C$42*C$6 -> 60000 | D13: =Assumptions!$C$42*D$6 -> 60000 | E13: =Assumptions!$C$42*E$6 -> 60000 | F13: =Assumptions!$C$42*F$6 -> 60000 | G13: =Assumptions!$C$42*G$6 -> 60000 | H13: =Assumptions!$C$42*H$6 -> 61200 | I13: =Assumptions!$C$42*I$6 -> 62424 | J13: =Assumptions!$C$42*J$6 -> 63672.48 | ... AF13: =Assumptions!$C$42*AF$6 -> 98436.36
B14: Pension taper — adjusted income threshold | C14: =Assumptions!$C$45*C$6 -> 260000 | D14: =Assumptions!$C$45*D$6 -> 260000 | E14: =Assumptions!$C$45*E$6 -> 260000 | F14: =Assumptions!$C$45*F$6 -> 260000 | G14: =Assumptions!$C$45*G$6 -> 260000 | H14: =Assumptions!$C$45*H$6 -> 265200 | I14: =Assumptions!$C$45*I$6 -> 270504 | J14: =Assumptions!$C$45*J$6 -> 275914.08 | ... AF14: =Assumptions!$C$45*AF$6 -> 426557.56
B15: Pension taper — minimum annual allowance | C15: =Assumptions!$C$46*C$6 -> 10000 | D15: =Assumptions!$C$46*D$6 -> 10000 | E15: =Assumptions!$C$46*E$6 -> 10000 | F15: =Assumptions!$C$46*F$6 -> 10000 | G15: =Assumptions!$C$46*G$6 -> 10000 | H15: =Assumptions!$C$46*H$6 -> 10200 | I15: =Assumptions!$C$46*I$6 -> 10404 | J15: =Assumptions!$C$46*J$6 -> 10612.08 | ... AF15: =Assumptions!$C$46*AF$6 -> 16406.06
B16: ISA allowance (each) | C16: =Assumptions!$C$43*C$6 -> 20000 | D16: =Assumptions!$C$43*D$6 -> 20000 | E16: =Assumptions!$C$43*E$6 -> 20000 | F16: =Assumptions!$C$43*F$6 -> 20000 | G16: =Assumptions!$C$43*G$6 -> 20000 | H16: =Assumptions!$C$43*H$6 -> 20400 | I16: =Assumptions!$C$43*I$6 -> 20808 | J16: =Assumptions!$C$43*J$6 -> 21224.16 | ... AF16: =Assumptions!$C$43*AF$6 -> 32812.12
B17: Junior ISA allowance (per child) | C17: =Assumptions!$C$44*C$6 -> 9000 | D17: =Assumptions!$C$44*D$6 -> 9000 | E17: =Assumptions!$C$44*E$6 -> 9000 | F17: =Assumptions!$C$44*F$6 -> 9000 | G17: =Assumptions!$C$44*G$6 -> 9000 | H17: =Assumptions!$C$44*H$6 -> 9180 | I17: =Assumptions!$C$44*I$6 -> 9363.6 | J17: =Assumptions!$C$44*J$6 -> 9550.872 | ... AF17: =Assumptions!$C$44*AF$6 -> 14765.454
B18: Basic rate | C18: =Assumptions!$C$53 -> 0.2 | D18: =Assumptions!$C$53 -> 0.2 | E18: =Assumptions!$C$53 -> 0.2 | F18: =Assumptions!$C$53 -> 0.2 | G18: =Assumptions!$C$53 -> 0.2 | H18: =Assumptions!$C$53 -> 0.2 | I18: =Assumptions!$C$53 -> 0.2 | J18: =Assumptions!$C$53 -> 0.2 | ... AF18: =Assumptions!$C$53 -> 0.2
B19: Higher rate | C19: =Assumptions!$C$54 -> 0.4 | D19: =Assumptions!$C$54 -> 0.4 | E19: =Assumptions!$C$54 -> 0.4 | F19: =Assumptions!$C$54 -> 0.4 | G19: =Assumptions!$C$54 -> 0.4 | H19: =Assumptions!$C$54 -> 0.4 | I19: =Assumptions!$C$54 -> 0.4 | J19: =Assumptions!$C$54 -> 0.4 | ... AF19: =Assumptions!$C$54 -> 0.4
B20: Additional rate | C20: =Assumptions!$C$55 -> 0.45 | D20: =Assumptions!$C$55 -> 0.45 | E20: =Assumptions!$C$55 -> 0.45 | F20: =Assumptions!$C$55 -> 0.45 | G20: =Assumptions!$C$55 -> 0.45 | H20: =Assumptions!$C$55 -> 0.45 | I20: =Assumptions!$C$55 -> 0.45 | J20: =Assumptions!$C$55 -> 0.45 | ... AF20: =Assumptions!$C$55 -> 0.45
B21: NI main rate | C21: =Assumptions!$C$58 -> 0.08 | D21: =Assumptions!$C$58 -> 0.08 | E21: =Assumptions!$C$58 -> 0.08 | F21: =Assumptions!$C$58 -> 0.08 | G21: =Assumptions!$C$58 -> 0.08 | H21: =Assumptions!$C$58 -> 0.08 | I21: =Assumptions!$C$58 -> 0.08 | J21: =Assumptions!$C$58 -> 0.08 | ... AF21: =Assumptions!$C$58 -> 0.08
B22: NI upper rate | C22: =Assumptions!$C$59 -> 0.02 | D22: =Assumptions!$C$59 -> 0.02 | E22: =Assumptions!$C$59 -> 0.02 | F22: =Assumptions!$C$59 -> 0.02 | G22: =Assumptions!$C$59 -> 0.02 | H22: =Assumptions!$C$59 -> 0.02 | I22: =Assumptions!$C$59 -> 0.02 | J22: =Assumptions!$C$59 -> 0.02 | ... AF22: =Assumptions!$C$59 -> 0.02

Sheet Returns
A1: INVESTMENT RETURNS — THE AGE GLIDEPATH
A2: Junior ISAs earn a flat 8%. Every other pot follows the glidepath you specified: 8% until age 50, falling in a straight line to 2% at age 70. The joint ISA uses the AVERAGE of MM's and DM's ages because it is joint money; each pension uses its own owner's age.
A4: RATES BY YEAR
B5: Year | C5: 2026 | D5: 2027 | E5: 2028 | F5: 2029 | G5: 2030 | H5: 2031 | I5: 2032 | J5: 2033 | K5: 2034 | L5: 2035 | M5: 2036 | N5: 2037 | O5: 2038 | P5: 2039 | Q5: 2040 | R5: 2041 | S5: 2042 | T5: 2043 | U5: 2044 | V5: 2045 | W5: 2046 | X5: 2047 | Y5: 2048 | Z5: 2049 | AA5: 2050 | AB5: 2051 | AC5: 2052 | AD5: 2053 | AE5: 2054 | AF5: 2055
B6: MM age | C6: =Assumptions!C$12 -> 35 | D6: =Assumptions!D$12 -> 36 | E6: =Assumptions!E$12 -> 37 | F6: =Assumptions!F$12 -> 38 | G6: =Assumptions!G$12 -> 39 | H6: =Assumptions!H$12 -> 40 | I6: =Assumptions!I$12 -> 41 | J6: =Assumptions!J$12 -> 42 | ... AF6: =Assumptions!AF$12 -> 64
B7: DM age | C7: =Assumptions!C$13 -> 44 | D7: =Assumptions!D$13 -> 45 | E7: =Assumptions!E$13 -> 46 | F7: =Assumptions!F$13 -> 47 | G7: =Assumptions!G$13 -> 48 | H7: =Assumptions!H$13 -> 49 | I7: =Assumptions!I$13 -> 50 | J7: =Assumptions!J$13 -> 51 | ... AF7: =Assumptions!AF$13 -> 73
B8: Average age | C8: =Assumptions!C$14 -> 39.5 | D8: =Assumptions!D$14 -> 40.5 | E8: =Assumptions!E$14 -> 41.5 | F8: =Assumptions!F$14 -> 42.5 | G8: =Assumptions!G$14 -> 43.5 | H8: =Assumptions!H$14 -> 44.5 | I8: =Assumptions!I$14 -> 45.5 | J8: =Assumptions!J$14 -> 46.5 | ... AF8: =Assumptions!AF$14 -> 68.5
B9: MM pension return | C9: =IF(Assumptions!$C$39=1,MIN(Assumptions!$C$33,MAX(Assumptions!$C$35,Assumptions!$C$33-(Assumptions!$C$33-Assumptions!$C$35)*(C6-Assumptions!$C$34)/(Assumptions!$C$36-Assumptions!$C$34))),Assumptions!$C$33) -> 0.08 | D9: =IF(Assumptions!$C$39=1,MIN(Assumptions!$C$33,MAX(Assumptions!$C$35,Assumptions!$C$33-(Assumptions!$C$33-Assumptions!$C$35)*(D6-Assumptions!$C$34)/(Assumptions!$C$36-Assumptions!$C$34))),Assumptions!$C$33) -> 0.08 | E9: =IF(Assumptions!$C$39=1,MIN(Assumptions!$C$33,MAX(Assumptions!$C$35,Assumptions!$C$33-(Assumptions!$C$33-Assumptions!$C$35)*(E6-Assumptions!$C$34)/(Assumptions!$C$36-Assumptions!$C$34))),Assumptions!$C$33) -> 0.08 | F9: =IF(Assumptions!$C$39=1,MIN(Assumptions!$C$33,MAX(Assumptions!$C$35,Assumptions!$C$33-(Assumptions!$C$33-Assumptions!$C$35)*(F6-Assumptions!$C$34)/(Assumptions!$C$36-Assumptions!$C$34))),Assumptions!$C$33) -> 0.08 | G9: =IF(Assumptions!$C$39=1,MIN(Assumptions!$C$33,MAX(Assumptions!$C$35,Assumptions!$C$33-(Assumptions!$C$33-Assumptions!$C$35)*(G6-Assumptions!$C$34)/(Assumptions!$C$36-Assumptions!$C$34))),Assumptions!$C$33) -> 0.08 | H9: =IF(Assumptions!$C$39=1,MIN(Assumptions!$C$33,MAX(Assumptions!$C$35,Assumptions!$C$33-(Assumptions!$C$33-Assumptions!$C$35)*(H6-Assumptions!$C$34)/(Assumptions!$C$36-Assumptions!$C$34))),Assumptions!$C$33) -> 0.08 | I9: =IF(Assumptions!$C$39=1,MIN(Assumptions!$C$33,MAX(Assumptions!$C$35,Assumptions!$C$33-(Assumptions!$C$33-Assumptions!$C$35)*(I6-Assumptions!$C$34)/(Assumptions!$C$36-Assumptions!$C$34))),Assumptions!$C$33) -> 0.08 | J9: =IF(Assumptions!$C$39=1,MIN(Assumptions!$C$33,MAX(Assumptions!$C$35,Assumptions!$C$33-(Assumptions!$C$33-Assumptions!$C$35)*(J6-Assumptions!$C$34)/(Assumptions!$C$36-Assumptions!$C$34))),Assumptions!$C$33) -> 0.08 | ... AF9: =IF(Assumptions!$C$39=1,MIN(Assumptions!$C$33,MAX(Assumptions!$C$35,Assumptions!$C$33-(Assumptions!$C$33-Assumptions!$C$35)*(AF6-Assumptions!$C$34)/(Assumptions!$C$36-Assumptions!$C$34))),Assumptions!$C$33) -> 0.038
B10: DM pension return | C10: =IF(Assumptions!$C$39=1,MIN(Assumptions!$C$33,MAX(Assumptions!$C$35,Assumptions!$C$33-(Assumptions!$C$33-Assumptions!$C$35)*(C7-Assumptions!$C$34)/(Assumptions!$C$36-Assumptions!$C$34))),Assumptions!$C$33) -> 0.08 | D10: =IF(Assumptions!$C$39=1,MIN(Assumptions!$C$33,MAX(Assumptions!$C$35,Assumptions!$C$33-(Assumptions!$C$33-Assumptions!$C$35)*(D7-Assumptions!$C$34)/(Assumptions!$C$36-Assumptions!$C$34))),Assumptions!$C$33) -> 0.08 | E10: =IF(Assumptions!$C$39=1,MIN(Assumptions!$C$33,MAX(Assumptions!$C$35,Assumptions!$C$33-(Assumptions!$C$33-Assumptions!$C$35)*(E7-Assumptions!$C$34)/(Assumptions!$C$36-Assumptions!$C$34))),Assumptions!$C$33) -> 0.08 | F10: =IF(Assumptions!$C$39=1,MIN(Assumptions!$C$33,MAX(Assumptions!$C$35,Assumptions!$C$33-(Assumptions!$C$33-Assumptions!$C$35)*(F7-Assumptions!$C$34)/(Assumptions!$C$36-Assumptions!$C$34))),Assumptions!$C$33) -> 0.08 | G10: =IF(Assumptions!$C$39=1,MIN(Assumptions!$C$33,MAX(Assumptions!$C$35,Assumptions!$C$33-(Assumptions!$C$33-Assumptions!$C$35)*(G7-Assumptions!$C$34)/(Assumptions!$C$36-Assumptions!$C$34))),Assumptions!$C$33) -> 0.08 | H10: =IF(Assumptions!$C$39=1,MIN(Assumptions!$C$33,MAX(Assumptions!$C$35,Assumptions!$C$33-(Assumptions!$C$33-Assumptions!$C$35)*(H7-Assumptions!$C$34)/(Assumptions!$C$36-Assumptions!$C$34))),Assumptions!$C$33) -> 0.08 | I10: =IF(Assumptions!$C$39=1,MIN(Assumptions!$C$33,MAX(Assumptions!$C$35,Assumptions!$C$33-(Assumptions!$C$33-Assumptions!$C$35)*(I7-Assumptions!$C$34)/(Assumptions!$C$36-Assumptions!$C$34))),Assumptions!$C$33) -> 0.08 | J10: =IF(Assumptions!$C$39=1,MIN(Assumptions!$C$33,MAX(Assumptions!$C$35,Assumptions!$C$33-(Assumptions!$C$33-Assumptions!$C$35)*(J7-Assumptions!$C$34)/(Assumptions!$C$36-Assumptions!$C$34))),Assumptions!$C$33) -> 0.077 | ... AF10: =IF(Assumptions!$C$39=1,MIN(Assumptions!$C$33,MAX(Assumptions!$C$35,Assumptions!$C$33-(Assumptions!$C$33-Assumptions!$C$35)*(AF7-Assumptions!$C$34)/(Assumptions!$C$36-Assumptions!$C$34))),Assumptions!$C$33) -> 0.02
B11: Joint ISA return | C11: =MIN(Assumptions!$C$33,MAX(Assumptions!$C$35,Assumptions!$C$33-(Assumptions!$C$33-Assumptions!$C$35)*(C8-Assumptions!$C$34)/(Assumptions!$C$36-Assumptions!$C$34))) -> 0.08 | D11: =MIN(Assumptions!$C$33,MAX(Assumptions!$C$35,Assumptions!$C$33-(Assumptions!$C$33-Assumptions!$C$35)*(D8-Assumptions!$C$34)/(Assumptions!$C$36-Assumptions!$C$34))) -> 0.08 | E11: =MIN(Assumptions!$C$33,MAX(Assumptions!$C$35,Assumptions!$C$33-(Assumptions!$C$33-Assumptions!$C$35)*(E8-Assumptions!$C$34)/(Assumptions!$C$36-Assumptions!$C$34))) -> 0.08 | F11: =MIN(Assumptions!$C$33,MAX(Assumptions!$C$35,Assumptions!$C$33-(Assumptions!$C$33-Assumptions!$C$35)*(F8-Assumptions!$C$34)/(Assumptions!$C$36-Assumptions!$C$34))) -> 0.08 | G11: =MIN(Assumptions!$C$33,MAX(Assumptions!$C$35,Assumptions!$C$33-(Assumptions!$C$33-Assumptions!$C$35)*(G8-Assumptions!$C$34)/(Assumptions!$C$36-Assumptions!$C$34))) -> 0.08 | H11: =MIN(Assumptions!$C$33,MAX(Assumptions!$C$35,Assumptions!$C$33-(Assumptions!$C$33-Assumptions!$C$35)*(H8-Assumptions!$C$34)/(Assumptions!$C$36-Assumptions!$C$34))) -> 0.08 | I11: =MIN(Assumptions!$C$33,MAX(Assumptions!$C$35,Assumptions!$C$33-(Assumptions!$C$33-Assumptions!$C$35)*(I8-Assumptions!$C$34)/(Assumptions!$C$36-Assumptions!$C$34))) -> 0.08 | J11: =MIN(Assumptions!$C$33,MAX(Assumptions!$C$35,Assumptions!$C$33-(Assumptions!$C$33-Assumptions!$C$35)*(J8-Assumptions!$C$34)/(Assumptions!$C$36-Assumptions!$C$34))) -> 0.08 | ... AF11: =MIN(Assumptions!$C$33,MAX(Assumptions!$C$35,Assumptions!$C$33-(Assumptions!$C$33-Assumptions!$C$35)*(AF8-Assumptions!$C$34)/(Assumptions!$C$36-Assumptions!$C$34))) -> 0.0245
B12: Taxable (non-ISA) savings return | C12: =MAX(Assumptions!$C$38,C11-Assumptions!$C$37) -> 0.065 | D12: =MAX(Assumptions!$C$38,D11-Assumptions!$C$37) -> 0.065 | E12: =MAX(Assumptions!$C$38,E11-Assumptions!$C$37) -> 0.065 | F12: =MAX(Assumptions!$C$38,F11-Assumptions!$C$37) -> 0.065 | G12: =MAX(Assumptions!$C$38,G11-Assumptions!$C$37) -> 0.065 | H12: =MAX(Assumptions!$C$38,H11-Assumptions!$C$37) -> 0.065 | I12: =MAX(Assumptions!$C$38,I11-Assumptions!$C$37) -> 0.065 | J12: =MAX(Assumptions!$C$38,J11-Assumptions!$C$37) -> 0.065 | ... AF12: =MAX(Assumptions!$C$38,AF11-Assumptions!$C$37) -> 0.0095
B13: Junior ISA return | C13: =Assumptions!$C$32 -> 0.08 | D13: =Assumptions!$C$32 -> 0.08 | E13: =Assumptions!$C$32 -> 0.08 | F13: =Assumptions!$C$32 -> 0.08 | G13: =Assumptions!$C$32 -> 0.08 | H13: =Assumptions!$C$32 -> 0.08 | I13: =Assumptions!$C$32 -> 0.08 | J13: =Assumptions!$C$32 -> 0.08 | ... AF13: =Assumptions!$C$32 -> 0.08
A15: CUMULATIVE GROWTH FACTORS (used by the DM-exit sweep)
B16: Cumulative growth factor — MM pension | C16: =(1+C9) -> 1.08 | D16: =C16*(1+D9) -> 1.1664 | E16: =D16*(1+E9) -> 1.259712 | F16: =E16*(1+F9) -> 1.360489 | G16: =F16*(1+G9) -> 1.4693281 | H16: =G16*(1+H9) -> 1.5868743 | I16: =H16*(1+I9) -> 1.7138243 | J16: =I16*(1+J9) -> 1.8509302 | K16: =J16*(1+K9) -> 1.9990046 | ... AF16: =AE16*(1+AF9) -> 7.4869983
B17: Cumulative growth factor — DM pension | C17: =(1+C10) -> 1.08 | D17: =C17*(1+D10) -> 1.1664 | E17: =D17*(1+E10) -> 1.259712 | F17: =E17*(1+F10) -> 1.360489 | G17: =F17*(1+G10) -> 1.4693281 | H17: =G17*(1+H10) -> 1.5868743 | I17: =H17*(1+I10) -> 1.7138243 | J17: =I17*(1+J10) -> 1.8457887 | K17: =J17*(1+K10) -> 1.9823771 | ... AF17: =AE17*(1+AF10) -> 4.6768456
B18: Cumulative growth factor — Joint liquid savings | C18: =(1+C11) -> 1.08 | D18: =C18*(1+D11) -> 1.1664 | E18: =D18*(1+E11) -> 1.259712 | F18: =E18*(1+F11) -> 1.360489 | G18: =F18*(1+G11) -> 1.4693281 | H18: =G18*(1+H11) -> 1.5868743 | I18: =H18*(1+I11) -> 1.7138243 | J18: =I18*(1+J11) -> 1.8509302 | K18: =J18*(1+K11) -> 1.9990046 | ... AF18: =AE18*(1+AF11) -> 6.0399012
B20: MM workplace pension input (employee + employer) | C20: =MM_Income!C$12 -> 21000 | D20: =MM_Income!D$12 -> 23100 | E20: =MM_Income!E$12 -> 24024 | F20: =MM_Income!F$12 -> 24504.48 | G20: =MM_Income!G$12 -> 24994.57 | H20: =MM_Income!H$12 -> 25494.461 | I20: =MM_Income!I$12 -> 26004.35 | J20: =MM_Income!J$12 -> 26524.437 | ... AF20: =MM_Income!AF$12 -> 41006.241
B21: MM workplace input divided by the cumulative factor | C21: =C20/C16 -> 19444.444 | D21: =D20/D16 -> 19804.527 | E21: =E20/E16 -> 19071.026 | F21: =F20/F16 -> 18011.524 | G21: =G20/G16 -> 17010.884 | H21: =H20/H16 -> 16065.835 | I21: =I20/I16 -> 15173.289 | J21: =J20/J16 -> 14330.328 | ... AF21: =AF20/AF16 -> 5476.9935
B22: Running total of the row above | C22: =C21 -> 19444.444 | D22: =C22+D21 -> 39248.971 | E22: =D22+E21 -> 58319.997 | F22: =E22+F21 -> 76331.521 | G22: =F22+G21 -> 93342.405 | H22: =G22+H21 -> 109408.24 | I22: =H22+I21 -> 124581.53 | J22: =I22+J21 -> 138911.86 | K22: =J22+K21 -> 152446.06 | ... AF22: =AE22+AF21 -> 321809.41

Sheet MM_Income
A1: MM — INCOME, TAX, PENSION CONTRIBUTIONS AND BALANCE
A2: Workplace pension: NET PAY arrangement — the employee contribution reduces taxable pay but not National Insurance; the employer contribution is not taxable but does count towards the £60,000 annual allowance. Personal SIPP: RELIEF AT SOURCE — HMRC adds 20%, so £1 of gross costs 80p of cash, and the tax bands are extended by the gross contribution to give higher and additional-rate relief.
A4: MM — PAY AND PENSION INPUTS
B5: Year | C5: 2026 | D5: 2027 | E5: 2028 | F5: 2029 | G5: 2030 | H5: 2031 | I5: 2032 | J5: 2033 | K5: 2034 | L5: 2035 | M5: 2036 | N5: 2037 | O5: 2038 | P5: 2039 | Q5: 2040 | R5: 2041 | S5: 2042 | T5: 2043 | U5: 2044 | V5: 2045 | W5: 2046 | X5: 2047 | Y5: 2048 | Z5: 2049 | AA5: 2050 | AB5: 2051 | AC5: 2052 | AD5: 2053 | AE5: 2054 | AF5: 2055
B6: Age at 31 December | C6: =Assumptions!C$12 -> 35 | D6: =Assumptions!D$12 -> 36 | E6: =Assumptions!E$12 -> 37 | F6: =Assumptions!F$12 -> 38 | G6: =Assumptions!G$12 -> 39 | H6: =Assumptions!H$12 -> 40 | I6: =Assumptions!I$12 -> 41 | J6: =Assumptions!J$12 -> 42 | ... AF6: =Assumptions!AF$12 -> 64
B8: Total gross income | C8: =Assumptions!$C$21*Assumptions!C$9 -> 170000 | D8: =Assumptions!$C$21*Assumptions!D$9 -> 176800 | E8: =Assumptions!$C$21*Assumptions!E$9 -> 183872 | F8: =Assumptions!$C$21*Assumptions!F$9 -> 187549.44 | G8: =Assumptions!$C$21*Assumptions!G$9 -> 191300.43 | H8: =Assumptions!$C$21*Assumptions!H$9 -> 195126.44 | I8: =Assumptions!$C$21*Assumptions!I$9 -> 199028.97 | J8: =Assumptions!$C$21*Assumptions!J$9 -> 203009.55 | ... AF8: =Assumptions!$C$21*Assumptions!AF$9 -> 313848.63
B9: Base salary | C9: =Assumptions!$C$22 -> 100000 | D9: =IF(Assumptions!$C$23>0,Assumptions!$C$23*Assumptions!D$9/Assumptions!$D$9,Assumptions!$C$22*Assumptions!D$9) -> 110000 | E9: =IF(Assumptions!$C$23>0,Assumptions!$C$23*Assumptions!E$9/Assumptions!$D$9,Assumptions!$C$22*Assumptions!E$9) -> 114400 | F9: =IF(Assumptions!$C$23>0,Assumptions!$C$23*Assumptions!F$9/Assumptions!$D$9,Assumptions!$C$22*Assumptions!F$9) -> 116688 | G9: =IF(Assumptions!$C$23>0,Assumptions!$C$23*Assumptions!G$9/Assumptions!$D$9,Assumptions!$C$22*Assumptions!G$9) -> 119021.76 | H9: =IF(Assumptions!$C$23>0,Assumptions!$C$23*Assumptions!H$9/Assumptions!$D$9,Assumptions!$C$22*Assumptions!H$9) -> 121402.2 | I9: =IF(Assumptions!$C$23>0,Assumptions!$C$23*Assumptions!I$9/Assumptions!$D$9,Assumptions!$C$22*Assumptions!I$9) -> 123830.24 | J9: =IF(Assumptions!$C$23>0,Assumptions!$C$23*Assumptions!J$9/Assumptions!$D$9,Assumptions!$C$22*Assumptions!J$9) -> 126306.84 | K9: =IF(Assumptions!$C$23>0,Assumptions!$C$23*Assumptions!K$9/Assumptions!$D$9,Assumptions!$C$22*Assumptions!K$9) -> 128832.98 | ... AF9: =IF(Assumptions!$C$23>0,Assumptions!$C$23*Assumptions!AF$9/Assumptions!$D$9,Assumptions!$C$22*Assumptions!AF$9) -> 195267.81
B10: Employee workplace pension contribution | C10: =C9*Assumptions!$C$28 -> 7000 | D10: =D9*Assumptions!$C$28 -> 7700 | E10: =E9*Assumptions!$C$28 -> 8008 | F10: =F9*Assumptions!$C$28 -> 8168.16 | G10: =G9*Assumptions!$C$28 -> 8331.5232 | H10: =H9*Assumptions!$C$28 -> 8498.1537 | I10: =I9*Assumptions!$C$28 -> 8668.1167 | J10: =J9*Assumptions!$C$28 -> 8841.4791 | ... AF10: =AF9*Assumptions!$C$28 -> 13668.747
B11: Employer workplace pension contribution | C11: =C9*Assumptions!$C$29 -> 14000 | D11: =D9*Assumptions!$C$29 -> 15400 | E11: =E9*Assumptions!$C$29 -> 16016 | F11: =F9*Assumptions!$C$29 -> 16336.32 | G11: =G9*Assumptions!$C$29 -> 16663.046 | H11: =H9*Assumptions!$C$29 -> 16996.307 | I11: =I9*Assumptions!$C$29 -> 17336.233 | J11: =J9*Assumptions!$C$29 -> 17682.958 | ... AF11: =AF9*Assumptions!$C$29 -> 27337.494
B12: Total workplace pension input | C12: =C10+C11 -> 21000 | D12: =D10+D11 -> 23100 | E12: =E10+E11 -> 24024 | F12: =F10+F11 -> 24504.48 | G12: =G10+G11 -> 24994.57 | H12: =H10+H11 -> 25494.461 | I12: =I10+I11 -> 26004.35 | J12: =J10+J11 -> 26524.437 | ... AF12: =AF10+AF11 -> 41006.241
B13: Adjusted income (for the annual allowance taper) | C13: =C8+C11 -> 184000 | D13: =D8+D11 -> 192200 | E13: =E8+E11 -> 199888 | F13: =F8+F11 -> 203885.76 | G13: =G8+G11 -> 207963.48 | H13: =H8+H11 -> 212122.74 | I13: =I8+I11 -> 216365.2 | J13: =J8+J11 -> 220692.5 | ... AF13: =AF8+AF11 -> 341186.12
B14: Annual allowance available after any taper | C14: =MAX(Tax_Bands!C$15,Tax_Bands!C$13-MAX(0,C13-Tax_Bands!C$14)/2) -> 60000 | D14: =MAX(Tax_Bands!D$15,Tax_Bands!D$13-MAX(0,D13-Tax_Bands!D$14)/2) -> 60000 | E14: =MAX(Tax_Bands!E$15,Tax_Bands!E$13-MAX(0,E13-Tax_Bands!E$14)/2) -> 60000 | F14: =MAX(Tax_Bands!F$15,Tax_Bands!F$13-MAX(0,F13-Tax_Bands!F$14)/2) -> 60000 | G14: =MAX(Tax_Bands!G$15,Tax_Bands!G$13-MAX(0,G13-Tax_Bands!G$14)/2) -> 60000 | H14: =MAX(Tax_Bands!H$15,Tax_Bands!H$13-MAX(0,H13-Tax_Bands!H$14)/2) -> 61200 | I14: =MAX(Tax_Bands!I$15,Tax_Bands!I$13-MAX(0,I13-Tax_Bands!I$14)/2) -> 62424 | J14: =MAX(Tax_Bands!J$15,Tax_Bands!J$13-MAX(0,J13-Tax_Bands!J$14)/2) -> 63672.48 | ... AF14: =MAX(Tax_Bands!AF$15,Tax_Bands!AF$13-MAX(0,AF13-Tax_Bands!AF$14)/2) -> 98436.36
B15: SIPP HEADROOM (allowance less workplace contributions) | C15: =MAX(0,MIN(C14-C12,C8-C10)) -> 39000 | D15: =MAX(0,MIN(D14-D12,D8-D10)) -> 36900 | E15: =MAX(0,MIN(E14-E12,E8-E10)) -> 35976 | F15: =MAX(0,MIN(F14-F12,F8-F10)) -> 35495.52 | G15: =MAX(0,MIN(G14-G12,G8-G10)) -> 35005.43 | H15: =MAX(0,MIN(H14-H12,H8-H10)) -> 35705.539 | I15: =MAX(0,MIN(I14-I12,I8-I10)) -> 36419.65 | J15: =MAX(0,MIN(J14-J12,J8-J10)) -> 37148.043 | ... AF15: =MAX(0,MIN(AF14-AF12,AF8-AF10)) -> 57430.119
A16: MM — TAX BEFORE ANY PERSONAL SIPP CONTRIBUTION
B17: Taxable pay (income less the employee workplace contribution) | C17: =C8-C10 -> 163000 | D17: =D8-D10 -> 169100 | E17: =E8-E10 -> 175864 | F17: =F8-F10 -> 179381.28 | G17: =G8-G10 -> 182968.91 | H17: =H8-H10 -> 186628.28 | I17: =I8-I10 -> 190360.85 | J17: =J8-J10 -> 194168.07 | ... AF17: =AF8-AF10 -> 300179.88
B18: Personal allowance after taper | C18: =MAX(0,Tax_Bands!C$7-MAX(0,C17-Tax_Bands!C$8)/2) -> 0 | D18: =MAX(0,Tax_Bands!D$7-MAX(0,D17-Tax_Bands!D$8)/2) -> 0 | E18: =MAX(0,Tax_Bands!E$7-MAX(0,E17-Tax_Bands!E$8)/2) -> 0 | F18: =MAX(0,Tax_Bands!F$7-MAX(0,F17-Tax_Bands!F$8)/2) -> 0 | G18: =MAX(0,Tax_Bands!G$7-MAX(0,G17-Tax_Bands!G$8)/2) -> 0 | H18: =MAX(0,Tax_Bands!H$7-MAX(0,H17-Tax_Bands!H$8)/2) -> 0 | I18: =MAX(0,Tax_Bands!I$7-MAX(0,I17-Tax_Bands!I$8)/2) -> 0 | J18: =MAX(0,Tax_Bands!J$7-MAX(0,J17-Tax_Bands!J$8)/2) -> 0 | ... AF18: =MAX(0,Tax_Bands!AF$7-MAX(0,AF17-Tax_Bands!AF$8)/2) -> 0
B19: Taxable income | C19: =MAX(0,C17-C18) -> 163000 | D19: =MAX(0,D17-D18) -> 169100 | E19: =MAX(0,E17-E18) -> 175864 | F19: =MAX(0,F17-F18) -> 179381.28 | G19: =MAX(0,G17-G18) -> 182968.91 | H19: =MAX(0,H17-H18) -> 186628.28 | I19: =MAX(0,I17-I18) -> 190360.85 | J19: =MAX(0,J17-J18) -> 194168.07 | ... AF19: =MAX(0,AF17-AF18) -> 300179.88
B20: Income tax | C20: =Tax_Bands!C$18*MIN(C19,Tax_Bands!C$9)+Tax_Bands!C$19*MAX(0,MIN(C19,Tax_Bands!C$10)-Tax_Bands!C$9)+Tax_Bands!C$20*MAX(0,C19-Tax_Bands!C$10) -> 59553 | D20: =Tax_Bands!D$18*MIN(D19,Tax_Bands!D$9)+Tax_Bands!D$19*MAX(0,MIN(D19,Tax_Bands!D$10)-Tax_Bands!D$9)+Tax_Bands!D$20*MAX(0,D19-Tax_Bands!D$10) -> 62298 | E20: =Tax_Bands!E$18*MIN(E19,Tax_Bands!E$9)+Tax_Bands!E$19*MAX(0,MIN(E19,Tax_Bands!E$10)-Tax_Bands!E$9)+Tax_Bands!E$20*MAX(0,E19-Tax_Bands!E$10) -> 65341.8 | F20: =Tax_Bands!F$18*MIN(F19,Tax_Bands!F$9)+Tax_Bands!F$19*MAX(0,MIN(F19,Tax_Bands!F$10)-Tax_Bands!F$9)+Tax_Bands!F$20*MAX(0,F19-Tax_Bands!F$10) -> 66924.576 | G20: =Tax_Bands!G$18*MIN(G19,Tax_Bands!G$9)+Tax_Bands!G$19*MAX(0,MIN(G19,Tax_Bands!G$10)-Tax_Bands!G$9)+Tax_Bands!G$20*MAX(0,G19-Tax_Bands!G$10) -> 68539.008 | H20: =Tax_Bands!H$18*MIN(H19,Tax_Bands!H$9)+Tax_Bands!H$19*MAX(0,MIN(H19,Tax_Bands!H$10)-Tax_Bands!H$9)+Tax_Bands!H$20*MAX(0,H19-Tax_Bands!H$10) -> 69909.788 | I20: =Tax_Bands!I$18*MIN(I19,Tax_Bands!I$9)+Tax_Bands!I$19*MAX(0,MIN(I19,Tax_Bands!I$10)-Tax_Bands!I$9)+Tax_Bands!I$20*MAX(0,I19-Tax_Bands!I$10) -> 71307.983 | J20: =Tax_Bands!J$18*MIN(J19,Tax_Bands!J$9)+Tax_Bands!J$19*MAX(0,MIN(J19,Tax_Bands!J$10)-Tax_Bands!J$9)+Tax_Bands!J$20*MAX(0,J19-Tax_Bands!J$10) -> 72734.143 | ... AF20: =Tax_Bands!AF$18*MIN(AF19,Tax_Bands!AF$9)+Tax_Bands!AF$19*MAX(0,MIN(AF19,Tax_Bands!AF$10)-Tax_Bands!AF$9)+Tax_Bands!AF$20*MAX(0,AF19-Tax_Bands!AF$10) -> 112445.51
B21: Employee National Insurance | C21: =Tax_Bands!C$21*MAX(0,MIN(C8,Tax_Bands!C$12)-Tax_Bands!C$11)+Tax_Bands!C$22*MAX(0,C8-Tax_Bands!C$12) -> 5410.6 | D21: =Tax_Bands!D$21*MAX(0,MIN(D8,Tax_Bands!D$12)-Tax_Bands!D$11)+Tax_Bands!D$22*MAX(0,D8-Tax_Bands!D$12) -> 5546.6 | E21: =Tax_Bands!E$21*MAX(0,MIN(E8,Tax_Bands!E$12)-Tax_Bands!E$11)+Tax_Bands!E$22*MAX(0,E8-Tax_Bands!E$12) -> 5688.04 | F21: =Tax_Bands!F$21*MAX(0,MIN(F8,Tax_Bands!F$12)-Tax_Bands!F$11)+Tax_Bands!F$22*MAX(0,F8-Tax_Bands!F$12) -> 5761.5888 | G21: =Tax_Bands!G$21*MAX(0,MIN(G8,Tax_Bands!G$12)-Tax_Bands!G$11)+Tax_Bands!G$22*MAX(0,G8-Tax_Bands!G$12) -> 5836.6086 | H21: =Tax_Bands!H$21*MAX(0,MIN(H8,Tax_Bands!H$12)-Tax_Bands!H$11)+Tax_Bands!H$22*MAX(0,H8-Tax_Bands!H$12) -> 5953.3407 | I21: =Tax_Bands!I$21*MAX(0,MIN(I8,Tax_Bands!I$12)-Tax_Bands!I$11)+Tax_Bands!I$22*MAX(0,I8-Tax_Bands!I$12) -> 6072.4076 | J21: =Tax_Bands!J$21*MAX(0,MIN(J8,Tax_Bands!J$12)-Tax_Bands!J$11)+Tax_Bands!J$22*MAX(0,J8-Tax_Bands!J$12) -> 6193.8557 | ... AF21: =Tax_Bands!AF$21*MAX(0,MIN(AF8,Tax_Bands!AF$12)-Tax_Bands!AF$11)+Tax_Bands!AF$22*MAX(0,AF8-Tax_Bands!AF$12) -> 9575.575
B22: NET PAY (cash in hand before any personal SIPP contribution) | C22: =C17-C20-C21 -> 98036.4 | D22: =D17-D20-D21 -> 101255.4 | E22: =E17-E20-E21 -> 104834.16 | F22: =F17-F20-F21 -> 106695.12 | G22: =G17-G20-G21 -> 108593.29 | H22: =H17-H20-H21 -> 110765.16 | I22: =I17-I20-I21 -> 112980.46 | J22: =J17-J20-J21 -> 115240.07 | ... AF22: =AF17-AF20-AF21 -> 178158.8
A23: MM — WITH THE PERSONAL SIPP CONTRIBUTION ACTUALLY AFFORDED
B24: Personal SIPP contribution (gross) | C24: =Household_Base!C$37 -> 39000 | D24: =Household_Base!D$37 -> 36900 | E24: =Household_Base!E$37 -> 35976 | F24: =Household_Base!F$37 -> 35495.52 | G24: =Household_Base!G$37 -> 35005.43 | H24: =Household_Base!H$37 -> 35705.539 | I24: =Household_Base!I$37 -> 36419.65 | J24: =Household_Base!J$37 -> 37148.043 | ... AF24: =Household_Base!AF$37 -> 57430.119
B25: Adjusted net income | C25: =C17-C24 -> 124000 | D25: =D17-D24 -> 132200 | E25: =E17-E24 -> 139888 | F25: =F17-F24 -> 143885.76 | G25: =G17-G24 -> 147963.48 | H25: =H17-H24 -> 150922.74 | I25: =I17-I24 -> 153941.2 | J25: =J17-J24 -> 157020.02 | ... AF25: =AF17-AF24 -> 242749.76
B26: Personal allowance after taper | C26: =MAX(0,Tax_Bands!C$7-MAX(0,C25-Tax_Bands!C$8)/2) -> 570 | D26: =MAX(0,Tax_Bands!D$7-MAX(0,D25-Tax_Bands!D$8)/2) -> 0 | E26: =MAX(0,Tax_Bands!E$7-MAX(0,E25-Tax_Bands!E$8)/2) -> 0 | F26: =MAX(0,Tax_Bands!F$7-MAX(0,F25-Tax_Bands!F$8)/2) -> 0 | G26: =MAX(0,Tax_Bands!G$7-MAX(0,G25-Tax_Bands!G$8)/2) -> 0 | H26: =MAX(0,Tax_Bands!H$7-MAX(0,H25-Tax_Bands!H$8)/2) -> 0 | I26: =MAX(0,Tax_Bands!I$7-MAX(0,I25-Tax_Bands!I$8)/2) -> 0 | J26: =MAX(0,Tax_Bands!J$7-MAX(0,J25-Tax_Bands!J$8)/2) -> 0 | ... AF26: =MAX(0,Tax_Bands!AF$7-MAX(0,AF25-Tax_Bands!AF$8)/2) -> 0
B27: Taxable income | C27: =MAX(0,C17-C26) -> 162430 | D27: =MAX(0,D17-D26) -> 169100 | E27: =MAX(0,E17-E26) -> 175864 | F27: =MAX(0,F17-F26) -> 179381.28 | G27: =MAX(0,G17-G26) -> 182968.91 | H27: =MAX(0,H17-H26) -> 186628.28 | I27: =MAX(0,I17-I26) -> 190360.85 | J27: =MAX(0,J17-J26) -> 194168.07 | ... AF27: =MAX(0,AF17-AF26) -> 300179.88
B28: Income tax | C28: =Tax_Bands!C$18*MIN(C27,Tax_Bands!C$9+C24)+Tax_Bands!C$19*MAX(0,MIN(C27,Tax_Bands!C$10+C24)-(Tax_Bands!C$9+C24))+Tax_Bands!C$20*MAX(0,C27-(Tax_Bands!C$10+C24)) -> 49632 | D28: =Tax_Bands!D$18*MIN(D27,Tax_Bands!D$9+D24)+Tax_Bands!D$19*MAX(0,MIN(D27,Tax_Bands!D$10+D24)-(Tax_Bands!D$9+D24))+Tax_Bands!D$20*MAX(0,D27-(Tax_Bands!D$10+D24)) -> 53073 | E28: =Tax_Bands!E$18*MIN(E27,Tax_Bands!E$9+E24)+Tax_Bands!E$19*MAX(0,MIN(E27,Tax_Bands!E$10+E24)-(Tax_Bands!E$9+E24))+Tax_Bands!E$20*MAX(0,E27-(Tax_Bands!E$10+E24)) -> 56347.8 | F28: =Tax_Bands!F$18*MIN(F27,Tax_Bands!F$9+F24)+Tax_Bands!F$19*MAX(0,MIN(F27,Tax_Bands!F$10+F24)-(Tax_Bands!F$9+F24))+Tax_Bands!F$20*MAX(0,F27-(Tax_Bands!F$10+F24)) -> 58050.696 | G28: =Tax_Bands!G$18*MIN(G27,Tax_Bands!G$9+G24)+Tax_Bands!G$19*MAX(0,MIN(G27,Tax_Bands!G$10+G24)-(Tax_Bands!G$9+G24))+Tax_Bands!G$20*MAX(0,G27-(Tax_Bands!G$10+G24)) -> 59787.65 | H28: =Tax_Bands!H$18*MIN(H27,Tax_Bands!H$9+H24)+Tax_Bands!H$19*MAX(0,MIN(H27,Tax_Bands!H$10+H24)-(Tax_Bands!H$9+H24))+Tax_Bands!H$20*MAX(0,H27-(Tax_Bands!H$10+H24)) -> 60983.403 | I28: =Tax_Bands!I$18*MIN(I27,Tax_Bands!I$9+I24)+Tax_Bands!I$19*MAX(0,MIN(I27,Tax_Bands!I$10+I24)-(Tax_Bands!I$9+I24))+Tax_Bands!I$20*MAX(0,I27-(Tax_Bands!I$10+I24)) -> 62203.071 | J28: =Tax_Bands!J$18*MIN(J27,Tax_Bands!J$9+J24)+Tax_Bands!J$19*MAX(0,MIN(J27,Tax_Bands!J$10+J24)-(Tax_Bands!J$9+J24))+Tax_Bands!J$20*MAX(0,J27-(Tax_Bands!J$10+J24)) -> 63447.132 | ... AF28: =Tax_Bands!AF$18*MIN(AF27,Tax_Bands!AF$9+AF24)+Tax_Bands!AF$19*MAX(0,MIN(AF27,Tax_Bands!AF$10+AF24)-(Tax_Bands!AF$9+AF24))+Tax_Bands!AF$20*MAX(0,AF27-(Tax_Bands!AF$10+AF24)) -> 98087.977
B29: Higher / additional-rate relief recovered | C29: =C20-C28 -> 9921 | D29: =D20-D28 -> 9225 | E29: =E20-E28 -> 8994 | F29: =F20-F28 -> 8873.88 | G29: =G20-G28 -> 8751.3576 | H29: =H20-H28 -> 8926.3848 | I29: =I20-I28 -> 9104.9124 | J29: =J20-J28 -> 9287.0107 | ... AF29: =AF20-AF28 -> 14357.53
B30: POST-TAX INCOME (gross income less income tax and NI) | C30: =C8-C28-C21 -> 114957.4 | D30: =D8-D28-D21 -> 118180.4 | E30: =E8-E28-E21 -> 121836.16 | F30: =F8-F28-F21 -> 123737.16 | G30: =G8-G28-G21 -> 125676.17 | H30: =H8-H28-H21 -> 128189.69 | I30: =I8-I28-I21 -> 130753.49 | J30: =J8-J28-J21 -> 133368.56 | ... AF30: =AF8-AF28-AF21 -> 206185.08
B31: Effective income tax + NI rate | C31: =IF(C8=0,0,(C28+C21)/C8) -> 0.32378 | D31: =IF(D8=0,0,(D28+D21)/D8) -> 0.33155882 | E31: =IF(E8=0,0,(E28+E21)/E8) -> 0.33738601 | F31: =IF(F8=0,0,(F28+F21)/F8) -> 0.34024247 | G31: =IF(G8=0,0,(G28+G21)/G8) -> 0.34304292 | H31: =IF(H8=0,0,(H28+H21)/H8) -> 0.34304292 | I31: =IF(I8=0,0,(I28+I21)/I8) -> 0.34304292 | J31: =IF(J8=0,0,(J28+J21)/J8) -> 0.34304292 | ... AF31: =IF(AF8=0,0,(AF28+AF21)/AF8) -> 0.34304292
A32: MM — PENSION BALANCE
B33: Opening balance | C33: =Assumptions!$C$26 -> 480000 | D33: =C37 -> 578400 | E33: =D37 -> 684672 | F33: =E37 -> 799445.76 | G33: =F37 -> 923401.42 | H33: =G37 -> 1057273.5 | I33: =H37 -> 1203055.4 | J33: =I37 -> 1361723.9 | K33: =J37 -> 1534334.2 | ... AF33: =AE37 -> 9051152.7
B34: Add: workplace contributions (employee + employer) | C34: =C12 -> 21000 | D34: =D12 -> 23100 | E34: =E12 -> 24024 | F34: =F12 -> 24504.48 | G34: =G12 -> 24994.57 | H34: =H12 -> 25494.461 | I34: =I12 -> 26004.35 | J34: =J12 -> 26524.437 | ... AF34: =AF12 -> 41006.241
B35: Add: personal SIPP contribution | C35: =C24 -> 39000 | D35: =D24 -> 36900 | E35: =E24 -> 35976 | F35: =F24 -> 35495.52 | G35: =G24 -> 35005.43 | H35: =H24 -> 35705.539 | I35: =I24 -> 36419.65 | J35: =J24 -> 37148.043 | ... AF35: =AF24 -> 57430.119
B36: Add: investment growth | C36: =C33*Returns!C$9 -> 38400 | D36: =D33*Returns!D$9 -> 46272 | E36: =E33*Returns!E$9 -> 54773.76 | F36: =F33*Returns!F$9 -> 63955.661 | G36: =G33*Returns!G$9 -> 73872.114 | H36: =H33*Returns!H$9 -> 84581.883 | I36: =I33*Returns!I$9 -> 96244.433 | J36: =J33*Returns!J$9 -> 108937.91 | ... AF36: =AF33*Returns!AF$9 -> 343943.8
B37: CLOSING BALANCE | C37: =C33+C34+C35+C36 -> 578400 | D37: =D33+D34+D35+D36 -> 684672 | E37: =E33+E34+E35+E36 -> 799445.76 | F37: =F33+F34+F35+F36 -> 923401.42 | G37: =G33+G34+G35+G36 -> 1057273.5 | H37: =H33+H34+H35+H36 -> 1203055.4 | I37: =I33+I34+I35+I36 -> 1361723.9 | J37: =J33+J34+J35+J36 -> 1534334.2 | ... AF37: =AF33+AF34+AF35+AF36 -> 9493532.9

Sheet DM_Income
A1: DM — INCOME, TAX, PENSION CONTRIBUTIONS AND BALANCE
A2: Workplace pension: NET PAY arrangement — the employee contribution reduces taxable pay but not National Insurance; the employer contribution is not taxable but does count towards the £60,000 annual allowance. Personal SIPP: RELIEF AT SOURCE — HMRC adds 20%, so £1 of gross costs 80p of cash, and the tax bands are extended by the gross contribution to give higher and additional-rate relief.
A4: DM — PAY AND PENSION INPUTS
B5: Year | C5: 2026 | D5: 2027 | E5: 2028 | F5: 2029 | G5: 2030 | H5: 2031 | I5: 2032 | J5: 2033 | K5: 2034 | L5: 2035 | M5: 2036 | N5: 2037 | O5: 2038 | P5: 2039 | Q5: 2040 | R5: 2041 | S5: 2042 | T5: 2043 | U5: 2044 | V5: 2045 | W5: 2046 | X5: 2047 | Y5: 2048 | Z5: 2049 | AA5: 2050 | AB5: 2051 | AC5: 2052 | AD5: 2053 | AE5: 2054 | AF5: 2055
B6: Age at 31 December | C6: =Assumptions!C$13 -> 44 | D6: =Assumptions!D$13 -> 45 | E6: =Assumptions!E$13 -> 46 | F6: =Assumptions!F$13 -> 47 | G6: =Assumptions!G$13 -> 48 | H6: =Assumptions!H$13 -> 49 | I6: =Assumptions!I$13 -> 50 | J6: =Assumptions!J$13 -> 51 | ... AF6: =Assumptions!AF$13 -> 73
B8: Total gross income | C8: =Assumptions!$D$21*Assumptions!C$9 -> 190000 | D8: =Assumptions!$D$21*Assumptions!D$9 -> 197600 | E8: =Assumptions!$D$21*Assumptions!E$9 -> 205504 | F8: =Assumptions!$D$21*Assumptions!F$9 -> 209614.08 | G8: =Assumptions!$D$21*Assumptions!G$9 -> 213806.36 | H8: =Assumptions!$D$21*Assumptions!H$9 -> 218082.49 | I8: =Assumptions!$D$21*Assumptions!I$9 -> 222444.14 | J8: =Assumptions!$D$21*Assumptions!J$9 -> 226893.02 | ... AF8: =Assumptions!$D$21*Assumptions!AF$9 -> 350772
B9: Base salary | C9: =Assumptions!$D$22 -> 130000 | D9: =IF(Assumptions!$D$23>0,Assumptions!$D$23*Assumptions!D$9/Assumptions!$D$9,Assumptions!$D$22*Assumptions!D$9) -> 135200 | E9: =IF(Assumptions!$D$23>0,Assumptions!$D$23*Assumptions!E$9/Assumptions!$D$9,Assumptions!$D$22*Assumptions!E$9) -> 140608 | F9: =IF(Assumptions!$D$23>0,Assumptions!$D$23*Assumptions!F$9/Assumptions!$D$9,Assumptions!$D$22*Assumptions!F$9) -> 143420.16 | G9: =IF(Assumptions!$D$23>0,Assumptions!$D$23*Assumptions!G$9/Assumptions!$D$9,Assumptions!$D$22*Assumptions!G$9) -> 146288.56 | H9: =IF(Assumptions!$D$23>0,Assumptions!$D$23*Assumptions!H$9/Assumptions!$D$9,Assumptions!$D$22*Assumptions!H$9) -> 149214.33 | I9: =IF(Assumptions!$D$23>0,Assumptions!$D$23*Assumptions!I$9/Assumptions!$D$9,Assumptions!$D$22*Assumptions!I$9) -> 152198.62 | J9: =IF(Assumptions!$D$23>0,Assumptions!$D$23*Assumptions!J$9/Assumptions!$D$9,Assumptions!$D$22*Assumptions!J$9) -> 155242.59 | K9: =IF(Assumptions!$D$23>0,Assumptions!$D$23*Assumptions!K$9/Assumptions!$D$9,Assumptions!$D$22*Assumptions!K$9) -> 158347.45 | ... AF9: =IF(Assumptions!$D$23>0,Assumptions!$D$23*Assumptions!AF$9/Assumptions!$D$9,Assumptions!$D$22*Assumptions!AF$9) -> 240001.89
B10: Employee workplace pension contribution | C10: =C9*Assumptions!$D$28 -> 15600 | D10: =D9*Assumptions!$D$28 -> 16224 | E10: =E9*Assumptions!$D$28 -> 16872.96 | F10: =F9*Assumptions!$D$28 -> 17210.419 | G10: =G9*Assumptions!$D$28 -> 17554.628 | H10: =H9*Assumptions!$D$28 -> 17905.72 | I10: =I9*Assumptions!$D$28 -> 18263.835 | J10: =J9*Assumptions!$D$28 -> 18629.111 | ... AF10: =AF9*Assumptions!$D$28 -> 28800.227
B11: Employer workplace pension contribution | C11: =C9*Assumptions!$D$29 -> 15600 | D11: =D9*Assumptions!$D$29 -> 16224 | E11: =E9*Assumptions!$D$29 -> 16872.96 | F11: =F9*Assumptions!$D$29 -> 17210.419 | G11: =G9*Assumptions!$D$29 -> 17554.628 | H11: =H9*Assumptions!$D$29 -> 17905.72 | I11: =I9*Assumptions!$D$29 -> 18263.835 | J11: =J9*Assumptions!$D$29 -> 18629.111 | ... AF11: =AF9*Assumptions!$D$29 -> 28800.227
B12: Total workplace pension input | C12: =C10+C11 -> 31200 | D12: =D10+D11 -> 32448 | E12: =E10+E11 -> 33745.92 | F12: =F10+F11 -> 34420.838 | G12: =G10+G11 -> 35109.255 | H12: =H10+H11 -> 35811.44 | I12: =I10+I11 -> 36527.669 | J12: =J10+J11 -> 37258.222 | ... AF12: =AF10+AF11 -> 57600.454
B13: Adjusted income (for the annual allowance taper) | C13: =C8+C11 -> 205600 | D13: =D8+D11 -> 213824 | E13: =E8+E11 -> 222376.96 | F13: =F8+F11 -> 226824.5 | G13: =G8+G11 -> 231360.99 | H13: =H8+H11 -> 235988.21 | I13: =I8+I11 -> 240707.97 | J13: =J8+J11 -> 245522.13 | ... AF13: =AF8+AF11 -> 379572.23
B14: Annual allowance available after any taper | C14: =MAX(Tax_Bands!C$15,Tax_Bands!C$13-MAX(0,C13-Tax_Bands!C$14)/2) -> 60000 | D14: =MAX(Tax_Bands!D$15,Tax_Bands!D$13-MAX(0,D13-Tax_Bands!D$14)/2) -> 60000 | E14: =MAX(Tax_Bands!E$15,Tax_Bands!E$13-MAX(0,E13-Tax_Bands!E$14)/2) -> 60000 | F14: =MAX(Tax_Bands!F$15,Tax_Bands!F$13-MAX(0,F13-Tax_Bands!F$14)/2) -> 60000 | G14: =MAX(Tax_Bands!G$15,Tax_Bands!G$13-MAX(0,G13-Tax_Bands!G$14)/2) -> 60000 | H14: =MAX(Tax_Bands!H$15,Tax_Bands!H$13-MAX(0,H13-Tax_Bands!H$14)/2) -> 61200 | I14: =MAX(Tax_Bands!I$15,Tax_Bands!I$13-MAX(0,I13-Tax_Bands!I$14)/2) -> 62424 | J14: =MAX(Tax_Bands!J$15,Tax_Bands!J$13-MAX(0,J13-Tax_Bands!J$14)/2) -> 63672.48 | ... AF14: =MAX(Tax_Bands!AF$15,Tax_Bands!AF$13-MAX(0,AF13-Tax_Bands!AF$14)/2) -> 98436.36
B15: SIPP HEADROOM (allowance less workplace contributions) | C15: =MAX(0,MIN(C14-C12,C8-C10)) -> 28800 | D15: =MAX(0,MIN(D14-D12,D8-D10)) -> 27552 | E15: =MAX(0,MIN(E14-E12,E8-E10)) -> 26254.08 | F15: =MAX(0,MIN(F14-F12,F8-F10)) -> 25579.162 | G15: =MAX(0,MIN(G14-G12,G8-G10)) -> 24890.745 | H15: =MAX(0,MIN(H14-H12,H8-H10)) -> 25388.56 | I15: =MAX(0,MIN(I14-I12,I8-I10)) -> 25896.331 | J15: =MAX(0,MIN(J14-J12,J8-J10)) -> 26414.258 | ... AF15: =MAX(0,MIN(AF14-AF12,AF8-AF10)) -> 40835.905
A16: DM — TAX BEFORE ANY PERSONAL SIPP CONTRIBUTION
B17: Taxable pay (income less the employee workplace contribution) | C17: =C8-C10 -> 174400 | D17: =D8-D10 -> 181376 | E17: =E8-E10 -> 188631.04 | F17: =F8-F10 -> 192403.66 | G17: =G8-G10 -> 196251.73 | H17: =H8-H10 -> 200176.77 | I17: =I8-I10 -> 204180.3 | J17: =J8-J10 -> 208263.91 | ... AF17: =AF8-AF10 -> 321971.77
B18: Personal allowance after taper | C18: =MAX(0,Tax_Bands!C$7-MAX(0,C17-Tax_Bands!C$8)/2) -> 0 | D18: =MAX(0,Tax_Bands!D$7-MAX(0,D17-Tax_Bands!D$8)/2) -> 0 | E18: =MAX(0,Tax_Bands!E$7-MAX(0,E17-Tax_Bands!E$8)/2) -> 0 | F18: =MAX(0,Tax_Bands!F$7-MAX(0,F17-Tax_Bands!F$8)/2) -> 0 | G18: =MAX(0,Tax_Bands!G$7-MAX(0,G17-Tax_Bands!G$8)/2) -> 0 | H18: =MAX(0,Tax_Bands!H$7-MAX(0,H17-Tax_Bands!H$8)/2) -> 0 | I18: =MAX(0,Tax_Bands!I$7-MAX(0,I17-Tax_Bands!I$8)/2) -> 0 | J18: =MAX(0,Tax_Bands!J$7-MAX(0,J17-Tax_Bands!J$8)/2) -> 0 | ... AF18: =MAX(0,Tax_Bands!AF$7-MAX(0,AF17-Tax_Bands!AF$8)/2) -> 0
B19: Taxable income | C19: =MAX(0,C17-C18) -> 174400 | D19: =MAX(0,D17-D18) -> 181376 | E19: =MAX(0,E17-E18) -> 188631.04 | F19: =MAX(0,F17-F18) -> 192403.66 | G19: =MAX(0,G17-G18) -> 196251.73 | H19: =MAX(0,H17-H18) -> 200176.77 | I19: =MAX(0,I17-I18) -> 204180.3 | J19: =MAX(0,J17-J18) -> 208263.91 | ... AF19: =MAX(0,AF17-AF18) -> 321971.77
B20: Income tax | C20: =Tax_Bands!C$18*MIN(C19,Tax_Bands!C$9)+Tax_Bands!C$19*MAX(0,MIN(C19,Tax_Bands!C$10)-Tax_Bands!C$9)+Tax_Bands!C$20*MAX(0,C19-Tax_Bands!C$10) -> 64683 | D20: =Tax_Bands!D$18*MIN(D19,Tax_Bands!D$9)+Tax_Bands!D$19*MAX(0,MIN(D19,Tax_Bands!D$10)-Tax_Bands!D$9)+Tax_Bands!D$20*MAX(0,D19-Tax_Bands!D$10) -> 67822.2 | E20: =Tax_Bands!E$18*MIN(E19,Tax_Bands!E$9)+Tax_Bands!E$19*MAX(0,MIN(E19,Tax_Bands!E$10)-Tax_Bands!E$9)+Tax_Bands!E$20*MAX(0,E19-Tax_Bands!E$10) -> 71086.968 | F20: =Tax_Bands!F$18*MIN(F19,Tax_Bands!F$9)+Tax_Bands!F$19*MAX(0,MIN(F19,Tax_Bands!F$10)-Tax_Bands!F$9)+Tax_Bands!F$20*MAX(0,F19-Tax_Bands!F$10) -> 72784.647 | G20: =Tax_Bands!G$18*MIN(G19,Tax_Bands!G$9)+Tax_Bands!G$19*MAX(0,MIN(G19,Tax_Bands!G$10)-Tax_Bands!G$9)+Tax_Bands!G$20*MAX(0,G19-Tax_Bands!G$10) -> 74516.28 | H20: =Tax_Bands!H$18*MIN(H19,Tax_Bands!H$9)+Tax_Bands!H$19*MAX(0,MIN(H19,Tax_Bands!H$10)-Tax_Bands!H$9)+Tax_Bands!H$20*MAX(0,H19-Tax_Bands!H$10) -> 76006.606 | I20: =Tax_Bands!I$18*MIN(I19,Tax_Bands!I$9)+Tax_Bands!I$19*MAX(0,MIN(I19,Tax_Bands!I$10)-Tax_Bands!I$9)+Tax_Bands!I$20*MAX(0,I19-Tax_Bands!I$10) -> 77526.738 | J20: =Tax_Bands!J$18*MIN(J19,Tax_Bands!J$9)+Tax_Bands!J$19*MAX(0,MIN(J19,Tax_Bands!J$10)-Tax_Bands!J$9)+Tax_Bands!J$20*MAX(0,J19-Tax_Bands!J$10) -> 79077.273 | ... AF20: =Tax_Bands!AF$18*MIN(AF19,Tax_Bands!AF$9)+Tax_Bands!AF$19*MAX(0,MIN(AF19,Tax_Bands!AF$10)-Tax_Bands!AF$9)+Tax_Bands!AF$20*MAX(0,AF19-Tax_Bands!AF$10) -> 122251.86
B21: Employee National Insurance | C21: =Tax_Bands!C$21*MAX(0,MIN(C8,Tax_Bands!C$12)-Tax_Bands!C$11)+Tax_Bands!C$22*MAX(0,C8-Tax_Bands!C$12) -> 5810.6 | D21: =Tax_Bands!D$21*MAX(0,MIN(D8,Tax_Bands!D$12)-Tax_Bands!D$11)+Tax_Bands!D$22*MAX(0,D8-Tax_Bands!D$12) -> 5962.6 | E21: =Tax_Bands!E$21*MAX(0,MIN(E8,Tax_Bands!E$12)-Tax_Bands!E$11)+Tax_Bands!E$22*MAX(0,E8-Tax_Bands!E$12) -> 6120.68 | F21: =Tax_Bands!F$21*MAX(0,MIN(F8,Tax_Bands!F$12)-Tax_Bands!F$11)+Tax_Bands!F$22*MAX(0,F8-Tax_Bands!F$12) -> 6202.8816 | G21: =Tax_Bands!G$21*MAX(0,MIN(G8,Tax_Bands!G$12)-Tax_Bands!G$11)+Tax_Bands!G$22*MAX(0,G8-Tax_Bands!G$12) -> 6286.7272 | H21: =Tax_Bands!H$21*MAX(0,MIN(H8,Tax_Bands!H$12)-Tax_Bands!H$11)+Tax_Bands!H$22*MAX(0,H8-Tax_Bands!H$12) -> 6412.4618 | I21: =Tax_Bands!I$21*MAX(0,MIN(I8,Tax_Bands!I$12)-Tax_Bands!I$11)+Tax_Bands!I$22*MAX(0,I8-Tax_Bands!I$12) -> 6540.711 | J21: =Tax_Bands!J$21*MAX(0,MIN(J8,Tax_Bands!J$12)-Tax_Bands!J$11)+Tax_Bands!J$22*MAX(0,J8-Tax_Bands!J$12) -> 6671.5252 | ... AF21: =Tax_Bands!AF$21*MAX(0,MIN(AF8,Tax_Bands!AF$12)-Tax_Bands!AF$11)+Tax_Bands!AF$22*MAX(0,AF8-Tax_Bands!AF$12) -> 10314.042
B22: NET PAY (cash in hand before any personal SIPP contribution) | C22: =C17-C20-C21 -> 103906.4 | D22: =D17-D20-D21 -> 107591.2 | E22: =E17-E20-E21 -> 111423.39 | F22: =F17-F20-F21 -> 113416.13 | G22: =G17-G20-G21 -> 115448.73 | H22: =H17-H20-H21 -> 117757.7 | I22: =I17-I20-I21 -> 120112.86 | J22: =J17-J20-J21 -> 122515.11 | ... AF22: =AF17-AF20-AF21 -> 189405.87
A23: DM — WITH THE PERSONAL SIPP CONTRIBUTION ACTUALLY AFFORDED
B24: Personal SIPP contribution (gross) | C24: =Household_Base!C$38 -> 28800 | D24: =Household_Base!D$38 -> 27552 | E24: =Household_Base!E$38 -> 26254.08 | F24: =Household_Base!F$38 -> 25579.162 | G24: =Household_Base!G$38 -> 24890.745 | H24: =Household_Base!H$38 -> 25388.56 | I24: =Household_Base!I$38 -> 25896.331 | J24: =Household_Base!J$38 -> 26414.258 | ... AF24: =Household_Base!AF$38 -> 40835.905
B25: Adjusted net income | C25: =C17-C24 -> 145600 | D25: =D17-D24 -> 153824 | E25: =E17-E24 -> 162376.96 | F25: =F17-F24 -> 166824.5 | G25: =G17-G24 -> 171360.99 | H25: =H17-H24 -> 174788.21 | I25: =I17-I24 -> 178283.97 | J25: =J17-J24 -> 181849.65 | ... AF25: =AF17-AF24 -> 281135.87
B26: Personal allowance after taper | C26: =MAX(0,Tax_Bands!C$7-MAX(0,C25-Tax_Bands!C$8)/2) -> 0 | D26: =MAX(0,Tax_Bands!D$7-MAX(0,D25-Tax_Bands!D$8)/2) -> 0 | E26: =MAX(0,Tax_Bands!E$7-MAX(0,E25-Tax_Bands!E$8)/2) -> 0 | F26: =MAX(0,Tax_Bands!F$7-MAX(0,F25-Tax_Bands!F$8)/2) -> 0 | G26: =MAX(0,Tax_Bands!G$7-MAX(0,G25-Tax_Bands!G$8)/2) -> 0 | H26: =MAX(0,Tax_Bands!H$7-MAX(0,H25-Tax_Bands!H$8)/2) -> 0 | I26: =MAX(0,Tax_Bands!I$7-MAX(0,I25-Tax_Bands!I$8)/2) -> 0 | J26: =MAX(0,Tax_Bands!J$7-MAX(0,J25-Tax_Bands!J$8)/2) -> 0 | ... AF26: =MAX(0,Tax_Bands!AF$7-MAX(0,AF25-Tax_Bands!AF$8)/2) -> 0
B27: Taxable income | C27: =MAX(0,C17-C26) -> 174400 | D27: =MAX(0,D17-D26) -> 181376 | E27: =MAX(0,E17-E26) -> 188631.04 | F27: =MAX(0,F17-F26) -> 192403.66 | G27: =MAX(0,G17-G26) -> 196251.73 | H27: =MAX(0,H17-H26) -> 200176.77 | I27: =MAX(0,I17-I26) -> 204180.3 | J27: =MAX(0,J17-J26) -> 208263.91 | ... AF27: =MAX(0,AF17-AF26) -> 321971.77
B28: Income tax | C28: =Tax_Bands!C$18*MIN(C27,Tax_Bands!C$9+C24)+Tax_Bands!C$19*MAX(0,MIN(C27,Tax_Bands!C$10+C24)-(Tax_Bands!C$9+C24))+Tax_Bands!C$20*MAX(0,C27-(Tax_Bands!C$10+C24)) -> 57483 | D28: =Tax_Bands!D$18*MIN(D27,Tax_Bands!D$9+D24)+Tax_Bands!D$19*MAX(0,MIN(D27,Tax_Bands!D$10+D24)-(Tax_Bands!D$9+D24))+Tax_Bands!D$20*MAX(0,D27-(Tax_Bands!D$10+D24)) -> 60934.2 | E28: =Tax_Bands!E$18*MIN(E27,Tax_Bands!E$9+E24)+Tax_Bands!E$19*MAX(0,MIN(E27,Tax_Bands!E$10+E24)-(Tax_Bands!E$9+E24))+Tax_Bands!E$20*MAX(0,E27-(Tax_Bands!E$10+E24)) -> 64523.448 | F28: =Tax_Bands!F$18*MIN(F27,Tax_Bands!F$9+F24)+Tax_Bands!F$19*MAX(0,MIN(F27,Tax_Bands!F$10+F24)-(Tax_Bands!F$9+F24))+Tax_Bands!F$20*MAX(0,F27-(Tax_Bands!F$10+F24)) -> 66389.857 | G28: =Tax_Bands!G$18*MIN(G27,Tax_Bands!G$9+G24)+Tax_Bands!G$19*MAX(0,MIN(G27,Tax_Bands!G$10+G24)-(Tax_Bands!G$9+G24))+Tax_Bands!G$20*MAX(0,G27-(Tax_Bands!G$10+G24)) -> 68293.594 | H28: =Tax_Bands!H$18*MIN(H27,Tax_Bands!H$9+H24)+Tax_Bands!H$19*MAX(0,MIN(H27,Tax_Bands!H$10+H24)-(Tax_Bands!H$9+H24))+Tax_Bands!H$20*MAX(0,H27-(Tax_Bands!H$10+H24)) -> 69659.466 | I28: =Tax_Bands!I$18*MIN(I27,Tax_Bands!I$9+I24)+Tax_Bands!I$19*MAX(0,MIN(I27,Tax_Bands!I$10+I24)-(Tax_Bands!I$9+I24))+Tax_Bands!I$20*MAX(0,I27-(Tax_Bands!I$10+I24)) -> 71052.655 | J28: =Tax_Bands!J$18*MIN(J27,Tax_Bands!J$9+J24)+Tax_Bands!J$19*MAX(0,MIN(J27,Tax_Bands!J$10+J24)-(Tax_Bands!J$9+J24))+Tax_Bands!J$20*MAX(0,J27-(Tax_Bands!J$10+J24)) -> 72473.708 | ... AF28: =Tax_Bands!AF$18*MIN(AF27,Tax_Bands!AF$9+AF24)+Tax_Bands!AF$19*MAX(0,MIN(AF27,Tax_Bands!AF$10+AF24)-(Tax_Bands!AF$9+AF24))+Tax_Bands!AF$20*MAX(0,AF27-(Tax_Bands!AF$10+AF24)) -> 112042.88
B29: Higher / additional-rate relief recovered | C29: =C20-C28 -> 7200 | D29: =D20-D28 -> 6888 | E29: =E20-E28 -> 6563.52 | F29: =F20-F28 -> 6394.7904 | G29: =G20-G28 -> 6222.6862 | H29: =H20-H28 -> 6347.1399 | I29: =I20-I28 -> 6474.0827 | J29: =J20-J28 -> 6603.5644 | ... AF29: =AF20-AF28 -> 10208.976
B30: POST-TAX INCOME (gross income less income tax and NI) | C30: =C8-C28-C21 -> 126706.4 | D30: =D8-D28-D21 -> 130703.2 | E30: =E8-E28-E21 -> 134859.87 | F30: =F8-F28-F21 -> 137021.34 | G30: =G8-G28-G21 -> 139226.04 | H30: =H8-H28-H21 -> 142010.56 | I30: =I8-I28-I21 -> 144850.77 | J30: =J8-J28-J21 -> 147747.79 | ... AF30: =AF8-AF28-AF21 -> 228415.08
B31: Effective income tax + NI rate | C31: =IF(C8=0,0,(C28+C21)/C8) -> 0.33312421 | D31: =IF(D8=0,0,(D28+D21)/D8) -> 0.33854656 | E31: =IF(E8=0,0,(E28+E21)/E8) -> 0.34376036 | F31: =IF(F8=0,0,(F28+F21)/F8) -> 0.34631614 | G31: =IF(G8=0,0,(G28+G21)/G8) -> 0.34882181 | H31: =IF(H8=0,0,(H28+H21)/H8) -> 0.34882181 | I31: =IF(I8=0,0,(I28+I21)/I8) -> 0.34882181 | J31: =IF(J8=0,0,(J28+J21)/J8) -> 0.34882181 | ... AF31: =IF(AF8=0,0,(AF28+AF21)/AF8) -> 0.34882181
A32: DM — PENSION BALANCE
B33: Opening balance | C33: =Assumptions!$D$26 -> 760000 | D33: =C37 -> 880800 | E33: =D37 -> 1011264 | F33: =E37 -> 1152165.1 | G33: =F37 -> 1304338.3 | H33: =G37 -> 1468685.4 | I33: =H37 -> 1647380.2 | J33: =I37 -> 1841594.6 | K33: =J37 -> 2047069.9 | ... AF33: =AE37 -> 7426024.4
B34: Add: workplace contributions (employee + employer) | C34: =C12 -> 31200 | D34: =D12 -> 32448 | E34: =E12 -> 33745.92 | F34: =F12 -> 34420.838 | G34: =G12 -> 35109.255 | H34: =H12 -> 35811.44 | I34: =I12 -> 36527.669 | J34: =J12 -> 37258.222 | ... AF34: =AF12 -> 57600.454
B35: Add: personal SIPP contribution | C35: =C24 -> 28800 | D35: =D24 -> 27552 | E35: =E24 -> 26254.08 | F35: =F24 -> 25579.162 | G35: =G24 -> 24890.745 | H35: =H24 -> 25388.56 | I35: =I24 -> 25896.331 | J35: =J24 -> 26414.258 | ... AF35: =AF24 -> 40835.905
B36: Add: investment growth | C36: =C33*Returns!C$10 -> 60800 | D36: =D33*Returns!D$10 -> 70464 | E36: =E33*Returns!E$10 -> 80901.12 | F36: =F33*Returns!F$10 -> 92173.21 | G36: =G33*Returns!G$10 -> 104347.07 | H36: =H33*Returns!H$10 -> 117494.83 | I36: =I33*Returns!I$10 -> 131790.42 | J36: =J33*Returns!J$10 -> 141802.79 | ... AF36: =AF33*Returns!AF$10 -> 148520.49
B37: CLOSING BALANCE | C37: =C33+C34+C35+C36 -> 880800 | D37: =D33+D34+D35+D36 -> 1011264 | E37: =E33+E34+E35+E36 -> 1152165.1 | F37: =F33+F34+F35+F36 -> 1304338.3 | G37: =G33+G34+G35+G36 -> 1468685.4 | H37: =H33+H34+H35+H36 -> 1647380.2 | I37: =I33+I34+I35+I36 -> 1841594.6 | J37: =J33+J34+J35+J36 -> 2047069.9 | ... AF37: =AF33+AF34+AF35+AF36 -> 7672981.2

Sheet Children
A1: CHILDREN — CHILDCARE, UNIVERSITY, THE LONDON YEAR AND JUNIOR ISAs
A2: Each Junior ISA is funded at £9,000 a year and then STOPS as soon as the pot on its own, with no further contributions, will grow to cover three years of university plus one year of London living after graduation. JISA rules applied: £9,000 a year per child, separate from the adult ISA allowance, no access before 18, converts automatically to an adult ISA at 18.
A4: TIMELINE
B5: Year | C5: 2026 | D5: 2027 | E5: 2028 | F5: 2029 | G5: 2030 | H5: 2031 | I5: 2032 | J5: 2033 | K5: 2034 | L5: 2035 | M5: 2036 | N5: 2037 | O5: 2038 | P5: 2039 | Q5: 2040 | R5: 2041 | S5: 2042 | T5: 2043 | U5: 2044 | V5: 2045 | W5: 2046 | X5: 2047 | Y5: 2048 | Z5: 2049 | AA5: 2050 | AB5: 2051 | AC5: 2052 | AD5: 2053 | AE5: 2054 | AF5: 2055
B6: VM age | C6: =Assumptions!C$15 -> 6 | D6: =Assumptions!D$15 -> 7 | E6: =Assumptions!E$15 -> 8 | F6: =Assumptions!F$15 -> 9 | G6: =Assumptions!G$15 -> 10 | H6: =Assumptions!H$15 -> 11 | I6: =Assumptions!I$15 -> 12 | J6: =Assumptions!J$15 -> 13 | ... AF6: =Assumptions!AF$15 -> 35
B7: EM age | C7: =Assumptions!C$16 -> 3 | D7: =Assumptions!D$16 -> 4 | E7: =Assumptions!E$16 -> 5 | F7: =Assumptions!F$16 -> 6 | G7: =Assumptions!G$16 -> 7 | H7: =Assumptions!H$16 -> 8 | I7: =Assumptions!I$16 -> 9 | J7: =Assumptions!J$16 -> 10 | ... AF7: =Assumptions!AF$16 -> 32
B8: Child 3 age (scenario) | C8: =Assumptions!C$17 | D8: =Assumptions!D$17 -> 0 | E8: =Assumptions!E$17 -> 1 | F8: =Assumptions!F$17 -> 2 | G8: =Assumptions!G$17 -> 3 | H8: =Assumptions!H$17 -> 4 | I8: =Assumptions!I$17 -> 5 | J8: =Assumptions!J$17 -> 6 | ... AF8: =Assumptions!AF$17 -> 28
A9: CHILDCARE
B10: EM — months of nursery charged | C10: =IF(OR(C5<Assumptions!$D$84,C5>Assumptions!$D$86),0,IF(C5=Assumptions!$D$84,Assumptions!$D$85,IF(C5=Assumptions!$D$86,Assumptions!$D$87,12))) -> 12 | D10: =IF(OR(D5<Assumptions!$D$84,D5>Assumptions!$D$86),0,IF(D5=Assumptions!$D$84,Assumptions!$D$85,IF(D5=Assumptions!$D$86,Assumptions!$D$87,12))) -> 12 | E10: =IF(OR(E5<Assumptions!$D$84,E5>Assumptions!$D$86),0,IF(E5=Assumptions!$D$84,Assumptions!$D$85,IF(E5=Assumptions!$D$86,Assumptions!$D$87,12))) -> 8 | F10: =IF(OR(F5<Assumptions!$D$84,F5>Assumptions!$D$86),0,IF(F5=Assumptions!$D$84,Assumptions!$D$85,IF(F5=Assumptions!$D$86,Assumptions!$D$87,12))) -> 0 | G10: =IF(OR(G5<Assumptions!$D$84,G5>Assumptions!$D$86),0,IF(G5=Assumptions!$D$84,Assumptions!$D$85,IF(G5=Assumptions!$D$86,Assumptions!$D$87,12))) -> 0 | H10: =IF(OR(H5<Assumptions!$D$84,H5>Assumptions!$D$86),0,IF(H5=Assumptions!$D$84,Assumptions!$D$85,IF(H5=Assumptions!$D$86,Assumptions!$D$87,12))) -> 0 | I10: =IF(OR(I5<Assumptions!$D$84,I5>Assumptions!$D$86),0,IF(I5=Assumptions!$D$84,Assumptions!$D$85,IF(I5=Assumptions!$D$86,Assumptions!$D$87,12))) -> 0 | J10: =IF(OR(J5<Assumptions!$D$84,J5>Assumptions!$D$86),0,IF(J5=Assumptions!$D$84,Assumptions!$D$85,IF(J5=Assumptions!$D$86,Assumptions!$D$87,12))) -> 0 | ... AF10: =IF(OR(AF5<Assumptions!$D$84,AF5>Assumptions!$D$86),0,IF(AF5=Assumptions!$D$84,Assumptions!$D$85,IF(AF5=Assumptions!$D$86,Assumptions!$D$87,12))) -> 0
B11: EM — nursery fees | C11: =C10*Assumptions!$C$68*Assumptions!C$9 -> 32400 | D11: =D10*Assumptions!$C$68*Assumptions!D$9 -> 33696 | E11: =E10*Assumptions!$C$68*Assumptions!E$9 -> 23362.56 | F11: =F10*Assumptions!$C$68*Assumptions!F$9 -> 0 | G11: =G10*Assumptions!$C$68*Assumptions!G$9 -> 0 | H11: =H10*Assumptions!$C$68*Assumptions!H$9 -> 0 | I11: =I10*Assumptions!$C$68*Assumptions!I$9 -> 0 | J11: =J10*Assumptions!$C$68*Assumptions!J$9 -> 0 | ... AF11: =AF10*Assumptions!$C$68*Assumptions!AF$9 -> 0
B12: Nannies (both, until EM turns 10) | C12: =IF(C5<=Assumptions!$C$67,12*Assumptions!$C$66*Assumptions!C$9,0) -> 18000 | D12: =IF(D5<=Assumptions!$C$67,12*Assumptions!$C$66*Assumptions!D$9,0) -> 18720 | E12: =IF(E5<=Assumptions!$C$67,12*Assumptions!$C$66*Assumptions!E$9,0) -> 19468.8 | F12: =IF(F5<=Assumptions!$C$67,12*Assumptions!$C$66*Assumptions!F$9,0) -> 19858.176 | G12: =IF(G5<=Assumptions!$C$67,12*Assumptions!$C$66*Assumptions!G$9,0) -> 20255.34 | H12: =IF(H5<=Assumptions!$C$67,12*Assumptions!$C$66*Assumptions!H$9,0) -> 20660.446 | I12: =IF(I5<=Assumptions!$C$67,12*Assumptions!$C$66*Assumptions!I$9,0) -> 21073.655 | J12: =IF(J5<=Assumptions!$C$67,12*Assumptions!$C$66*Assumptions!J$9,0) -> 21495.128 | ... AF12: =IF(AF5<=Assumptions!$C$67,12*Assumptions!$C$66*Assumptions!AF$9,0) -> 0
A13: COST OF ONE YEAR OF UNIVERSITY, AND OF THE LONDON YEAR AFTER GRADUATION
B14: University — tuition plus accommodation and living (inflated) | C14: =(Assumptions!$C$75+Assumptions!$C$76)*Assumptions!C$9 -> 25450 | D14: =(Assumptions!$C$75+Assumptions!$C$76)*Assumptions!D$9 -> 26468 | E14: =(Assumptions!$C$75+Assumptions!$C$76)*Assumptions!E$9 -> 27526.72 | F14: =(Assumptions!$C$75+Assumptions!$C$76)*Assumptions!F$9 -> 28077.254 | G14: =(Assumptions!$C$75+Assumptions!$C$76)*Assumptions!G$9 -> 28638.799 | H14: =(Assumptions!$C$75+Assumptions!$C$76)*Assumptions!H$9 -> 29211.575 | I14: =(Assumptions!$C$75+Assumptions!$C$76)*Assumptions!I$9 -> 29795.807 | J14: =(Assumptions!$C$75+Assumptions!$C$76)*Assumptions!J$9 -> 30391.723 | ... AF14: =(Assumptions!$C$75+Assumptions!$C$76)*Assumptions!AF$9 -> 46984.986
B15: London — one year of living costs after graduation (inflated) | C15: =Assumptions!$C$78*Assumptions!C$9 -> 30000 | D15: =Assumptions!$C$78*Assumptions!D$9 -> 31200 | E15: =Assumptions!$C$78*Assumptions!E$9 -> 32448 | F15: =Assumptions!$C$78*Assumptions!F$9 -> 33096.96 | G15: =Assumptions!$C$78*Assumptions!G$9 -> 33758.899 | H15: =Assumptions!$C$78*Assumptions!H$9 -> 34434.077 | I15: =Assumptions!$C$78*Assumptions!I$9 -> 35122.759 | J15: =Assumptions!$C$78*Assumptions!J$9 -> 35825.214 | ... AF15: =Assumptions!$C$78*Assumptions!AF$9 -> 55385.052
A18: VM — WHAT HAS TO BE FUNDED, AND THE JUNIOR ISA THAT FUNDS IT
B19: VM — cost falling due this year | C19: =IF(AND(C5>=Assumptions!$C$89,C5<=Assumptions!$C$89+Assumptions!$C$77-1),C14,IF(C5=Assumptions!$C$90,C15,0)) -> 0 | D19: =IF(AND(D5>=Assumptions!$C$89,D5<=Assumptions!$C$89+Assumptions!$C$77-1),D14,IF(D5=Assumptions!$C$90,D15,0)) -> 0 | E19: =IF(AND(E5>=Assumptions!$C$89,E5<=Assumptions!$C$89+Assumptions!$C$77-1),E14,IF(E5=Assumptions!$C$90,E15,0)) -> 0 | F19: =IF(AND(F5>=Assumptions!$C$89,F5<=Assumptions!$C$89+Assumptions!$C$77-1),F14,IF(F5=Assumptions!$C$90,F15,0)) -> 0 | G19: =IF(AND(G5>=Assumptions!$C$89,G5<=Assumptions!$C$89+Assumptions!$C$77-1),G14,IF(G5=Assumptions!$C$90,G15,0)) -> 0 | H19: =IF(AND(H5>=Assumptions!$C$89,H5<=Assumptions!$C$89+Assumptions!$C$77-1),H14,IF(H5=Assumptions!$C$90,H15,0)) -> 0 | I19: =IF(AND(I5>=Assumptions!$C$89,I5<=Assumptions!$C$89+Assumptions!$C$77-1),I14,IF(I5=Assumptions!$C$90,I15,0)) -> 0 | J19: =IF(AND(J5>=Assumptions!$C$89,J5<=Assumptions!$C$89+Assumptions!$C$77-1),J14,IF(J5=Assumptions!$C$90,J15,0)) -> 0 | ... AF19: =IF(AND(AF5>=Assumptions!$C$89,AF5<=Assumptions!$C$89+Assumptions!$C$77-1),AF14,IF(AF5=Assumptions!$C$90,AF15,0)) -> 0
B20: VM — Junior ISA fund needed at the start of university | C20: =SUMPRODUCT($C$19:$AF$19/(1+Assumptions!$C$32)^($C$5:$AF$5-Assumptions!$C$89+1)) -> 121358.18 | D20: =SUMPRODUCT($C$19:$AF$19/(1+Assumptions!$C$32)^($C$5:$AF$5-Assumptions!$C$89+1)) -> 121358.18 | E20: =SUMPRODUCT($C$19:$AF$19/(1+Assumptions!$C$32)^($C$5:$AF$5-Assumptions!$C$89+1)) -> 121358.18 | F20: =SUMPRODUCT($C$19:$AF$19/(1+Assumptions!$C$32)^($C$5:$AF$5-Assumptions!$C$89+1)) -> 121358.18 | G20: =SUMPRODUCT($C$19:$AF$19/(1+Assumptions!$C$32)^($C$5:$AF$5-Assumptions!$C$89+1)) -> 121358.18 | H20: =SUMPRODUCT($C$19:$AF$19/(1+Assumptions!$C$32)^($C$5:$AF$5-Assumptions!$C$89+1)) -> 121358.18 | I20: =SUMPRODUCT($C$19:$AF$19/(1+Assumptions!$C$32)^($C$5:$AF$5-Assumptions!$C$89+1)) -> 121358.18 | J20: =SUMPRODUCT($C$19:$AF$19/(1+Assumptions!$C$32)^($C$5:$AF$5-Assumptions!$C$89+1)) -> 121358.18 | ... AF20: =SUMPRODUCT($C$19:$AF$19/(1+Assumptions!$C$32)^($C$5:$AF$5-Assumptions!$C$89+1)) -> 121358.18
B21: Fund projected to university if contributions stopped now | C21: =C22*(1+Assumptions!$C$32)^(Assumptions!$C$89-C5) -> 40794.356 | D21: =D22*(1+Assumptions!$C$32)^(Assumptions!$C$89-D5) -> 63457.887 | E21: =E22*(1+Assumptions!$C$32)^(Assumptions!$C$89-E5) -> 84442.638 | F21: =F22*(1+Assumptions!$C$32)^(Assumptions!$C$89-F5) -> 103872.96 | G21: =G22*(1+Assumptions!$C$32)^(Assumptions!$C$89-G5) -> 121864 | H21: =H22*(1+Assumptions!$C$32)^(Assumptions!$C$89-H5) -> 121864 | I21: =I22*(1+Assumptions!$C$32)^(Assumptions!$C$89-I5) -> 121864 | J21: =J22*(1+Assumptions!$C$32)^(Assumptions!$C$89-J5) -> 121864 | ... AF21: =AF22*(1+Assumptions!$C$32)^(Assumptions!$C$89-AF5) -> 505.82172
B22: Junior ISA — opening balance | C22: =Assumptions!$C$91 -> 15000 | D22: =C26 -> 25200 | E22: =D26 -> 36216 | F22: =E26 -> 48113.28 | G22: =F26 -> 60962.342 | H22: =G26 -> 65839.33 | I22: =H26 -> 71106.476 | J22: =I26 -> 76794.994 | K22: =J26 -> 82938.594 | ... AF22: =AE26 -> 1732.9162
B23: Add: contribution (£9,000 while still needed) | C23: =IF(AND(C5>=Assumptions!$C$93,C5<=Assumptions!$C$94,C21<C20),MIN(Assumptions!$C$92,Tax_Bands!C$17),0) -> 9000 | D23: =IF(AND(D5>=Assumptions!$C$93,D5<=Assumptions!$C$94,D21<D20),MIN(Assumptions!$C$92,Tax_Bands!D$17),0) -> 9000 | E23: =IF(AND(E5>=Assumptions!$C$93,E5<=Assumptions!$C$94,E21<E20),MIN(Assumptions!$C$92,Tax_Bands!E$17),0) -> 9000 | F23: =IF(AND(F5>=Assumptions!$C$93,F5<=Assumptions!$C$94,F21<F20),MIN(Assumptions!$C$92,Tax_Bands!F$17),0) -> 9000 | G23: =IF(AND(G5>=Assumptions!$C$93,G5<=Assumptions!$C$94,G21<G20),MIN(Assumptions!$C$92,Tax_Bands!G$17),0) -> 0 | H23: =IF(AND(H5>=Assumptions!$C$93,H5<=Assumptions!$C$94,H21<H20),MIN(Assumptions!$C$92,Tax_Bands!H$17),0) -> 0 | I23: =IF(AND(I5>=Assumptions!$C$93,I5<=Assumptions!$C$94,I21<I20),MIN(Assumptions!$C$92,Tax_Bands!I$17),0) -> 0 | J23: =IF(AND(J5>=Assumptions!$C$93,J5<=Assumptions!$C$94,J21<J20),MIN(Assumptions!$C$92,Tax_Bands!J$17),0) -> 0 | ... AF23: =IF(AND(AF5>=Assumptions!$C$93,AF5<=Assumptions!$C$94,AF21<AF20),MIN(Assumptions!$C$92,Tax_Bands!AF$17),0) -> 0
B24: Add: investment growth at the Junior ISA rate | C24: =C22*Assumptions!$C$32 -> 1200 | D24: =D22*Assumptions!$C$32 -> 2016 | E24: =E22*Assumptions!$C$32 -> 2897.28 | F24: =F22*Assumptions!$C$32 -> 3849.0624 | G24: =G22*Assumptions!$C$32 -> 4876.9874 | H24: =H22*Assumptions!$C$32 -> 5267.1464 | I24: =I22*Assumptions!$C$32 -> 5688.5181 | J24: =J22*Assumptions!$C$32 -> 6143.5995 | ... AF24: =AF22*Assumptions!$C$32 -> 138.6333
B25: Less: withdrawal to pay the cost | C25: =MIN(C22+C23+C24,C19) -> 0 | D25: =MIN(D22+D23+D24,D19) -> 0 | E25: =MIN(E22+E23+E24,E19) -> 0 | F25: =MIN(F22+F23+F24,F19) -> 0 | G25: =MIN(G22+G23+G24,G19) -> 0 | H25: =MIN(H22+H23+H24,H19) -> 0 | I25: =MIN(I22+I23+I24,I19) -> 0 | J25: =MIN(J22+J23+J24,J19) -> 0 | ... AF25: =MIN(AF22+AF23+AF24,AF19) -> 0
B26: VM — JUNIOR ISA CLOSING BALANCE | C26: =C22+C23+C24-C25 -> 25200 | D26: =D22+D23+D24-D25 -> 36216 | E26: =E22+E23+E24-E25 -> 48113.28 | F26: =F22+F23+F24-F25 -> 60962.342 | G26: =G22+G23+G24-G25 -> 65839.33 | H26: =H22+H23+H24-H25 -> 71106.476 | I26: =I22+I23+I24-I25 -> 76794.994 | J26: =J22+J23+J24-J25 -> 82938.594 | ... AF26: =AF22+AF23+AF24-AF25 -> 1871.5495
B27: VM — cost NOT covered by the Junior ISA (falls on the household) | C27: =C19-C25 -> 0 | D27: =D19-D25 -> 0 | E27: =E19-E25 -> 0 | F27: =F19-F25 -> 0 | G27: =G19-G25 -> 0 | H27: =H19-H25 -> 0 | I27: =I19-I25 -> 0 | J27: =J19-J25 -> 0 | ... AF27: =AF19-AF25 -> 0
A30: EM — WHAT HAS TO BE FUNDED, AND THE JUNIOR ISA THAT FUNDS IT
B31: EM — cost falling due this year | C31: =IF(AND(C5>=Assumptions!$D$89,C5<=Assumptions!$D$89+Assumptions!$C$77-1),C14,IF(C5=Assumptions!$D$90,C15,0)) -> 0 | D31: =IF(AND(D5>=Assumptions!$D$89,D5<=Assumptions!$D$89+Assumptions!$C$77-1),D14,IF(D5=Assumptions!$D$90,D15,0)) -> 0 | E31: =IF(AND(E5>=Assumptions!$D$89,E5<=Assumptions!$D$89+Assumptions!$C$77-1),E14,IF(E5=Assumptions!$D$90,E15,0)) -> 0 | F31: =IF(AND(F5>=Assumptions!$D$89,F5<=Assumptions!$D$89+Assumptions!$C$77-1),F14,IF(F5=Assumptions!$D$90,F15,0)) -> 0 | G31: =IF(AND(G5>=Assumptions!$D$89,G5<=Assumptions!$D$89+Assumptions!$C$77-1),G14,IF(G5=Assumptions!$D$90,G15,0)) -> 0 | H31: =IF(AND(H5>=Assumptions!$D$89,H5<=Assumptions!$D$89+Assumptions!$C$77-1),H14,IF(H5=Assumptions!$D$90,H15,0)) -> 0 | I31: =IF(AND(I5>=Assumptions!$D$89,I5<=Assumptions!$D$89+Assumptions!$C$77-1),I14,IF(I5=Assumptions!$D$90,I15,0)) -> 0 | J31: =IF(AND(J5>=Assumptions!$D$89,J5<=Assumptions!$D$89+Assumptions!$C$77-1),J14,IF(J5=Assumptions!$D$90,J15,0)) -> 0 | ... AF31: =IF(AND(AF5>=Assumptions!$D$89,AF5<=Assumptions!$D$89+Assumptions!$C$77-1),AF14,IF(AF5=Assumptions!$D$90,AF15,0)) -> 0
B32: EM — Junior ISA fund needed at the start of university | C32: =SUMPRODUCT($C$31:$AF$31/(1+Assumptions!$C$32)^($C$5:$AF$5-Assumptions!$D$89+1)) -> 128786.27 | D32: =SUMPRODUCT($C$31:$AF$31/(1+Assumptions!$C$32)^($C$5:$AF$5-Assumptions!$D$89+1)) -> 128786.27 | E32: =SUMPRODUCT($C$31:$AF$31/(1+Assumptions!$C$32)^($C$5:$AF$5-Assumptions!$D$89+1)) -> 128786.27 | F32: =SUMPRODUCT($C$31:$AF$31/(1+Assumptions!$C$32)^($C$5:$AF$5-Assumptions!$D$89+1)) -> 128786.27 | G32: =SUMPRODUCT($C$31:$AF$31/(1+Assumptions!$C$32)^($C$5:$AF$5-Assumptions!$D$89+1)) -> 128786.27 | H32: =SUMPRODUCT($C$31:$AF$31/(1+Assumptions!$C$32)^($C$5:$AF$5-Assumptions!$D$89+1)) -> 128786.27 | I32: =SUMPRODUCT($C$31:$AF$31/(1+Assumptions!$C$32)^($C$5:$AF$5-Assumptions!$D$89+1)) -> 128786.27 | J32: =SUMPRODUCT($C$31:$AF$31/(1+Assumptions!$C$32)^($C$5:$AF$5-Assumptions!$D$89+1)) -> 128786.27 | ... AF32: =SUMPRODUCT($C$31:$AF$31/(1+Assumptions!$C$32)^($C$5:$AF$5-Assumptions!$D$89+1)) -> 128786.27
B33: Fund projected to university if contributions stopped now | C33: =C34*(1+Assumptions!$C$32)^(Assumptions!$D$89-C5) -> 0 | D33: =D34*(1+Assumptions!$C$32)^(Assumptions!$D$89-D5) -> 28549.522 | E33: =E34*(1+Assumptions!$C$32)^(Assumptions!$D$89-E5) -> 54984.265 | F33: =F34*(1+Assumptions!$C$32)^(Assumptions!$D$89-F5) -> 79460.878 | G33: =G34*(1+Assumptions!$C$32)^(Assumptions!$D$89-G5) -> 102124.41 | H33: =H34*(1+Assumptions!$C$32)^(Assumptions!$D$89-H5) -> 123109.16 | I33: =I34*(1+Assumptions!$C$32)^(Assumptions!$D$89-I5) -> 142539.49 | J33: =J34*(1+Assumptions!$C$32)^(Assumptions!$D$89-J5) -> 142539.49 | ... AF33: =AF34*(1+Assumptions!$C$32)^(Assumptions!$D$89-AF5) -> 13753.211
B34: Junior ISA — opening balance | C34: =Assumptions!$D$91 -> 0 | D34: =C38 -> 9000 | E34: =D38 -> 18720 | F34: =E38 -> 29217.6 | G34: =F38 -> 40555.008 | H34: =G38 -> 52799.409 | I34: =H38 -> 66023.361 | J34: =I38 -> 71305.23 | K34: =J38 -> 77009.649 | ... AF34: =AE38 -> 37403.558
B35: Add: contribution (£9,000 while still needed) | C35: =IF(AND(C5>=Assumptions!$D$93,C5<=Assumptions!$D$94,C33<C32),MIN(Assumptions!$D$92,Tax_Bands!C$17),0) -> 9000 | D35: =IF(AND(D5>=Assumptions!$D$93,D5<=Assumptions!$D$94,D33<D32),MIN(Assumptions!$D$92,Tax_Bands!D$17),0) -> 9000 | E35: =IF(AND(E5>=Assumptions!$D$93,E5<=Assumptions!$D$94,E33<E32),MIN(Assumptions!$D$92,Tax_Bands!E$17),0) -> 9000 | F35: =IF(AND(F5>=Assumptions!$D$93,F5<=Assumptions!$D$94,F33<F32),MIN(Assumptions!$D$92,Tax_Bands!F$17),0) -> 9000 | G35: =IF(AND(G5>=Assumptions!$D$93,G5<=Assumptions!$D$94,G33<G32),MIN(Assumptions!$D$92,Tax_Bands!G$17),0) -> 9000 | H35: =IF(AND(H5>=Assumptions!$D$93,H5<=Assumptions!$D$94,H33<H32),MIN(Assumptions!$D$92,Tax_Bands!H$17),0) -> 9000 | I35: =IF(AND(I5>=Assumptions!$D$93,I5<=Assumptions!$D$94,I33<I32),MIN(Assumptions!$D$92,Tax_Bands!I$17),0) -> 0 | J35: =IF(AND(J5>=Assumptions!$D$93,J5<=Assumptions!$D$94,J33<J32),MIN(Assumptions!$D$92,Tax_Bands!J$17),0) -> 0 | ... AF35: =IF(AND(AF5>=Assumptions!$D$93,AF5<=Assumptions!$D$94,AF33<AF32),MIN(Assumptions!$D$92,Tax_Bands!AF$17),0) -> 0
B36: Add: investment growth at the Junior ISA rate | C36: =C34*Assumptions!$C$32 -> 0 | D36: =D34*Assumptions!$C$32 -> 720 | E36: =E34*Assumptions!$C$32 -> 1497.6 | F36: =F34*Assumptions!$C$32 -> 2337.408 | G36: =G34*Assumptions!$C$32 -> 3244.4006 | H36: =H34*Assumptions!$C$32 -> 4223.9527 | I36: =I34*Assumptions!$C$32 -> 5281.8689 | J36: =J34*Assumptions!$C$32 -> 5704.4184 | ... AF36: =AF34*Assumptions!$C$32 -> 2992.2847
B37: Less: withdrawal to pay the cost | C37: =MIN(C34+C35+C36,C31) -> 0 | D37: =MIN(D34+D35+D36,D31) -> 0 | E37: =MIN(E34+E35+E36,E31) -> 0 | F37: =MIN(F34+F35+F36,F31) -> 0 | G37: =MIN(G34+G35+G36,G31) -> 0 | H37: =MIN(H34+H35+H36,H31) -> 0 | I37: =MIN(I34+I35+I36,I31) -> 0 | J37: =MIN(J34+J35+J36,J31) -> 0 | ... AF37: =MIN(AF34+AF35+AF36,AF31) -> 0
B38: EM — JUNIOR ISA CLOSING BALANCE | C38: =C34+C35+C36-C37 -> 9000 | D38: =D34+D35+D36-D37 -> 18720 | E38: =E34+E35+E36-E37 -> 29217.6 | F38: =F34+F35+F36-F37 -> 40555.008 | G38: =G34+G35+G36-G37 -> 52799.409 | H38: =H34+H35+H36-H37 -> 66023.361 | I38: =I34+I35+I36-I37 -> 71305.23 | J38: =J34+J35+J36-J37 -> 77009.649 | ... AF38: =AF34+AF35+AF36-AF37 -> 40395.843
B39: EM — cost NOT covered by the Junior ISA (falls on the household) | C39: =C31-C37 -> 0 | D39: =D31-D37 -> 0 | E39: =E31-E37 -> 0 | F39: =F31-F37 -> 0 | G39: =G31-G37 -> 0 | H39: =H31-H37 -> 0 | I39: =I31-I37 -> 0 | J39: =J31-J37 -> 0 | ... AF39: =AF31-AF37 -> 0
A42: Child 3 — WHAT HAS TO BE FUNDED, AND THE JUNIOR ISA THAT FUNDS IT
B43: Child 3 — cost falling due this year | C43: =IF(AND(C5>=Assumptions!$E$89,C5<=Assumptions!$E$89+Assumptions!$C$77-1),C14,IF(C5=Assumptions!$E$90,C15,0)) -> 0 | D43: =IF(AND(D5>=Assumptions!$E$89,D5<=Assumptions!$E$89+Assumptions!$C$77-1),D14,IF(D5=Assumptions!$E$90,D15,0)) -> 0 | E43: =IF(AND(E5>=Assumptions!$E$89,E5<=Assumptions!$E$89+Assumptions!$C$77-1),E14,IF(E5=Assumptions!$E$90,E15,0)) -> 0 | F43: =IF(AND(F5>=Assumptions!$E$89,F5<=Assumptions!$E$89+Assumptions!$C$77-1),F14,IF(F5=Assumptions!$E$90,F15,0)) -> 0 | G43: =IF(AND(G5>=Assumptions!$E$89,G5<=Assumptions!$E$89+Assumptions!$C$77-1),G14,IF(G5=Assumptions!$E$90,G15,0)) -> 0 | H43: =IF(AND(H5>=Assumptions!$E$89,H5<=Assumptions!$E$89+Assumptions!$C$77-1),H14,IF(H5=Assumptions!$E$90,H15,0)) -> 0 | I43: =IF(AND(I5>=Assumptions!$E$89,I5<=Assumptions!$E$89+Assumptions!$C$77-1),I14,IF(I5=Assumptions!$E$90,I15,0)) -> 0 | J43: =IF(AND(J5>=Assumptions!$E$89,J5<=Assumptions!$E$89+Assumptions!$C$77-1),J14,IF(J5=Assumptions!$E$90,J15,0)) -> 0 | ... AF43: =IF(AND(AF5>=Assumptions!$E$89,AF5<=Assumptions!$E$89+Assumptions!$C$77-1),AF14,IF(AF5=Assumptions!$E$90,AF15,0)) -> 0
B44: Child 3 — Junior ISA fund needed at the start of university | C44: =SUMPRODUCT($C$43:$AF$43/(1+Assumptions!$C$32)^($C$5:$AF$5-Assumptions!$E$89+1)) -> 136669.02 | D44: =SUMPRODUCT($C$43:$AF$43/(1+Assumptions!$C$32)^($C$5:$AF$5-Assumptions!$E$89+1)) -> 136669.02 | E44: =SUMPRODUCT($C$43:$AF$43/(1+Assumptions!$C$32)^($C$5:$AF$5-Assumptions!$E$89+1)) -> 136669.02 | F44: =SUMPRODUCT($C$43:$AF$43/(1+Assumptions!$C$32)^($C$5:$AF$5-Assumptions!$E$89+1)) -> 136669.02 | G44: =SUMPRODUCT($C$43:$AF$43/(1+Assumptions!$C$32)^($C$5:$AF$5-Assumptions!$E$89+1)) -> 136669.02 | H44: =SUMPRODUCT($C$43:$AF$43/(1+Assumptions!$C$32)^($C$5:$AF$5-Assumptions!$E$89+1)) -> 136669.02 | I44: =SUMPRODUCT($C$43:$AF$43/(1+Assumptions!$C$32)^($C$5:$AF$5-Assumptions!$E$89+1)) -> 136669.02 | J44: =SUMPRODUCT($C$43:$AF$43/(1+Assumptions!$C$32)^($C$5:$AF$5-Assumptions!$E$89+1)) -> 136669.02 | ... AF44: =SUMPRODUCT($C$43:$AF$43/(1+Assumptions!$C$32)^($C$5:$AF$5-Assumptions!$E$89+1)) -> 136669.02
B45: Fund projected to university if contributions stopped now | C45: =C46*(1+Assumptions!$C$32)^(Assumptions!$E$89-C5) -> 0 | D45: =D46*(1+Assumptions!$C$32)^(Assumptions!$E$89-D5) -> 0 | E45: =E46*(1+Assumptions!$C$32)^(Assumptions!$E$89-E5) -> 0 | F45: =F46*(1+Assumptions!$C$32)^(Assumptions!$E$89-F5) -> 30833.484 | G45: =G46*(1+Assumptions!$C$32)^(Assumptions!$E$89-G5) -> 59383.006 | H45: =H46*(1+Assumptions!$C$32)^(Assumptions!$E$89-H5) -> 85817.748 | I45: =I46*(1+Assumptions!$C$32)^(Assumptions!$E$89-I5) -> 110294.36 | J45: =J46*(1+Assumptions!$C$32)^(Assumptions!$E$89-J5) -> 132957.89 | ... AF45: =AF46*(1+Assumptions!$C$32)^(Assumptions!$E$89-AF5) -> 17273.619
B46: Junior ISA — opening balance | C46: =Assumptions!$E$91 -> 0 | D46: =C50 -> 0 | E46: =D50 -> 0 | F46: =E50 -> 9000 | G46: =F50 -> 18720 | H46: =G50 -> 29217.6 | I46: =H50 -> 40555.008 | J46: =I50 -> 52799.409 | K46: =J50 -> 66023.361 | ... AF46: =AE50 -> 37292.448
B47: Add: contribution (£9,000 while still needed) | C47: =IF(AND(C5>=Assumptions!$E$93,C5<=Assumptions!$E$94,C45<C44),MIN(Assumptions!$E$92,Tax_Bands!C$17),0) -> 0 | D47: =IF(AND(D5>=Assumptions!$E$93,D5<=Assumptions!$E$94,D45<D44),MIN(Assumptions!$E$92,Tax_Bands!D$17),0) -> 0 | E47: =IF(AND(E5>=Assumptions!$E$93,E5<=Assumptions!$E$94,E45<E44),MIN(Assumptions!$E$92,Tax_Bands!E$17),0) -> 9000 | F47: =IF(AND(F5>=Assumptions!$E$93,F5<=Assumptions!$E$94,F45<F44),MIN(Assumptions!$E$92,Tax_Bands!F$17),0) -> 9000 | G47: =IF(AND(G5>=Assumptions!$E$93,G5<=Assumptions!$E$94,G45<G44),MIN(Assumptions!$E$92,Tax_Bands!G$17),0) -> 9000 | H47: =IF(AND(H5>=Assumptions!$E$93,H5<=Assumptions!$E$94,H45<H44),MIN(Assumptions!$E$92,Tax_Bands!H$17),0) -> 9000 | I47: =IF(AND(I5>=Assumptions!$E$93,I5<=Assumptions!$E$94,I45<I44),MIN(Assumptions!$E$92,Tax_Bands!I$17),0) -> 9000 | J47: =IF(AND(J5>=Assumptions!$E$93,J5<=Assumptions!$E$94,J45<J44),MIN(Assumptions!$E$92,Tax_Bands!J$17),0) -> 9000 | ... AF47: =IF(AND(AF5>=Assumptions!$E$93,AF5<=Assumptions!$E$94,AF45<AF44),MIN(Assumptions!$E$92,Tax_Bands!AF$17),0) -> 0
B48: Add: investment growth at the Junior ISA rate | C48: =C46*Assumptions!$C$32 -> 0 | D48: =D46*Assumptions!$C$32 -> 0 | E48: =E46*Assumptions!$C$32 -> 0 | F48: =F46*Assumptions!$C$32 -> 720 | G48: =G46*Assumptions!$C$32 -> 1497.6 | H48: =H46*Assumptions!$C$32 -> 2337.408 | I48: =I46*Assumptions!$C$32 -> 3244.4006 | J48: =J46*Assumptions!$C$32 -> 4223.9527 | ... AF48: =AF46*Assumptions!$C$32 -> 2983.3959
B49: Less: withdrawal to pay the cost | C49: =MIN(C46+C47+C48,C43) -> 0 | D49: =MIN(D46+D47+D48,D43) -> 0 | E49: =MIN(E46+E47+E48,E43) -> 0 | F49: =MIN(F46+F47+F48,F43) -> 0 | G49: =MIN(G46+G47+G48,G43) -> 0 | H49: =MIN(H46+H47+H48,H43) -> 0 | I49: =MIN(I46+I47+I48,I43) -> 0 | J49: =MIN(J46+J47+J48,J43) -> 0 | ... AF49: =MIN(AF46+AF47+AF48,AF43) -> 0
B50: Child 3 — JUNIOR ISA CLOSING BALANCE | C50: =C46+C47+C48-C49 -> 0 | D50: =D46+D47+D48-D49 -> 0 | E50: =E46+E47+E48-E49 -> 9000 | F50: =F46+F47+F48-F49 -> 18720 | G50: =G46+G47+G48-G49 -> 29217.6 | H50: =H46+H47+H48-H49 -> 40555.008 | I50: =I46+I47+I48-I49 -> 52799.409 | J50: =J46+J47+J48-J49 -> 66023.361 | ... AF50: =AF46+AF47+AF48-AF49 -> 40275.844
B51: Child 3 — cost NOT covered by the Junior ISA (falls on the household) | C51: =C43-C49 -> 0 | D51: =D43-D49 -> 0 | E51: =E43-E49 -> 0 | F51: =F43-F49 -> 0 | G51: =G43-G49 -> 0 | H51: =H43-H49 -> 0 | I51: =I43-I49 -> 0 | J51: =J43-J49 -> 0 | ... AF51: =AF43-AF49 -> 0
A55: TOTALS
B56: Junior ISA contributions — base case (VM + EM) | C56: =C23+C35 -> 18000 | D56: =D23+D35 -> 18000 | E56: =E23+E35 -> 18000 | F56: =F23+F35 -> 18000 | G56: =G23+G35 -> 9000 | H56: =H23+H35 -> 9000 | I56: =I23+I35 -> 0 | J56: =J23+J35 -> 0 | ... AF56: =AF23+AF35 -> 0
B57: Cost falling on the household — base case | C57: =C27+C39 -> 0 | D57: =D27+D39 -> 0 | E57: =E27+E39 -> 0 | F57: =F27+F39 -> 0 | G57: =G27+G39 -> 0 | H57: =H27+H39 -> 0 | I57: =I27+I39 -> 0 | J57: =J27+J39 -> 0 | ... AF57: =AF27+AF39 -> 0
B58: Children's Junior ISA assets at year end — base case | C58: =C26+C38 -> 34200 | D58: =D26+D38 -> 54936 | E58: =E26+E38 -> 77330.88 | F58: =F26+F38 -> 101517.35 | G58: =G26+G38 -> 118638.74 | H58: =H26+H38 -> 137129.84 | I58: =I26+I38 -> 148100.22 | J58: =J26+J38 -> 159948.24 | ... AF58: =AF26+AF38 -> 42267.392
A59: CHILD 3 — EXTRA COSTS (third-child scenario only)
B60: Child 3 — months of nursery charged | C60: =IF(OR(C5<Assumptions!$E$84,C5>Assumptions!$E$86),0,IF(C5=Assumptions!$E$84,Assumptions!$E$85,IF(C5=Assumptions!$E$86,Assumptions!$E$87,12))) -> 0 | D60: =IF(OR(D5<Assumptions!$E$84,D5>Assumptions!$E$86),0,IF(D5=Assumptions!$E$84,Assumptions!$E$85,IF(D5=Assumptions!$E$86,Assumptions!$E$87,12))) -> 0 | E60: =IF(OR(E5<Assumptions!$E$84,E5>Assumptions!$E$86),0,IF(E5=Assumptions!$E$84,Assumptions!$E$85,IF(E5=Assumptions!$E$86,Assumptions!$E$87,12))) -> 4 | F60: =IF(OR(F5<Assumptions!$E$84,F5>Assumptions!$E$86),0,IF(F5=Assumptions!$E$84,Assumptions!$E$85,IF(F5=Assumptions!$E$86,Assumptions!$E$87,12))) -> 12 | G60: =IF(OR(G5<Assumptions!$E$84,G5>Assumptions!$E$86),0,IF(G5=Assumptions!$E$84,Assumptions!$E$85,IF(G5=Assumptions!$E$86,Assumptions!$E$87,12))) -> 12 | H60: =IF(OR(H5<Assumptions!$E$84,H5>Assumptions!$E$86),0,IF(H5=Assumptions!$E$84,Assumptions!$E$85,IF(H5=Assumptions!$E$86,Assumptions!$E$87,12))) -> 8 | I60: =IF(OR(I5<Assumptions!$E$84,I5>Assumptions!$E$86),0,IF(I5=Assumptions!$E$84,Assumptions!$E$85,IF(I5=Assumptions!$E$86,Assumptions!$E$87,12))) -> 0 | J60: =IF(OR(J5<Assumptions!$E$84,J5>Assumptions!$E$86),0,IF(J5=Assumptions!$E$84,Assumptions!$E$85,IF(J5=Assumptions!$E$86,Assumptions!$E$87,12))) -> 0 | ... AF60: =IF(OR(AF5<Assumptions!$E$84,AF5>Assumptions!$E$86),0,IF(AF5=Assumptions!$E$84,Assumptions!$E$85,IF(AF5=Assumptions!$E$86,Assumptions!$E$87,12))) -> 0
B61: Child 3 — nursery fees | C61: =C60*Assumptions!$C$68*Assumptions!C$9 -> 0 | D61: =D60*Assumptions!$C$68*Assumptions!D$9 -> 0 | E61: =E60*Assumptions!$C$68*Assumptions!E$9 -> 11681.28 | F61: =F60*Assumptions!$C$68*Assumptions!F$9 -> 35744.717 | G61: =G60*Assumptions!$C$68*Assumptions!G$9 -> 36459.611 | H61: =H60*Assumptions!$C$68*Assumptions!H$9 -> 24792.536 | I61: =I60*Assumptions!$C$68*Assumptions!I$9 -> 0 | J61: =J60*Assumptions!$C$68*Assumptions!J$9 -> 0 | ... AF61: =AF60*Assumptions!$C$68*Assumptions!AF$9 -> 0
B62: Child 3 — extra general family spending | C62: =IF(C5<Assumptions!$C$98,0,IF(C5=Assumptions!$C$98,13-Assumptions!$C$99,12))*Assumptions!$C$72*Assumptions!C$9 -> 0 | D62: =IF(D5<Assumptions!$C$98,0,IF(D5=Assumptions!$C$98,13-Assumptions!$C$99,12))*Assumptions!$C$72*Assumptions!D$9 -> 3120 | E62: =IF(E5<Assumptions!$C$98,0,IF(E5=Assumptions!$C$98,13-Assumptions!$C$99,12))*Assumptions!$C$72*Assumptions!E$9 -> 6489.6 | F62: =IF(F5<Assumptions!$C$98,0,IF(F5=Assumptions!$C$98,13-Assumptions!$C$99,12))*Assumptions!$C$72*Assumptions!F$9 -> 6619.392 | G62: =IF(G5<Assumptions!$C$98,0,IF(G5=Assumptions!$C$98,13-Assumptions!$C$99,12))*Assumptions!$C$72*Assumptions!G$9 -> 6751.7798 | H62: =IF(H5<Assumptions!$C$98,0,IF(H5=Assumptions!$C$98,13-Assumptions!$C$99,12))*Assumptions!$C$72*Assumptions!H$9 -> 6886.8154 | I62: =IF(I5<Assumptions!$C$98,0,IF(I5=Assumptions!$C$98,13-Assumptions!$C$99,12))*Assumptions!$C$72*Assumptions!I$9 -> 7024.5517 | J62: =IF(J5<Assumptions!$C$98,0,IF(J5=Assumptions!$C$98,13-Assumptions!$C$99,12))*Assumptions!$C$72*Assumptions!J$9 -> 7165.0428 | ... AF62: =IF(AF5<Assumptions!$C$98,0,IF(AF5=Assumptions!$C$98,13-Assumptions!$C$99,12))*Assumptions!$C$72*Assumptions!AF$9 -> 11077.01
B63: Junior ISA contributions — three children | C63: =C56+C47 -> 18000 | D63: =D56+D47 -> 18000 | E63: =E56+E47 -> 27000 | F63: =F56+F47 -> 27000 | G63: =G56+G47 -> 18000 | H63: =H56+H47 -> 18000 | I63: =I56+I47 -> 9000 | J63: =J56+J47 -> 9000 | ... AF63: =AF56+AF47 -> 0
B64: Cost falling on the household — three children | C64: =C57+C51 -> 0 | D64: =D57+D51 -> 0 | E64: =E57+E51 -> 0 | F64: =F57+F51 -> 0 | G64: =G57+G51 -> 0 | H64: =H57+H51 -> 0 | I64: =I57+I51 -> 0 | J64: =J57+J51 -> 0 | ... AF64: =AF57+AF51 -> 0
B65: Children's Junior ISA assets — three children | C65: =C58+C50 -> 34200 | D65: =D58+D50 -> 54936 | E65: =E58+E50 -> 86330.88 | F65: =F58+F50 -> 120237.35 | G65: =G58+G50 -> 147856.34 | H65: =H58+H50 -> 177684.85 | I65: =I58+I50 -> 200899.63 | J65: =J58+J50 -> 225971.6 | ... AF65: =AF58+AF50 -> 82543.237

Sheet Household_Base
A1: HOUSEHOLD — BASE CASE (BOTH WORKING, TWO CHILDREN)
A2: Contributions are now DERIVED, not assumed. Expenses and Junior ISAs are paid first; whatever cash is left funds the SIPPs up to the remaining annual allowance, then the ISAs up to £20,000 each, then a taxable account. Net cash flow can never go negative — if there is not enough cash the SIPP and ISA contributions are cut instead.
A4: TIMELINE
B5: Year | C5: 2026 | D5: 2027 | E5: 2028 | F5: 2029 | G5: 2030 | H5: 2031 | I5: 2032 | J5: 2033 | K5: 2034 | L5: 2035 | M5: 2036 | N5: 2037 | O5: 2038 | P5: 2039 | Q5: 2040 | R5: 2041 | S5: 2042 | T5: 2043 | U5: 2044 | V5: 2045 | W5: 2046 | X5: 2047 | Y5: 2048 | Z5: 2049 | AA5: 2050 | AB5: 2051 | AC5: 2052 | AD5: 2053 | AE5: 2054 | AF5: 2055
B6: Inflation index | C6: =Assumptions!C$9 -> 1 | D6: =Assumptions!D$9 -> 1.04 | E6: =Assumptions!E$9 -> 1.0816 | F6: =Assumptions!F$9 -> 1.103232 | G6: =Assumptions!G$9 -> 1.1252966 | H6: =Assumptions!H$9 -> 1.1478026 | I6: =Assumptions!I$9 -> 1.1707586 | J6: =Assumptions!J$9 -> 1.1941738 | ... AF6: =Assumptions!AF$9 -> 1.8461684
A7: INCOME
B8: MM — net pay (before any personal SIPP contribution) | C8: =MM_Income!C$22 -> 98036.4 | D8: =MM_Income!D$22 -> 101255.4 | E8: =MM_Income!E$22 -> 104834.16 | F8: =MM_Income!F$22 -> 106695.12 | G8: =MM_Income!G$22 -> 108593.29 | H8: =MM_Income!H$22 -> 110765.16 | I8: =MM_Income!I$22 -> 112980.46 | J8: =MM_Income!J$22 -> 115240.07 | ... AF8: =MM_Income!AF$22 -> 178158.8
B9: DM — net pay (before any personal SIPP contribution) | C9: =DM_Income!C$22 -> 103906.4 | D9: =DM_Income!D$22 -> 107591.2 | E9: =DM_Income!E$22 -> 111423.39 | F9: =DM_Income!F$22 -> 113416.13 | G9: =DM_Income!G$22 -> 115448.73 | H9: =DM_Income!H$22 -> 117757.7 | I9: =DM_Income!I$22 -> 120112.86 | J9: =DM_Income!J$22 -> 122515.11 | ... AF9: =DM_Income!AF$22 -> 189405.87
B10: TOTAL NET PAY | C10: =C8+C9 -> 201942.8 | D10: =D8+D9 -> 208846.6 | E10: =E8+E9 -> 216257.55 | F10: =F8+F9 -> 220111.25 | G10: =G8+G9 -> 224042.02 | H10: =H8+H9 -> 228522.86 | I10: =I8+I9 -> 233093.31 | J10: =J8+J9 -> 237755.18 | ... AF10: =AF8+AF9 -> 367564.67
A11: HOUSEHOLD EXPENSES (2026 amounts, inflated every year)
B12: MM — personal expenses | C12: =12*Assumptions!$C$27*C$6 -> 12000 | D12: =12*Assumptions!$C$27*D$6 -> 12480 | E12: =12*Assumptions!$C$27*E$6 -> 12979.2 | F12: =12*Assumptions!$C$27*F$6 -> 13238.784 | G12: =12*Assumptions!$C$27*G$6 -> 13503.56 | H12: =12*Assumptions!$C$27*H$6 -> 13773.631 | I12: =12*Assumptions!$C$27*I$6 -> 14049.103 | J12: =12*Assumptions!$C$27*J$6 -> 14330.086 | ... AF12: =12*Assumptions!$C$27*AF$6 -> 22154.021
B13: DM — personal expenses | C13: =12*Assumptions!$D$27*C$6 -> 9600 | D13: =12*Assumptions!$D$27*D$6 -> 9984 | E13: =12*Assumptions!$D$27*E$6 -> 10383.36 | F13: =12*Assumptions!$D$27*F$6 -> 10591.027 | G13: =12*Assumptions!$D$27*G$6 -> 10802.848 | H13: =12*Assumptions!$D$27*H$6 -> 11018.905 | I13: =12*Assumptions!$D$27*I$6 -> 11239.283 | J13: =12*Assumptions!$D$27*J$6 -> 11464.068 | ... AF13: =12*Assumptions!$D$27*AF$6 -> 17723.217
B14: Mortgage (19-year term from 2026) | C14: =IF(C5<=Assumptions!$C$64,12*Assumptions!$C$62*C$6,0) -> 23400 | D14: =IF(D5<=Assumptions!$C$64,12*Assumptions!$C$62*D$6,0) -> 24336 | E14: =IF(E5<=Assumptions!$C$64,12*Assumptions!$C$62*E$6,0) -> 25309.44 | F14: =IF(F5<=Assumptions!$C$64,12*Assumptions!$C$62*F$6,0) -> 25815.629 | G14: =IF(G5<=Assumptions!$C$64,12*Assumptions!$C$62*G$6,0) -> 26331.941 | H14: =IF(H5<=Assumptions!$C$64,12*Assumptions!$C$62*H$6,0) -> 26858.58 | I14: =IF(I5<=Assumptions!$C$64,12*Assumptions!$C$62*I$6,0) -> 27395.752 | J14: =IF(J5<=Assumptions!$C$64,12*Assumptions!$C$62*J$6,0) -> 27943.667 | ... AF14: =IF(AF5<=Assumptions!$C$64,12*Assumptions!$C$62*AF$6,0) -> 0
B15: General family spending | C15: =12*Assumptions!$C$65*C$6 -> 24000 | D15: =12*Assumptions!$C$65*D$6 -> 24960 | E15: =12*Assumptions!$C$65*E$6 -> 25958.4 | F15: =12*Assumptions!$C$65*F$6 -> 26477.568 | G15: =12*Assumptions!$C$65*G$6 -> 27007.119 | H15: =12*Assumptions!$C$65*H$6 -> 27547.262 | I15: =12*Assumptions!$C$65*I$6 -> 28098.207 | J15: =12*Assumptions!$C$65*J$6 -> 28660.171 | ... AF15: =12*Assumptions!$C$65*AF$6 -> 44308.042
B16: Nannies | C16: =Children!C$12 -> 18000 | D16: =Children!D$12 -> 18720 | E16: =Children!E$12 -> 19468.8 | F16: =Children!F$12 -> 19858.176 | G16: =Children!G$12 -> 20255.34 | H16: =Children!H$12 -> 20660.446 | I16: =Children!I$12 -> 21073.655 | J16: =Children!J$12 -> 21495.128 | ... AF16: =Children!AF$12 -> 0
B17: Nursery — EM | C17: =Children!C$11 -> 32400 | D17: =Children!D$11 -> 33696 | E17: =Children!E$11 -> 23362.56 | F17: =Children!F$11 -> 0 | G17: =Children!G$11 -> 0 | H17: =Children!H$11 -> 0 | I17: =Children!I$11 -> 0 | J17: =Children!J$11 -> 0 | ... AF17: =Children!AF$11 -> 0
B18: Travel — China | C18: =Assumptions!$C$69*C$6 -> 3000 | D18: =Assumptions!$C$69*D$6 -> 3120 | E18: =Assumptions!$C$69*E$6 -> 3244.8 | F18: =Assumptions!$C$69*F$6 -> 3309.696 | G18: =Assumptions!$C$69*G$6 -> 3375.8899 | H18: =Assumptions!$C$69*H$6 -> 3443.4077 | I18: =Assumptions!$C$69*I$6 -> 3512.2759 | J18: =Assumptions!$C$69*J$6 -> 3582.5214 | ... AF18: =Assumptions!$C$69*AF$6 -> 5538.5052
B19: Travel — Italy | C19: =Assumptions!$C$70*C$6 -> 1000 | D19: =Assumptions!$C$70*D$6 -> 1040 | E19: =Assumptions!$C$70*E$6 -> 1081.6 | F19: =Assumptions!$C$70*F$6 -> 1103.232 | G19: =Assumptions!$C$70*G$6 -> 1125.2966 | H19: =Assumptions!$C$70*H$6 -> 1147.8026 | I19: =Assumptions!$C$70*I$6 -> 1170.7586 | J19: =Assumptions!$C$70*J$6 -> 1194.1738 | ... AF19: =Assumptions!$C$70*AF$6 -> 1846.1684
B20: Travel — family holiday | C20: =Assumptions!$C$71*C$6 -> 2000 | D20: =Assumptions!$C$71*D$6 -> 2080 | E20: =Assumptions!$C$71*E$6 -> 2163.2 | F20: =Assumptions!$C$71*F$6 -> 2206.464 | G20: =Assumptions!$C$71*G$6 -> 2250.5933 | H20: =Assumptions!$C$71*H$6 -> 2295.6051 | I20: =Assumptions!$C$71*I$6 -> 2341.5172 | J20: =Assumptions!$C$71*J$6 -> 2388.3476 | ... AF20: =Assumptions!$C$71*AF$6 -> 3692.3368
B21: University / London year not covered by the Junior ISAs | C21: =Children!C$57 -> 0 | D21: =Children!D$57 -> 0 | E21: =Children!E$57 -> 0 | F21: =Children!F$57 -> 0 | G21: =Children!G$57 -> 0 | H21: =Children!H$57 -> 0 | I21: =Children!I$57 -> 0 | J21: =Children!J$57 -> 0 | ... AF21: =Children!AF$57 -> 0
B22: TOTAL HOUSEHOLD EXPENSES | C22: =SUM(C12:C21) -> 125400 | D22: =SUM(D12:D21) -> 130416 | E22: =SUM(E12:E21) -> 123951.36 | F22: =SUM(F12:F21) -> 102600.58 | G22: =SUM(G12:G21) -> 104652.59 | H22: =SUM(H12:H21) -> 106745.64 | I22: =SUM(I12:I21) -> 108880.55 | J22: =SUM(J12:J21) -> 111058.16 | ... AF22: =SUM(AF12:AF21) -> 95262.29
B23: memo: total expenses in 2026 money | C23: =C22/C$6 -> 125400 | D23: =D22/D$6 -> 125400 | E23: =E22/E$6 -> 114600 | F23: =F22/F$6 -> 93000 | G23: =G22/G$6 -> 93000 | H23: =H22/H$6 -> 93000 | I23: =I22/I$6 -> 93000 | J23: =J22/J$6 -> 93000 | ... AF23: =AF22/AF$6 -> 51600
B24: memo: adult-only expenses (no childcare, no children's costs) | C24: =C12+C13+C14+C15+C18+C19+C20 -> 75000 | D24: =D12+D13+D14+D15+D18+D19+D20 -> 78000 | E24: =E12+E13+E14+E15+E18+E19+E20 -> 81120 | F24: =F12+F13+F14+F15+F18+F19+F20 -> 82742.4 | G24: =G12+G13+G14+G15+G18+G19+G20 -> 84397.248 | H24: =H12+H13+H14+H15+H18+H19+H20 -> 86085.193 | I24: =I12+I13+I14+I15+I18+I19+I20 -> 87806.897 | J24: =J12+J13+J14+J15+J18+J19+J20 -> 89563.035 | ... AF24: =AF12+AF13+AF14+AF15+AF18+AF19+AF20 -> 95262.29
A25: SAVINGS WATERFALL — WHAT IS ACTUALLY AFFORDABLE
B26: Junior ISA contributions | C26: =Children!C$56 -> 18000 | D26: =Children!D$56 -> 18000 | E26: =Children!E$56 -> 18000 | F26: =Children!F$56 -> 18000 | G26: =Children!G$56 -> 9000 | H26: =Children!H$56 -> 9000 | I26: =Children!I$56 -> 0 | J26: =Children!J$56 -> 0 | ... AF26: =Children!AF$56 -> 0
B27: CASH LEFT AFTER EXPENSES AND JUNIOR ISAs | C27: =C10-C22-C26 -> 58542.8 | D27: =D10-D22-D26 -> 60430.6 | E27: =E10-E22-E26 -> 74306.192 | F27: =F10-F22-F26 -> 99510.671 | G27: =G10-G22-G26 -> 110389.43 | H27: =H10-H22-H26 -> 112777.22 | I27: =I10-I22-I26 -> 124212.76 | J27: =J10-J22-J26 -> 126697.02 | ... AF27: =AF10-AF22-AF26 -> 272302.38
B28: CHECK — net pay does not cover expenses (1 = yes) | C28: =IF(C27<0,1,0) -> 0 | D28: =IF(D27<0,1,0) -> 0 | E28: =IF(E27<0,1,0) -> 0 | F28: =IF(F27<0,1,0) -> 0 | G28: =IF(G27<0,1,0) -> 0 | H28: =IF(H27<0,1,0) -> 0 | I28: =IF(I27<0,1,0) -> 0 | J28: =IF(J27<0,1,0) -> 0 | ... AF28: =IF(AF27<0,1,0) -> 0
B29: MM — SIPP headroom | C29: =MM_Income!C$15 -> 39000 | D29: =MM_Income!D$15 -> 36900 | E29: =MM_Income!E$15 -> 35976 | F29: =MM_Income!F$15 -> 35495.52 | G29: =MM_Income!G$15 -> 35005.43 | H29: =MM_Income!H$15 -> 35705.539 | I29: =MM_Income!I$15 -> 36419.65 | J29: =MM_Income!J$15 -> 37148.043 | ... AF29: =MM_Income!AF$15 -> 57430.119
B30: DM — SIPP headroom | C30: =DM_Income!C$15 -> 28800 | D30: =DM_Income!D$15 -> 27552 | E30: =DM_Income!E$15 -> 26254.08 | F30: =DM_Income!F$15 -> 25579.162 | G30: =DM_Income!G$15 -> 24890.745 | H30: =DM_Income!H$15 -> 25388.56 | I30: =DM_Income!I$15 -> 25896.331 | J30: =DM_Income!J$15 -> 26414.258 | ... AF30: =DM_Income!AF$15 -> 40835.905
B31: Total SIPP headroom | C31: =C29+C30 -> 67800 | D31: =D29+D30 -> 64452 | E31: =E29+E30 -> 62230.08 | F31: =F29+F30 -> 61074.682 | G31: =G29+G30 -> 59896.175 | H31: =H29+H30 -> 61094.099 | I31: =I29+I30 -> 62315.981 | J31: =J29+J30 -> 63562.3 | ... AF31: =AF29+AF30 -> 98266.024
B32: Cash needed to fill it (80% of gross — HMRC adds the other 20%) | C32: =(1-Tax_Bands!C$18)*C31 -> 54240 | D32: =(1-Tax_Bands!D$18)*D31 -> 51561.6 | E32: =(1-Tax_Bands!E$18)*E31 -> 49784.064 | F32: =(1-Tax_Bands!F$18)*F31 -> 48859.745 | G32: =(1-Tax_Bands!G$18)*G31 -> 47916.94 | H32: =(1-Tax_Bands!H$18)*H31 -> 48875.279 | I32: =(1-Tax_Bands!I$18)*I31 -> 49852.785 | J32: =(1-Tax_Bands!J$18)*J31 -> 50849.84 | ... AF32: =(1-Tax_Bands!AF$18)*AF31 -> 78612.819
B33: Funding factor (1.00 = the SIPPs can be filled in full) | C33: =IF(OR(C31<=0,C27<=0),0,MIN(1,C27/C32)) -> 1 | D33: =IF(OR(D31<=0,D27<=0),0,MIN(1,D27/D32)) -> 1 | E33: =IF(OR(E31<=0,E27<=0),0,MIN(1,E27/E32)) -> 1 | F33: =IF(OR(F31<=0,F27<=0),0,MIN(1,F27/F32)) -> 1 | G33: =IF(OR(G31<=0,G27<=0),0,MIN(1,G27/G32)) -> 1 | H33: =IF(OR(H31<=0,H27<=0),0,MIN(1,H27/H32)) -> 1 | I33: =IF(OR(I31<=0,I27<=0),0,MIN(1,I27/I32)) -> 1 | J33: =IF(OR(J31<=0,J27<=0),0,MIN(1,J27/J32)) -> 1 | ... AF33: =IF(OR(AF31<=0,AF27<=0),0,MIN(1,AF27/AF32)) -> 1
B34: MM — personal SIPP contribution (gross) | C34: =C33*C29 -> 39000 | D34: =D33*D29 -> 36900 | E34: =E33*E29 -> 35976 | F34: =F33*F29 -> 35495.52 | G34: =G33*G29 -> 35005.43 | H34: =H33*H29 -> 35705.539 | I34: =I33*I29 -> 36419.65 | J34: =J33*J29 -> 37148.043 | ... AF34: =AF33*AF29 -> 57430.119
B35: DM — personal SIPP contribution (gross) | C35: =C33*C30 -> 28800 | D35: =D33*D30 -> 27552 | E35: =E33*E30 -> 26254.08 | F35: =F33*F30 -> 25579.162 | G35: =G33*G30 -> 24890.745 | H35: =H33*H30 -> 25388.56 | I35: =I33*I30 -> 25896.331 | J35: =J33*J30 -> 26414.258 | ... AF35: =AF33*AF30 -> 40835.905
B36: Cash paid out for those contributions | C36: =(1-Tax_Bands!C$18)*(C34+C35) -> 54240 | D36: =(1-Tax_Bands!D$18)*(D34+D35) -> 51561.6 | E36: =(1-Tax_Bands!E$18)*(E34+E35) -> 49784.064 | F36: =(1-Tax_Bands!F$18)*(F34+F35) -> 48859.745 | G36: =(1-Tax_Bands!G$18)*(G34+G35) -> 47916.94 | H36: =(1-Tax_Bands!H$18)*(H34+H35) -> 48875.279 | I36: =(1-Tax_Bands!I$18)*(I34+I35) -> 49852.785 | J36: =(1-Tax_Bands!J$18)*(J34+J35) -> 50849.84 | ... AF36: =(1-Tax_Bands!AF$18)*(AF34+AF35) -> 78612.819
B37: MM personal SIPP (feeds MM_Income) | C37: =C34 -> 39000 | D37: =D34 -> 36900 | E37: =E34 -> 35976 | F37: =F34 -> 35495.52 | G37: =G34 -> 35005.43 | H37: =H34 -> 35705.539 | I37: =I34 -> 36419.65 | J37: =J34 -> 37148.043 | ... AF37: =AF34 -> 57430.119
B38: DM personal SIPP (feeds DM_Income) | C38: =C35 -> 28800 | D38: =D35 -> 27552 | E38: =E35 -> 26254.08 | F38: =F35 -> 25579.162 | G38: =G35 -> 24890.745 | H38: =H35 -> 25388.56 | I38: =I35 -> 25896.331 | J38: =J35 -> 26414.258 | ... AF38: =AF35 -> 40835.905
B39: Higher / additional-rate relief recovered | C39: =MM_Income!C$29+DM_Income!C$29 -> 17121 | D39: =MM_Income!D$29+DM_Income!D$29 -> 16113 | E39: =MM_Income!E$29+DM_Income!E$29 -> 15557.52 | F39: =MM_Income!F$29+DM_Income!F$29 -> 15268.67 | G39: =MM_Income!G$29+DM_Income!G$29 -> 14974.044 | H39: =MM_Income!H$29+DM_Income!H$29 -> 15273.525 | I39: =MM_Income!I$29+DM_Income!I$29 -> 15578.995 | J39: =MM_Income!J$29+DM_Income!J$29 -> 15890.575 | ... AF39: =MM_Income!AF$29+DM_Income!AF$29 -> 24566.506
B40: CASH LEFT AFTER THE SIPPs | C40: =C27-C36+C39 -> 21423.8 | D40: =D27-D36+D39 -> 24982 | E40: =E27-E36+E39 -> 40079.648 | F40: =F27-F36+F39 -> 65919.596 | G40: =G27-G36+G39 -> 77446.532 | H40: =H27-H36+H39 -> 79175.463 | I40: =I27-I36+I39 -> 89938.972 | J40: =J27-J36+J39 -> 91737.751 | ... AF40: =AF27-AF36+AF39 -> 218256.07
B41: MM — ISA contribution | C41: =MIN(Tax_Bands!C$16,MAX(0,C40)/2) -> 10711.9 | D41: =MIN(Tax_Bands!D$16,MAX(0,D40)/2) -> 12491 | E41: =MIN(Tax_Bands!E$16,MAX(0,E40)/2) -> 20000 | F41: =MIN(Tax_Bands!F$16,MAX(0,F40)/2) -> 20000 | G41: =MIN(Tax_Bands!G$16,MAX(0,G40)/2) -> 20000 | H41: =MIN(Tax_Bands!H$16,MAX(0,H40)/2) -> 20400 | I41: =MIN(Tax_Bands!I$16,MAX(0,I40)/2) -> 20808 | J41: =MIN(Tax_Bands!J$16,MAX(0,J40)/2) -> 21224.16 | ... AF41: =MIN(Tax_Bands!AF$16,MAX(0,AF40)/2) -> 32812.12
B42: DM — ISA contribution | C42: =MIN(Tax_Bands!C$16,MAX(0,C40)-C41) -> 10711.9 | D42: =MIN(Tax_Bands!D$16,MAX(0,D40)-D41) -> 12491 | E42: =MIN(Tax_Bands!E$16,MAX(0,E40)-E41) -> 20000 | F42: =MIN(Tax_Bands!F$16,MAX(0,F40)-F41) -> 20000 | G42: =MIN(Tax_Bands!G$16,MAX(0,G40)-G41) -> 20000 | H42: =MIN(Tax_Bands!H$16,MAX(0,H40)-H41) -> 20400 | I42: =MIN(Tax_Bands!I$16,MAX(0,I40)-I41) -> 20808 | J42: =MIN(Tax_Bands!J$16,MAX(0,J40)-J41) -> 21224.16 | ... AF42: =MIN(Tax_Bands!AF$16,MAX(0,AF40)-AF41) -> 32812.12
B43: Total ISA contribution | C43: =C41+C42 -> 21423.8 | D43: =D41+D42 -> 24982 | E43: =E41+E42 -> 40000 | F43: =F41+F42 -> 40000 | G43: =G41+G42 -> 40000 | H43: =H41+H42 -> 40800 | I43: =I41+I42 -> 41616 | J43: =J41+J42 -> 42448.32 | ... AF43: =AF41+AF42 -> 65624.24
B44: NET CASH FLOW LEFT OVER (goes to taxable savings) | C44: =C40-C43 -> 0 | D44: =D40-D43 -> 0 | E44: =E40-E43 -> 79.648 | F44: =F40-F43 -> 25919.596 | G44: =G40-G43 -> 37446.532 | H44: =H40-H43 -> 38375.463 | I44: =I40-I43 -> 48322.972 | J44: =J40-J43 -> 49289.431 | ... AF44: =AF40-AF43 -> 152631.83
A45: WHAT GOES INTO LONG-TERM SAVINGS EACH YEAR
B46: Into pensions (employee + employer + personal SIPP) | C46: =MM_Income!C$12+DM_Income!C$12+C34+C35 -> 120000 | D46: =MM_Income!D$12+DM_Income!D$12+D34+D35 -> 120000 | E46: =MM_Income!E$12+DM_Income!E$12+E34+E35 -> 120000 | F46: =MM_Income!F$12+DM_Income!F$12+F34+F35 -> 120000 | G46: =MM_Income!G$12+DM_Income!G$12+G34+G35 -> 120000 | H46: =MM_Income!H$12+DM_Income!H$12+H34+H35 -> 122400 | I46: =MM_Income!I$12+DM_Income!I$12+I34+I35 -> 124848 | J46: =MM_Income!J$12+DM_Income!J$12+J34+J35 -> 127344.96 | ... AF46: =MM_Income!AF$12+DM_Income!AF$12+AF34+AF35 -> 196872.72
B47: Into ISAs | C47: =C43 -> 21423.8 | D47: =D43 -> 24982 | E47: =E43 -> 40000 | F47: =F43 -> 40000 | G47: =G43 -> 40000 | H47: =H43 -> 40800 | I47: =I43 -> 41616 | J47: =J43 -> 42448.32 | ... AF47: =AF43 -> 65624.24
B48: Into Junior ISAs | C48: =C26 -> 18000 | D48: =D26 -> 18000 | E48: =E26 -> 18000 | F48: =F26 -> 18000 | G48: =G26 -> 9000 | H48: =H26 -> 9000 | I48: =I26 -> 0 | J48: =J26 -> 0 | ... AF48: =AF26 -> 0
B49: Into taxable savings | C49: =C44 -> 0 | D49: =D44 -> 0 | E49: =E44 -> 79.648 | F49: =F44 -> 25919.596 | G49: =G44 -> 37446.532 | H49: =H44 -> 38375.463 | I49: =I44 -> 48322.972 | J49: =J44 -> 49289.431 | ... AF49: =AF44 -> 152631.83
B50: TOTAL SAVED | C50: =SUM(C46:C49) -> 159423.8 | D50: =SUM(D46:D49) -> 162982 | E50: =SUM(E46:E49) -> 178079.65 | F50: =SUM(F46:F49) -> 203919.6 | G50: =SUM(G46:G49) -> 206446.53 | H50: =SUM(H46:H49) -> 210575.46 | I50: =SUM(I46:I49) -> 214786.97 | J50: =SUM(J46:J49) -> 219082.71 | ... AF50: =SUM(AF46:AF49) -> 415128.79
A51: BALANCE SHEET AT YEAR END
B52: Taxable savings — opening | C52: 0 | D52: =C55 -> 0 | E52: =D55 -> 0 | F52: =E55 -> 79.648 | G52: =F55 -> 26004.421 | H52: =G55 -> 65141.241 | I52: =H55 -> 107750.88 | J52: =I55 -> 163077.66 | K52: =J55 -> 222967.14 | ... AF52: =AE55 -> 3489873
B53: Add: growth | C53: =C52*Returns!C$12 -> 0 | D53: =D52*Returns!D$12 -> 0 | E53: =E52*Returns!E$12 -> 0 | F53: =F52*Returns!F$12 -> 5.17712 | G53: =G52*Returns!G$12 -> 1690.2874 | H53: =H52*Returns!H$12 -> 4234.1806 | I53: =I52*Returns!I$12 -> 7003.8075 | J53: =J52*Returns!J$12 -> 10600.048 | ... AF53: =AF52*Returns!AF$12 -> 33153.794
B54: Add / (less): net cash flow | C54: =C44 -> 0 | D54: =D44 -> 0 | E54: =E44 -> 79.648 | F54: =F44 -> 25919.596 | G54: =G44 -> 37446.532 | H54: =H44 -> 38375.463 | I54: =I44 -> 48322.972 | J54: =J44 -> 49289.431 | ... AF54: =AF44 -> 152631.83
B55: Taxable savings — closing | C55: =MAX(0,C52+C53+C54) -> 0 | D55: =MAX(0,D52+D53+D54) -> 0 | E55: =MAX(0,E52+E53+E54) -> 79.648 | F55: =MAX(0,F52+F53+F54) -> 26004.421 | G55: =MAX(0,G52+G53+G54) -> 65141.241 | H55: =MAX(0,H52+H53+H54) -> 107750.88 | I55: =MAX(0,I52+I53+I54) -> 163077.66 | J55: =MAX(0,J52+J53+J54) -> 222967.14 | ... AF55: =MAX(0,AF52+AF53+AF54) -> 3675658.6
B56: Drawdown required from the ISA | C56: =MAX(0,-(C52+C53+C54)) -> 0 | D56: =MAX(0,-(D52+D53+D54)) -> 0 | E56: =MAX(0,-(E52+E53+E54)) -> 0 | F56: =MAX(0,-(F52+F53+F54)) -> 0 | G56: =MAX(0,-(G52+G53+G54)) -> 0 | H56: =MAX(0,-(H52+H53+H54)) -> 0 | I56: =MAX(0,-(I52+I53+I54)) -> 0 | J56: =MAX(0,-(J52+J53+J54)) -> 0 | ... AF56: =MAX(0,-(AF52+AF53+AF54)) -> 0
B57: Household ISA — opening | C57: =Assumptions!$C$25+Assumptions!$D$25 -> 260000 | D57: =C61 -> 302223.8 | E57: =D61 -> 351383.7 | F57: =E61 -> 419494.4 | G57: =F61 -> 493053.95 | H57: =G61 -> 572498.27 | I57: =H61 -> 659098.13 | J57: =I61 -> 753441.98 | K57: =J61 -> 856165.66 | ... AF57: =AE61 -> 4512682.3
B58: Add: contributions | C58: =C43 -> 21423.8 | D58: =D43 -> 24982 | E58: =E43 -> 40000 | F58: =F43 -> 40000 | G58: =G43 -> 40000 | H58: =H43 -> 40800 | I58: =I43 -> 41616 | J58: =J43 -> 42448.32 | ... AF58: =AF43 -> 65624.24
B59: Add: growth | C59: =C57*Returns!C$11 -> 20800 | D59: =D57*Returns!D$11 -> 24177.904 | E59: =E57*Returns!E$11 -> 28110.696 | F59: =F57*Returns!F$11 -> 33559.552 | G59: =G57*Returns!G$11 -> 39444.316 | H59: =H57*Returns!H$11 -> 45799.861 | I59: =I57*Returns!I$11 -> 52727.85 | J59: =J57*Returns!J$11 -> 60275.358 | ... AF59: =AF57*Returns!AF$11 -> 110560.72
B60: Less: drawdown | C60: =-C56 -> 0 | D60: =-D56 -> 0 | E60: =-E56 -> 0 | F60: =-F56 -> 0 | G60: =-G56 -> 0 | H60: =-H56 -> 0 | I60: =-I56 -> 0 | J60: =-J56 -> 0 | ... AF60: =-AF56 -> 0
B61: Household ISA — closing | C61: =MAX(0,C57+C58+C59+C60) -> 302223.8 | D61: =MAX(0,D57+D58+D59+D60) -> 351383.7 | E61: =MAX(0,E57+E58+E59+E60) -> 419494.4 | F61: =MAX(0,F57+F58+F59+F60) -> 493053.95 | G61: =MAX(0,G57+G58+G59+G60) -> 572498.27 | H61: =MAX(0,H57+H58+H59+H60) -> 659098.13 | I61: =MAX(0,I57+I58+I59+I60) -> 753441.98 | J61: =MAX(0,J57+J58+J59+J60) -> 856165.66 | ... AF61: =MAX(0,AF57+AF58+AF59+AF60) -> 4688867.3
B62: MM pension — closing | C62: =MM_Income!C$37 -> 578400 | D62: =MM_Income!D$37 -> 684672 | E62: =MM_Income!E$37 -> 799445.76 | F62: =MM_Income!F$37 -> 923401.42 | G62: =MM_Income!G$37 -> 1057273.5 | H62: =MM_Income!H$37 -> 1203055.4 | I62: =MM_Income!I$37 -> 1361723.9 | J62: =MM_Income!J$37 -> 1534334.2 | ... AF62: =MM_Income!AF$37 -> 9493532.9
B63: DM pension — closing | C63: =DM_Income!C$37 -> 880800 | D63: =DM_Income!D$37 -> 1011264 | E63: =DM_Income!E$37 -> 1152165.1 | F63: =DM_Income!F$37 -> 1304338.3 | G63: =DM_Income!G$37 -> 1468685.4 | H63: =DM_Income!H$37 -> 1647380.2 | I63: =DM_Income!I$37 -> 1841594.6 | J63: =DM_Income!J$37 -> 2047069.9 | ... AF63: =DM_Income!AF$37 -> 7672981.2
B64: HOUSEHOLD PENSIONS | C64: =C62+C63 -> 1459200 | D64: =D62+D63 -> 1695936 | E64: =E62+E63 -> 1951610.9 | F64: =F62+F63 -> 2227739.8 | G64: =G62+G63 -> 2525958.9 | H64: =H62+H63 -> 2850435.6 | I64: =I62+I63 -> 3203318.5 | J64: =J62+J63 -> 3581404.2 | ... AF64: =AF62+AF63 -> 17166514
B65: LIQUID SAVINGS (ISA + taxable) | C65: =C55+C61 -> 302223.8 | D65: =D55+D61 -> 351383.7 | E65: =E55+E61 -> 419574.05 | F65: =F55+F61 -> 519058.37 | G65: =G55+G61 -> 637639.51 | H65: =H55+H61 -> 766849.01 | I65: =I55+I61 -> 916519.64 | J65: =J55+J61 -> 1079132.8 | ... AF65: =AF55+AF61 -> 8364525.9
B66: TOTAL NET WORTH (excluding the house) | C66: =C65+C64 -> 1761423.8 | D66: =D65+D64 -> 2047319.7 | E66: =E65+E64 -> 2371184.9 | F66: =F65+F64 -> 2746798.1 | G66: =G65+G64 -> 3163598.4 | H66: =H65+H64 -> 3617284.7 | I66: =I65+I64 -> 4119838.1 | J66: =J65+J64 -> 4660537 | ... AF66: =AF65+AF64 -> 25531040
B67: memo: net worth in 2026 money | C67: =C66/C$6 -> 1761423.8 | D67: =D66/D$6 -> 1968576.6 | E67: =E66/E$6 -> 2192293.8 | F67: =F66/F$6 -> 2489773.8 | G67: =G66/G$6 -> 2811346.2 | H67: =H66/H$6 -> 3151486.8 | I67: =I66/I$6 -> 3518947.5 | J67: =J66/J$6 -> 3902729.2 | ... AF67: =AF66/AF$6 -> 13829204
B68: memo: children's Junior ISA assets (theirs, not yours) | C68: =Children!C$58 -> 34200 | D68: =Children!D$58 -> 54936 | E68: =Children!E$58 -> 77330.88 | F68: =Children!F$58 -> 101517.35 | G68: =Children!G$58 -> 118638.74 | H68: =Children!H$58 -> 137129.84 | I68: =Children!I$58 -> 148100.22 | J68: =Children!J$58 -> 159948.24 | ... AF68: =Children!AF$58 -> 42267.392
A69: KEY RATIOS AND CHECKS
B70: MM net pay ÷ (household expenses + Junior ISAs) | C70: =C8/(C22+C26) -> 0.6836569 | D70: =D8/(D22+D26) -> 0.68224046 | E70: =E8/(E22+E26) -> 0.7385217 | F70: =F8/(F22+F26) -> 0.88469822 | G70: =G8/(G22+G26) -> 0.95548453 | H70: =H8/(H22+H26) -> 0.95697044 | I70: =I8/(I22+I26) -> 1.0376551 | J70: =J8/(J22+J26) -> 1.0376551 | ... AF70: =AF8/(AF22+AF26) -> 1.8701923
B71: DM net pay ÷ (household expenses + Junior ISAs) | C71: =C9/(C22+C26) -> 0.72459135 | D71: =D9/(D22+D26) -> 0.72492993 | E71: =E9/(E22+E26) -> 0.78494064 | F71: =F9/(F22+F26) -> 0.94042778 | G71: =G9/(G22+G26) -> 1.0158038 | H71: =H9/(H22+H26) -> 1.0173835 | I71: =I9/(I22+I26) -> 1.1031617 | J71: =J9/(J22+J26) -> 1.1031617 | ... AF71: =AF9/(AF22+AF26) -> 1.9882566
B72: Total net pay ÷ household expenses | C72: =C10/C22 -> 1.6103892 | D72: =D10/D22 -> 1.6013879 | E72: =E10/E22 -> 1.7446969 | F72: =F10/F22 -> 2.1453217 | G72: =G10/G22 -> 2.1408168 | H72: =H10/H22 -> 2.1408168 | I72: =I10/I22 -> 2.1408168 | J72: =J10/J22 -> 2.1408168 | ... AF72: =AF10/AF22 -> 3.8584489
B73: Liquid savings ÷ annual expenses (years of cover) | C73: =C65/C22 -> 2.4100781 | D73: =D65/D22 -> 2.6943297 | E73: =E65/E22 -> 3.3849895 | F73: =F65/F22 -> 5.0590201 | G73: =G65/G22 -> 6.0929168 | H73: =H65/H22 -> 7.1838908 | I73: =I65/I22 -> 8.4176616 | J73: =J65/J22 -> 9.7168256 | ... AF73: =AF65/AF22 -> 87.805216
B74: CHECK — negative net cash flow (must be zero) | C74: =IF(C44<0,1,0) -> 0 | D74: =IF(D44<0,1,0) -> 0 | E74: =IF(E44<0,1,0) -> 0 | F74: =IF(F44<0,1,0) -> 0 | G74: =IF(G44<0,1,0) -> 0 | H74: =IF(H44<0,1,0) -> 0 | I74: =IF(I44<0,1,0) -> 0 | J74: =IF(J44<0,1,0) -> 0 | ... AF74: =IF(AF44<0,1,0) -> 0

Sheet Analysis_DM_Exit
A1: WHEN CAN DM STOP WORKING? — BASE CASE (TWO CHILDREN)
A2: Three rungs. RUNG 1 is the earliest DM could stop and still be safe, living partly off savings as you asked. RUNG 2 is the year MM's pay alone covers everything with no drawdown at all. RUNG 3 adds a comfort margin. Throughout, DM earns NOTHING from the business, and once he stops the household makes no further SIPP or ISA contributions — MM keeps only her contractual workplace pension.
A4: RUNGS 2 AND 3 — CAN MM'S PAY ALONE CARRY THE FAMILY, WITHOUT TOUCHING SAVINGS?
B5: Year | C5: 2026 | D5: 2027 | E5: 2028 | F5: 2029 | G5: 2030 | H5: 2031 | I5: 2032 | J5: 2033 | K5: 2034 | L5: 2035 | M5: 2036 | N5: 2037 | O5: 2038 | P5: 2039 | Q5: 2040 | R5: 2041 | S5: 2042 | T5: 2043 | U5: 2044 | V5: 2045 | W5: 2046 | X5: 2047 | Y5: 2048 | Z5: 2049 | AA5: 2050 | AB5: 2051 | AC5: 2052 | AD5: 2053 | AE5: 2054 | AF5: 2055
B6: MM — net pay | C6: =Household_Base!C$8 -> 98036.4 | D6: =Household_Base!D$8 -> 101255.4 | E6: =Household_Base!E$8 -> 104834.16 | F6: =Household_Base!F$8 -> 106695.12 | G6: =Household_Base!G$8 -> 108593.29 | H6: =Household_Base!H$8 -> 110765.16 | I6: =Household_Base!I$8 -> 112980.46 | J6: =Household_Base!J$8 -> 115240.07 | ... AF6: =Household_Base!AF$8 -> 178158.8
B7: Household expenses + Junior ISA contributions | C7: =Household_Base!C$22+Household_Base!C$26 -> 143400 | D7: =Household_Base!D$22+Household_Base!D$26 -> 148416 | E7: =Household_Base!E$22+Household_Base!E$26 -> 141951.36 | F7: =Household_Base!F$22+Household_Base!F$26 -> 120600.58 | G7: =Household_Base!G$22+Household_Base!G$26 -> 113652.59 | H7: =Household_Base!H$22+Household_Base!H$26 -> 115745.64 | I7: =Household_Base!I$22+Household_Base!I$26 -> 108880.55 | J7: =Household_Base!J$22+Household_Base!J$26 -> 111058.16 | ... AF7: =Household_Base!AF$22+Household_Base!AF$26 -> 95262.29
B8: Coverage — MM's pay alone | C8: =C6/C7 -> 0.6836569 | D8: =D6/D7 -> 0.68224046 | E8: =E6/E7 -> 0.7385217 | F8: =F6/F7 -> 0.88469822 | G8: =G6/G7 -> 0.95548453 | H8: =H6/H7 -> 0.95697044 | I8: =I6/I7 -> 1.0376551 | J8: =J6/J7 -> 1.0376551 | ... AF8: =AF6/AF7 -> 1.8701923
B9: Covers 1.00x from this year onward, for good (1 = yes) | C9: =IF(MIN(C8:$AF$8)>=1,1,0) -> 0 | D9: =IF(MIN(D8:$AF$8)>=1,1,0) -> 0 | E9: =IF(MIN(E8:$AF$8)>=1,1,0) -> 0 | F9: =IF(MIN(F8:$AF$8)>=1,1,0) -> 0 | G9: =IF(MIN(G8:$AF$8)>=1,1,0) -> 0 | H9: =IF(MIN(H8:$AF$8)>=1,1,0) -> 0 | I9: =IF(MIN(I8:$AF$8)>=1,1,0) -> 1 | J9: =IF(MIN(J8:$AF$8)>=1,1,0) -> 1 | ... AF9: =IF(MIN(AF8:$AF$8)>=1,1,0) -> 1
B10: Covers the comfort bar from this year onward, for good (1 = yes) | C10: =IF(MIN(C8:$AF$8)>=Assumptions!$C$115,1,0) -> 0 | D10: =IF(MIN(D8:$AF$8)>=Assumptions!$C$115,1,0) -> 0 | E10: =IF(MIN(E8:$AF$8)>=Assumptions!$C$115,1,0) -> 0 | F10: =IF(MIN(F8:$AF$8)>=Assumptions!$C$115,1,0) -> 0 | G10: =IF(MIN(G8:$AF$8)>=Assumptions!$C$115,1,0) -> 0 | H10: =IF(MIN(H8:$AF$8)>=Assumptions!$C$115,1,0) -> 0 | I10: =IF(MIN(I8:$AF$8)>=Assumptions!$C$115,1,0) -> 0 | J10: =IF(MIN(J8:$AF$8)>=Assumptions!$C$115,1,0) -> 0 | ... AF10: =IF(MIN(AF8:$AF$8)>=Assumptions!$C$115,1,0) -> 1
A12: INPUTS TO THE SWEEP (what happens in the years after DM stops)
B13: Household cash flow once DM has stopped (MM's pay less spending and Junior ISAs) | C13: =C6-C7 -> -45363.6 | D13: =D6-D7 -> -47160.6 | E13: =E6-E7 -> -37117.2 | F13: =F6-F7 -> -13905.461 | G13: =G6-G7 -> -5059.298 | H13: =H6-H7 -> -4980.484 | I13: =I6-I7 -> 4099.9063 | J13: =J6-J7 -> 4181.9045 | ... AF13: =AF6-AF7 -> 82896.512
B14: Liquid savings floor (12 months of household spending) | C14: =Household_Base!C$22*Assumptions!$C$111/12 -> 125400 | D14: =Household_Base!D$22*Assumptions!$C$111/12 -> 130416 | E14: =Household_Base!E$22*Assumptions!$C$111/12 -> 123951.36 | F14: =Household_Base!F$22*Assumptions!$C$111/12 -> 102600.58 | G14: =Household_Base!G$22*Assumptions!$C$111/12 -> 104652.59 | H14: =Household_Base!H$22*Assumptions!$C$111/12 -> 106745.64 | I14: =Household_Base!I$22*Assumptions!$C$111/12 -> 108880.55 | J14: =Household_Base!J$22*Assumptions!$C$111/12 -> 111058.16 | ... AF14: =Household_Base!AF$22*Assumptions!$C$111/12 -> 95262.29
B15: Return on the joint ISA | C15: =Returns!C$11 -> 0.08 | D15: =Returns!D$11 -> 0.08 | E15: =Returns!E$11 -> 0.08 | F15: =Returns!F$11 -> 0.08 | G15: =Returns!G$11 -> 0.08 | H15: =Returns!H$11 -> 0.08 | I15: =Returns!I$11 -> 0.08 | J15: =Returns!J$11 -> 0.08 | ... AF15: =Returns!AF$11 -> 0.0245
B16: Return on taxable savings | C16: =Returns!C$12 -> 0.065 | D16: =Returns!D$12 -> 0.065 | E16: =Returns!E$12 -> 0.065 | F16: =Returns!F$12 -> 0.065 | G16: =Returns!G$12 -> 0.065 | H16: =Returns!H$12 -> 0.065 | I16: =Returns!I$12 -> 0.065 | J16: =Returns!J$12 -> 0.065 | ... AF16: =Returns!AF$12 -> 0.0095
B17: Taxable savings while BOTH are working | C17: =Household_Base!C$55 -> 0 | D17: =Household_Base!D$55 -> 0 | E17: =Household_Base!E$55 -> 79.648 | F17: =Household_Base!F$55 -> 26004.421 | G17: =Household_Base!G$55 -> 65141.241 | H17: =Household_Base!H$55 -> 107750.88 | I17: =Household_Base!I$55 -> 163077.66 | J17: =Household_Base!J$55 -> 222967.14 | ... AF17: =Household_Base!AF$55 -> 3675658.6
B18: Joint ISA while BOTH are working | C18: =Household_Base!C$61 -> 302223.8 | D18: =Household_Base!D$61 -> 351383.7 | E18: =Household_Base!E$61 -> 419494.4 | F18: =Household_Base!F$61 -> 493053.95 | G18: =Household_Base!G$61 -> 572498.27 | H18: =Household_Base!H$61 -> 659098.13 | I18: =Household_Base!I$61 -> 753441.98 | J18: =Household_Base!J$61 -> 856165.66 | ... AF18: =Household_Base!AF$61 -> 4688867.3
A20: GRID A — TAXABLE SAVINGS, IF DM'S LAST FULL WORKING YEAR IS THE YEAR IN COLUMN B
B21: Year | C21: 2026 | D21: 2027 | E21: 2028 | F21: 2029 | G21: 2030 | H21: 2031 | I21: 2032 | J21: 2033 | K21: 2034 | L21: 2035 | M21: 2036 | N21: 2037 | O21: 2038 | P21: 2039 | Q21: 2040 | R21: 2041 | S21: 2042 | T21: 2043 | U21: 2044 | V21: 2045 | W21: 2046 | X21: 2047 | Y21: 2048 | Z21: 2049 | AA21: 2050 | AB21: 2051 | AC21: 2052 | AD21: 2053 | AE21: 2054 | AF21: 2055
B22: 2026 | C22: =C17 -> 0 | D22: =IF(D$5<=$B22,D17,MAX(0,C22*(1+D$16)+D$13)) -> 0 | E22: =IF(E$5<=$B22,E17,MAX(0,D22*(1+E$16)+E$13)) -> 0 | F22: =IF(F$5<=$B22,F17,MAX(0,E22*(1+F$16)+F$13)) -> 0 | G22: =IF(G$5<=$B22,G17,MAX(0,F22*(1+G$16)+G$13)) -> 0 | H22: =IF(H$5<=$B22,H17,MAX(0,G22*(1+H$16)+H$13)) -> 0 | I22: =IF(I$5<=$B22,I17,MAX(0,H22*(1+I$16)+I$13)) -> 4099.9063 | J22: =IF(J$5<=$B22,J17,MAX(0,I22*(1+J$16)+J$13)) -> 8548.3047 | K22: =IF(K$5<=$B22,K17,MAX(0,J22*(1+K$16)+K$13)) -> 35294.518 | ... AF22: =IF(AF$5<=$B22,AF17,MAX(0,AE22*(1+AF$16)+AF$13)) -> 1461692.9
B23: 2027 | C23: =C17 -> 0 | D23: =IF(D$5<=$B23,D17,MAX(0,C23*(1+D$16)+D$13)) -> 0 | E23: =IF(E$5<=$B23,E17,MAX(0,D23*(1+E$16)+E$13)) -> 0 | F23: =IF(F$5<=$B23,F17,MAX(0,E23*(1+F$16)+F$13)) -> 0 | G23: =IF(G$5<=$B23,G17,MAX(0,F23*(1+G$16)+G$13)) -> 0 | H23: =IF(H$5<=$B23,H17,MAX(0,G23*(1+H$16)+H$13)) -> 0 | I23: =IF(I$5<=$B23,I17,MAX(0,H23*(1+I$16)+I$13)) -> 4099.9063 | J23: =IF(J$5<=$B23,J17,MAX(0,I23*(1+J$16)+J$13)) -> 8548.3047 | K23: =IF(K$5<=$B23,K17,MAX(0,J23*(1+K$16)+K$13)) -> 35294.518 | ... AF23: =IF(AF$5<=$B23,AF17,MAX(0,AE23*(1+AF$16)+AF$13)) -> 1461692.9
B24: 2028 | C24: =C17 -> 0 | D24: =IF(D$5<=$B24,D17,MAX(0,C24*(1+D$16)+D$13)) -> 0 | E24: =IF(E$5<=$B24,E17,MAX(0,D24*(1+E$16)+E$13)) -> 79.648 | F24: =IF(F$5<=$B24,F17,MAX(0,E24*(1+F$16)+F$13)) -> 0 | G24: =IF(G$5<=$B24,G17,MAX(0,F24*(1+G$16)+G$13)) -> 0 | H24: =IF(H$5<=$B24,H17,MAX(0,G24*(1+H$16)+H$13)) -> 0 | I24: =IF(I$5<=$B24,I17,MAX(0,H24*(1+I$16)+I$13)) -> 4099.9063 | J24: =IF(J$5<=$B24,J17,MAX(0,I24*(1+J$16)+J$13)) -> 8548.3047 | K24: =IF(K$5<=$B24,K17,MAX(0,J24*(1+K$16)+K$13)) -> 35294.518 | ... AF24: =IF(AF$5<=$B24,AF17,MAX(0,AE24*(1+AF$16)+AF$13)) -> 1461692.9
B25: 2029 | C25: =C17 -> 0 | D25: =IF(D$5<=$B25,D17,MAX(0,C25*(1+D$16)+D$13)) -> 0 | E25: =IF(E$5<=$B25,E17,MAX(0,D25*(1+E$16)+E$13)) -> 79.648 | F25: =IF(F$5<=$B25,F17,MAX(0,E25*(1+F$16)+F$13)) -> 26004.421 | G25: =IF(G$5<=$B25,G17,MAX(0,F25*(1+G$16)+G$13)) -> 22635.411 | H25: =IF(H$5<=$B25,H17,MAX(0,G25*(1+H$16)+H$13)) -> 19126.228 | I25: =IF(I$5<=$B25,I17,MAX(0,H25*(1+I$16)+I$13)) -> 24469.34 | J25: =IF(J$5<=$B25,J17,MAX(0,I25*(1+J$16)+J$13)) -> 30241.751 | K25: =IF(K$5<=$B25,K17,MAX(0,J25*(1+K$16)+K$13)) -> 58398.038 | ... AF25: =IF(AF$5<=$B25,AF17,MAX(0,AE25*(1+AF$16)+AF$13)) -> 1513353.3
B26: 2030 | C26: =C17 -> 0 | D26: =IF(D$5<=$B26,D17,MAX(0,C26*(1+D$16)+D$13)) -> 0 | E26: =IF(E$5<=$B26,E17,MAX(0,D26*(1+E$16)+E$13)) -> 79.648 | F26: =IF(F$5<=$B26,F17,MAX(0,E26*(1+F$16)+F$13)) -> 26004.421 | G26: =IF(G$5<=$B26,G17,MAX(0,F26*(1+G$16)+G$13)) -> 65141.241 | H26: =IF(H$5<=$B26,H17,MAX(0,G26*(1+H$16)+H$13)) -> 64394.937 | I26: =IF(I$5<=$B26,I17,MAX(0,H26*(1+I$16)+I$13)) -> 72680.515 | J26: =IF(J$5<=$B26,J17,MAX(0,I26*(1+J$16)+J$13)) -> 81586.653 | K26: =IF(K$5<=$B26,K17,MAX(0,J26*(1+K$16)+K$13)) -> 113080.36 | ... AF26: =IF(AF$5<=$B26,AF17,MAX(0,AE26*(1+AF$16)+AF$13)) -> 1635624.9
B27: 2031 | C27: =C17 -> 0 | D27: =IF(D$5<=$B27,D17,MAX(0,C27*(1+D$16)+D$13)) -> 0 | E27: =IF(E$5<=$B27,E17,MAX(0,D27*(1+E$16)+E$13)) -> 79.648 | F27: =IF(F$5<=$B27,F17,MAX(0,E27*(1+F$16)+F$13)) -> 26004.421 | G27: =IF(G$5<=$B27,G17,MAX(0,F27*(1+G$16)+G$13)) -> 65141.241 | H27: =IF(H$5<=$B27,H17,MAX(0,G27*(1+H$16)+H$13)) -> 107750.88 | I27: =IF(I$5<=$B27,I17,MAX(0,H27*(1+I$16)+I$13)) -> 118854.6 | J27: =IF(J$5<=$B27,J17,MAX(0,I27*(1+J$16)+J$13)) -> 130762.05 | K27: =IF(K$5<=$B27,K17,MAX(0,J27*(1+K$16)+K$13)) -> 165452.16 | ... AF27: =IF(AF$5<=$B27,AF17,MAX(0,AE27*(1+AF$16)+AF$13)) -> 1752730.2
B28: 2032 | C28: =C17 -> 0 | D28: =IF(D$5<=$B28,D17,MAX(0,C28*(1+D$16)+D$13)) -> 0 | E28: =IF(E$5<=$B28,E17,MAX(0,D28*(1+E$16)+E$13)) -> 79.648 | F28: =IF(F$5<=$B28,F17,MAX(0,E28*(1+F$16)+F$13)) -> 26004.421 | G28: =IF(G$5<=$B28,G17,MAX(0,F28*(1+G$16)+G$13)) -> 65141.241 | H28: =IF(H$5<=$B28,H17,MAX(0,G28*(1+H$16)+H$13)) -> 107750.88 | I28: =IF(I$5<=$B28,I17,MAX(0,H28*(1+I$16)+I$13)) -> 163077.66 | J28: =IF(J$5<=$B28,J17,MAX(0,I28*(1+J$16)+J$13)) -> 177859.62 | K28: =IF(K$5<=$B28,K17,MAX(0,J28*(1+K$16)+K$13)) -> 215611.06 | ... AF28: =IF(AF$5<=$B28,AF17,MAX(0,AE28*(1+AF$16)+AF$13)) -> 1864887.4
B29: 2033 | C29: =C17 -> 0 | D29: =IF(D$5<=$B29,D17,MAX(0,C29*(1+D$16)+D$13)) -> 0 | E29: =IF(E$5<=$B29,E17,MAX(0,D29*(1+E$16)+E$13)) -> 79.648 | F29: =IF(F$5<=$B29,F17,MAX(0,E29*(1+F$16)+F$13)) -> 26004.421 | G29: =IF(G$5<=$B29,G17,MAX(0,F29*(1+G$16)+G$13)) -> 65141.241 | H29: =IF(H$5<=$B29,H17,MAX(0,G29*(1+H$16)+H$13)) -> 107750.88 | I29: =IF(I$5<=$B29,I17,MAX(0,H29*(1+I$16)+I$13)) -> 163077.66 | J29: =IF(J$5<=$B29,J17,MAX(0,I29*(1+J$16)+J$13)) -> 222967.14 | K29: =IF(K$5<=$B29,K17,MAX(0,J29*(1+K$16)+K$13)) -> 263650.58 | ... AF29: =IF(AF$5<=$B29,AF17,MAX(0,AE29*(1+AF$16)+AF$13)) -> 1972305.5
B30: 2034 | C30: =C17 -> 0 | D30: =IF(D$5<=$B30,D17,MAX(0,C30*(1+D$16)+D$13)) -> 0 | E30: =IF(E$5<=$B30,E17,MAX(0,D30*(1+E$16)+E$13)) -> 79.648 | F30: =IF(F$5<=$B30,F17,MAX(0,E30*(1+F$16)+F$13)) -> 26004.421 | G30: =IF(G$5<=$B30,G17,MAX(0,F30*(1+G$16)+G$13)) -> 65141.241 | H30: =IF(H$5<=$B30,H17,MAX(0,G30*(1+H$16)+H$13)) -> 107750.88 | I30: =IF(I$5<=$B30,I17,MAX(0,H30*(1+I$16)+I$13)) -> 163077.66 | J30: =IF(J$5<=$B30,J17,MAX(0,I30*(1+J$16)+J$13)) -> 222967.14 | K30: =IF(K$5<=$B30,K17,MAX(0,J30*(1+K$16)+K$13)) -> 309660.26 | ... AF30: =IF(AF$5<=$B30,AF17,MAX(0,AE30*(1+AF$16)+AF$13)) -> 2075184.8
B31: 2035 | C31: =C17 -> 0 | D31: =IF(D$5<=$B31,D17,MAX(0,C31*(1+D$16)+D$13)) -> 0 | E31: =IF(E$5<=$B31,E17,MAX(0,D31*(1+E$16)+E$13)) -> 79.648 | F31: =IF(F$5<=$B31,F17,MAX(0,E31*(1+F$16)+F$13)) -> 26004.421 | G31: =IF(G$5<=$B31,G17,MAX(0,F31*(1+G$16)+G$13)) -> 65141.241 | H31: =IF(H$5<=$B31,H17,MAX(0,G31*(1+H$16)+H$13)) -> 107750.88 | I31: =IF(I$5<=$B31,I17,MAX(0,H31*(1+I$16)+I$13)) -> 163077.66 | J31: =IF(J$5<=$B31,J17,MAX(0,I31*(1+J$16)+J$13)) -> 222967.14 | K31: =IF(K$5<=$B31,K17,MAX(0,J31*(1+K$16)+K$13)) -> 309660.26 | ... AF31: =IF(AF$5<=$B31,AF17,MAX(0,AE31*(1+AF$16)+AF$13)) -> 2173717.1
B32: 2036 | C32: =C17 -> 0 | D32: =IF(D$5<=$B32,D17,MAX(0,C32*(1+D$16)+D$13)) -> 0 | E32: =IF(E$5<=$B32,E17,MAX(0,D32*(1+E$16)+E$13)) -> 79.648 | F32: =IF(F$5<=$B32,F17,MAX(0,E32*(1+F$16)+F$13)) -> 26004.421 | G32: =IF(G$5<=$B32,G17,MAX(0,F32*(1+G$16)+G$13)) -> 65141.241 | H32: =IF(H$5<=$B32,H17,MAX(0,G32*(1+H$16)+H$13)) -> 107750.88 | I32: =IF(I$5<=$B32,I17,MAX(0,H32*(1+I$16)+I$13)) -> 163077.66 | J32: =IF(J$5<=$B32,J17,MAX(0,I32*(1+J$16)+J$13)) -> 222967.14 | K32: =IF(K$5<=$B32,K17,MAX(0,J32*(1+K$16)+K$13)) -> 309660.26 | ... AF32: =IF(AF$5<=$B32,AF17,MAX(0,AE32*(1+AF$16)+AF$13)) -> 2268086.1
B33: 2037 | C33: =C17 -> 0 | D33: =IF(D$5<=$B33,D17,MAX(0,C33*(1+D$16)+D$13)) -> 0 | E33: =IF(E$5<=$B33,E17,MAX(0,D33*(1+E$16)+E$13)) -> 79.648 | F33: =IF(F$5<=$B33,F17,MAX(0,E33*(1+F$16)+F$13)) -> 26004.421 | G33: =IF(G$5<=$B33,G17,MAX(0,F33*(1+G$16)+G$13)) -> 65141.241 | H33: =IF(H$5<=$B33,H17,MAX(0,G33*(1+H$16)+H$13)) -> 107750.88 | I33: =IF(I$5<=$B33,I17,MAX(0,H33*(1+I$16)+I$13)) -> 163077.66 | J33: =IF(J$5<=$B33,J17,MAX(0,I33*(1+J$16)+J$13)) -> 222967.14 | K33: =IF(K$5<=$B33,K17,MAX(0,J33*(1+K$16)+K$13)) -> 309660.26 | ... AF33: =IF(AF$5<=$B33,AF17,MAX(0,AE33*(1+AF$16)+AF$13)) -> 2358595.1
B34: 2038 | C34: =C17 -> 0 | D34: =IF(D$5<=$B34,D17,MAX(0,C34*(1+D$16)+D$13)) -> 0 | E34: =IF(E$5<=$B34,E17,MAX(0,D34*(1+E$16)+E$13)) -> 79.648 | F34: =IF(F$5<=$B34,F17,MAX(0,E34*(1+F$16)+F$13)) -> 26004.421 | G34: =IF(G$5<=$B34,G17,MAX(0,F34*(1+G$16)+G$13)) -> 65141.241 | H34: =IF(H$5<=$B34,H17,MAX(0,G34*(1+H$16)+H$13)) -> 107750.88 | I34: =IF(I$5<=$B34,I17,MAX(0,H34*(1+I$16)+I$13)) -> 163077.66 | J34: =IF(J$5<=$B34,J17,MAX(0,I34*(1+J$16)+J$13)) -> 222967.14 | K34: =IF(K$5<=$B34,K17,MAX(0,J34*(1+K$16)+K$13)) -> 309660.26 | ... AF34: =IF(AF$5<=$B34,AF17,MAX(0,AE34*(1+AF$16)+AF$13)) -> 2445647.6
B35: 2039 | C35: =C17 -> 0 | D35: =IF(D$5<=$B35,D17,MAX(0,C35*(1+D$16)+D$13)) -> 0 | E35: =IF(E$5<=$B35,E17,MAX(0,D35*(1+E$16)+E$13)) -> 79.648 | F35: =IF(F$5<=$B35,F17,MAX(0,E35*(1+F$16)+F$13)) -> 26004.421 | G35: =IF(G$5<=$B35,G17,MAX(0,F35*(1+G$16)+G$13)) -> 65141.241 | H35: =IF(H$5<=$B35,H17,MAX(0,G35*(1+H$16)+H$13)) -> 107750.88 | I35: =IF(I$5<=$B35,I17,MAX(0,H35*(1+I$16)+I$13)) -> 163077.66 | J35: =IF(J$5<=$B35,J17,MAX(0,I35*(1+J$16)+J$13)) -> 222967.14 | K35: =IF(K$5<=$B35,K17,MAX(0,J35*(1+K$16)+K$13)) -> 309660.26 | ... AF35: =IF(AF$5<=$B35,AF17,MAX(0,AE35*(1+AF$16)+AF$13)) -> 2529613.2
B36: 2040 | C36: =C17 -> 0 | D36: =IF(D$5<=$B36,D17,MAX(0,C36*(1+D$16)+D$13)) -> 0 | E36: =IF(E$5<=$B36,E17,MAX(0,D36*(1+E$16)+E$13)) -> 79.648 | F36: =IF(F$5<=$B36,F17,MAX(0,E36*(1+F$16)+F$13)) -> 26004.421 | G36: =IF(G$5<=$B36,G17,MAX(0,F36*(1+G$16)+G$13)) -> 65141.241 | H36: =IF(H$5<=$B36,H17,MAX(0,G36*(1+H$16)+H$13)) -> 107750.88 | I36: =IF(I$5<=$B36,I17,MAX(0,H36*(1+I$16)+I$13)) -> 163077.66 | J36: =IF(J$5<=$B36,J17,MAX(0,I36*(1+J$16)+J$13)) -> 222967.14 | K36: =IF(K$5<=$B36,K17,MAX(0,J36*(1+K$16)+K$13)) -> 309660.26 | ... AF36: =IF(AF$5<=$B36,AF17,MAX(0,AE36*(1+AF$16)+AF$13)) -> 2610831.7
B37: 2041 | C37: =C17 -> 0 | D37: =IF(D$5<=$B37,D17,MAX(0,C37*(1+D$16)+D$13)) -> 0 | E37: =IF(E$5<=$B37,E17,MAX(0,D37*(1+E$16)+E$13)) -> 79.648 | F37: =IF(F$5<=$B37,F17,MAX(0,E37*(1+F$16)+F$13)) -> 26004.421 | G37: =IF(G$5<=$B37,G17,MAX(0,F37*(1+G$16)+G$13)) -> 65141.241 | H37: =IF(H$5<=$B37,H17,MAX(0,G37*(1+H$16)+H$13)) -> 107750.88 | I37: =IF(I$5<=$B37,I17,MAX(0,H37*(1+I$16)+I$13)) -> 163077.66 | J37: =IF(J$5<=$B37,J17,MAX(0,I37*(1+J$16)+J$13)) -> 222967.14 | K37: =IF(K$5<=$B37,K17,MAX(0,J37*(1+K$16)+K$13)) -> 309660.26 | ... AF37: =IF(AF$5<=$B37,AF17,MAX(0,AE37*(1+AF$16)+AF$13)) -> 2689617.1
B38: 2042 | C38: =C17 -> 0 | D38: =IF(D$5<=$B38,D17,MAX(0,C38*(1+D$16)+D$13)) -> 0 | E38: =IF(E$5<=$B38,E17,MAX(0,D38*(1+E$16)+E$13)) -> 79.648 | F38: =IF(F$5<=$B38,F17,MAX(0,E38*(1+F$16)+F$13)) -> 26004.421 | G38: =IF(G$5<=$B38,G17,MAX(0,F38*(1+G$16)+G$13)) -> 65141.241 | H38: =IF(H$5<=$B38,H17,MAX(0,G38*(1+H$16)+H$13)) -> 107750.88 | I38: =IF(I$5<=$B38,I17,MAX(0,H38*(1+I$16)+I$13)) -> 163077.66 | J38: =IF(J$5<=$B38,J17,MAX(0,I38*(1+J$16)+J$13)) -> 222967.14 | K38: =IF(K$5<=$B38,K17,MAX(0,J38*(1+K$16)+K$13)) -> 309660.26 | ... AF38: =IF(AF$5<=$B38,AF17,MAX(0,AE38*(1+AF$16)+AF$13)) -> 2766260.9
B39: 2043 | C39: =C17 -> 0 | D39: =IF(D$5<=$B39,D17,MAX(0,C39*(1+D$16)+D$13)) -> 0 | E39: =IF(E$5<=$B39,E17,MAX(0,D39*(1+E$16)+E$13)) -> 79.648 | F39: =IF(F$5<=$B39,F17,MAX(0,E39*(1+F$16)+F$13)) -> 26004.421 | G39: =IF(G$5<=$B39,G17,MAX(0,F39*(1+G$16)+G$13)) -> 65141.241 | H39: =IF(H$5<=$B39,H17,MAX(0,G39*(1+H$16)+H$13)) -> 107750.88 | I39: =IF(I$5<=$B39,I17,MAX(0,H39*(1+I$16)+I$13)) -> 163077.66 | J39: =IF(J$5<=$B39,J17,MAX(0,I39*(1+J$16)+J$13)) -> 222967.14 | K39: =IF(K$5<=$B39,K17,MAX(0,J39*(1+K$16)+K$13)) -> 309660.26 | ... AF39: =IF(AF$5<=$B39,AF17,MAX(0,AE39*(1+AF$16)+AF$13)) -> 2841035.4
B40: 2044 | C40: =C17 -> 0 | D40: =IF(D$5<=$B40,D17,MAX(0,C40*(1+D$16)+D$13)) -> 0 | E40: =IF(E$5<=$B40,E17,MAX(0,D40*(1+E$16)+E$13)) -> 79.648 | F40: =IF(F$5<=$B40,F17,MAX(0,E40*(1+F$16)+F$13)) -> 26004.421 | G40: =IF(G$5<=$B40,G17,MAX(0,F40*(1+G$16)+G$13)) -> 65141.241 | H40: =IF(H$5<=$B40,H17,MAX(0,G40*(1+H$16)+H$13)) -> 107750.88 | I40: =IF(I$5<=$B40,I17,MAX(0,H40*(1+I$16)+I$13)) -> 163077.66 | J40: =IF(J$5<=$B40,J17,MAX(0,I40*(1+J$16)+J$13)) -> 222967.14 | K40: =IF(K$5<=$B40,K17,MAX(0,J40*(1+K$16)+K$13)) -> 309660.26 | ... AF40: =IF(AF$5<=$B40,AF17,MAX(0,AE40*(1+AF$16)+AF$13)) -> 2914196.1
B41: 2045 | C41: =C17 -> 0 | D41: =IF(D$5<=$B41,D17,MAX(0,C41*(1+D$16)+D$13)) -> 0 | E41: =IF(E$5<=$B41,E17,MAX(0,D41*(1+E$16)+E$13)) -> 79.648 | F41: =IF(F$5<=$B41,F17,MAX(0,E41*(1+F$16)+F$13)) -> 26004.421 | G41: =IF(G$5<=$B41,G17,MAX(0,F41*(1+G$16)+G$13)) -> 65141.241 | H41: =IF(H$5<=$B41,H17,MAX(0,G41*(1+H$16)+H$13)) -> 107750.88 | I41: =IF(I$5<=$B41,I17,MAX(0,H41*(1+I$16)+I$13)) -> 163077.66 | J41: =IF(J$5<=$B41,J17,MAX(0,I41*(1+J$16)+J$13)) -> 222967.14 | K41: =IF(K$5<=$B41,K17,MAX(0,J41*(1+K$16)+K$13)) -> 309660.26 | ... AF41: =IF(AF$5<=$B41,AF17,MAX(0,AE41*(1+AF$16)+AF$13)) -> 2985984.3
A44: GRID B — JOINT ISA (drawn on only once taxable savings are exhausted)
B45: Year | C45: 2026 | D45: 2027 | E45: 2028 | F45: 2029 | G45: 2030 | H45: 2031 | I45: 2032 | J45: 2033 | K45: 2034 | L45: 2035 | M45: 2036 | N45: 2037 | O45: 2038 | P45: 2039 | Q45: 2040 | R45: 2041 | S45: 2042 | T45: 2043 | U45: 2044 | V45: 2045 | W45: 2046 | X45: 2047 | Y45: 2048 | Z45: 2049 | AA45: 2050 | AB45: 2051 | AC45: 2052 | AD45: 2053 | AE45: 2054 | AF45: 2055
B46: 2026 | C46: =C18 -> 302223.8 | D46: =IF(D$5<=$B46,D18,MAX(0,C46*(1+D$15)-MAX(0,-(C22*(1+D$16)+D$13)))) -> 279241.1 | E46: =IF(E$5<=$B46,E18,MAX(0,D46*(1+E$15)-MAX(0,-(D22*(1+E$16)+E$13)))) -> 264463.19 | F46: =IF(F$5<=$B46,F18,MAX(0,E46*(1+F$15)-MAX(0,-(E22*(1+F$16)+F$13)))) -> 271714.79 | G46: =IF(G$5<=$B46,G18,MAX(0,F46*(1+G$15)-MAX(0,-(F22*(1+G$16)+G$13)))) -> 288392.67 | H46: =IF(H$5<=$B46,H18,MAX(0,G46*(1+H$15)-MAX(0,-(G22*(1+H$16)+H$13)))) -> 306483.6 | I46: =IF(I$5<=$B46,I18,MAX(0,H46*(1+I$15)-MAX(0,-(H22*(1+I$16)+I$13)))) -> 331002.29 | J46: =IF(J$5<=$B46,J18,MAX(0,I46*(1+J$15)-MAX(0,-(I22*(1+J$16)+J$13)))) -> 357482.47 | K46: =IF(K$5<=$B46,K18,MAX(0,J46*(1+K$15)-MAX(0,-(J22*(1+K$16)+K$13)))) -> 386081.07 | ... AF46: =IF(AF$5<=$B46,AF18,MAX(0,AE46*(1+AF$15)-MAX(0,-(AE22*(1+AF$16)+AF$13)))) -> 1166526.3
B47: 2027 | C47: =C18 -> 302223.8 | D47: =IF(D$5<=$B47,D18,MAX(0,C47*(1+D$15)-MAX(0,-(C23*(1+D$16)+D$13)))) -> 351383.7 | E47: =IF(E$5<=$B47,E18,MAX(0,D47*(1+E$15)-MAX(0,-(D23*(1+E$16)+E$13)))) -> 342377.2 | F47: =IF(F$5<=$B47,F18,MAX(0,E47*(1+F$15)-MAX(0,-(E23*(1+F$16)+F$13)))) -> 355861.92 | G47: =IF(G$5<=$B47,G18,MAX(0,F47*(1+G$15)-MAX(0,-(F23*(1+G$16)+G$13)))) -> 379271.57 | H47: =IF(H$5<=$B47,H18,MAX(0,G47*(1+H$15)-MAX(0,-(G23*(1+H$16)+H$13)))) -> 404632.81 | I47: =IF(I$5<=$B47,I18,MAX(0,H47*(1+I$15)-MAX(0,-(H23*(1+I$16)+I$13)))) -> 437003.44 | J47: =IF(J$5<=$B47,J18,MAX(0,I47*(1+J$15)-MAX(0,-(I23*(1+J$16)+J$13)))) -> 471963.71 | K47: =IF(K$5<=$B47,K18,MAX(0,J47*(1+K$15)-MAX(0,-(J23*(1+K$16)+K$13)))) -> 509720.81 | ... AF47: =IF(AF$5<=$B47,AF18,MAX(0,AE47*(1+AF$15)-MAX(0,-(AE23*(1+AF$16)+AF$13)))) -> 1540098.1
B48: 2028 | C48: =C18 -> 302223.8 | D48: =IF(D$5<=$B48,D18,MAX(0,C48*(1+D$15)-MAX(0,-(C24*(1+D$16)+D$13)))) -> 351383.7 | E48: =IF(E$5<=$B48,E18,MAX(0,D48*(1+E$15)-MAX(0,-(D24*(1+E$16)+E$13)))) -> 419494.4 | F48: =IF(F$5<=$B48,F18,MAX(0,E48*(1+F$15)-MAX(0,-(E24*(1+F$16)+F$13)))) -> 439233.32 | G48: =IF(G$5<=$B48,G18,MAX(0,F48*(1+G$15)-MAX(0,-(F24*(1+G$16)+G$13)))) -> 469312.68 | H48: =IF(H$5<=$B48,H18,MAX(0,G48*(1+H$15)-MAX(0,-(G24*(1+H$16)+H$13)))) -> 501877.21 | I48: =IF(I$5<=$B48,I18,MAX(0,H48*(1+I$15)-MAX(0,-(H24*(1+I$16)+I$13)))) -> 542027.39 | J48: =IF(J$5<=$B48,J18,MAX(0,I48*(1+J$15)-MAX(0,-(I24*(1+J$16)+J$13)))) -> 585389.58 | K48: =IF(K$5<=$B48,K18,MAX(0,J48*(1+K$15)-MAX(0,-(J24*(1+K$16)+K$13)))) -> 632220.75 | ... AF48: =IF(AF$5<=$B48,AF18,MAX(0,AE48*(1+AF$15)-MAX(0,-(AE24*(1+AF$16)+AF$13)))) -> 1910226.1
B49: 2029 | C49: =C18 -> 302223.8 | D49: =IF(D$5<=$B49,D18,MAX(0,C49*(1+D$15)-MAX(0,-(C25*(1+D$16)+D$13)))) -> 351383.7 | E49: =IF(E$5<=$B49,E18,MAX(0,D49*(1+E$15)-MAX(0,-(D25*(1+E$16)+E$13)))) -> 419494.4 | F49: =IF(F$5<=$B49,F18,MAX(0,E49*(1+F$15)-MAX(0,-(E25*(1+F$16)+F$13)))) -> 493053.95 | G49: =IF(G$5<=$B49,G18,MAX(0,F49*(1+G$15)-MAX(0,-(F25*(1+G$16)+G$13)))) -> 532498.27 | H49: =IF(H$5<=$B49,H18,MAX(0,G49*(1+H$15)-MAX(0,-(G25*(1+H$16)+H$13)))) -> 575098.13 | I49: =IF(I$5<=$B49,I18,MAX(0,H49*(1+I$15)-MAX(0,-(H25*(1+I$16)+I$13)))) -> 621105.98 | J49: =IF(J$5<=$B49,J18,MAX(0,I49*(1+J$15)-MAX(0,-(I25*(1+J$16)+J$13)))) -> 670794.46 | K49: =IF(K$5<=$B49,K18,MAX(0,J49*(1+K$15)-MAX(0,-(J25*(1+K$16)+K$13)))) -> 724458.02 | ... AF49: =IF(AF$5<=$B49,AF18,MAX(0,AE49*(1+AF$15)-MAX(0,-(AE25*(1+AF$16)+AF$13)))) -> 2188916.8
B50: 2030 | C50: =C18 -> 302223.8 | D50: =IF(D$5<=$B50,D18,MAX(0,C50*(1+D$15)-MAX(0,-(C26*(1+D$16)+D$13)))) -> 351383.7 | E50: =IF(E$5<=$B50,E18,MAX(0,D50*(1+E$15)-MAX(0,-(D26*(1+E$16)+E$13)))) -> 419494.4 | F50: =IF(F$5<=$B50,F18,MAX(0,E50*(1+F$15)-MAX(0,-(E26*(1+F$16)+F$13)))) -> 493053.95 | G50: =IF(G$5<=$B50,G18,MAX(0,F50*(1+G$15)-MAX(0,-(F26*(1+G$16)+G$13)))) -> 572498.27 | H50: =IF(H$5<=$B50,H18,MAX(0,G50*(1+H$15)-MAX(0,-(G26*(1+H$16)+H$13)))) -> 618298.13 | I50: =IF(I$5<=$B50,I18,MAX(0,H50*(1+I$15)-MAX(0,-(H26*(1+I$16)+I$13)))) -> 667761.98 | J50: =IF(J$5<=$B50,J18,MAX(0,I50*(1+J$15)-MAX(0,-(I26*(1+J$16)+J$13)))) -> 721182.94 | K50: =IF(K$5<=$B50,K18,MAX(0,J50*(1+K$15)-MAX(0,-(J26*(1+K$16)+K$13)))) -> 778877.57 | ... AF50: =IF(AF$5<=$B50,AF18,MAX(0,AE50*(1+AF$15)-MAX(0,-(AE26*(1+AF$16)+AF$13)))) -> 2353343
B51: 2031 | C51: =C18 -> 302223.8 | D51: =IF(D$5<=$B51,D18,MAX(0,C51*(1+D$15)-MAX(0,-(C27*(1+D$16)+D$13)))) -> 351383.7 | E51: =IF(E$5<=$B51,E18,MAX(0,D51*(1+E$15)-MAX(0,-(D27*(1+E$16)+E$13)))) -> 419494.4 | F51: =IF(F$5<=$B51,F18,MAX(0,E51*(1+F$15)-MAX(0,-(E27*(1+F$16)+F$13)))) -> 493053.95 | G51: =IF(G$5<=$B51,G18,MAX(0,F51*(1+G$15)-MAX(0,-(F27*(1+G$16)+G$13)))) -> 572498.27 | H51: =IF(H$5<=$B51,H18,MAX(0,G51*(1+H$15)-MAX(0,-(G27*(1+H$16)+H$13)))) -> 659098.13 | I51: =IF(I$5<=$B51,I18,MAX(0,H51*(1+I$15)-MAX(0,-(H27*(1+I$16)+I$13)))) -> 711825.98 | J51: =IF(J$5<=$B51,J18,MAX(0,I51*(1+J$15)-MAX(0,-(I27*(1+J$16)+J$13)))) -> 768772.06 | K51: =IF(K$5<=$B51,K18,MAX(0,J51*(1+K$15)-MAX(0,-(J27*(1+K$16)+K$13)))) -> 830273.82 | ... AF51: =IF(AF$5<=$B51,AF18,MAX(0,AE51*(1+AF$15)-MAX(0,-(AE27*(1+AF$16)+AF$13)))) -> 2508634.4
B52: 2032 | C52: =C18 -> 302223.8 | D52: =IF(D$5<=$B52,D18,MAX(0,C52*(1+D$15)-MAX(0,-(C28*(1+D$16)+D$13)))) -> 351383.7 | E52: =IF(E$5<=$B52,E18,MAX(0,D52*(1+E$15)-MAX(0,-(D28*(1+E$16)+E$13)))) -> 419494.4 | F52: =IF(F$5<=$B52,F18,MAX(0,E52*(1+F$15)-MAX(0,-(E28*(1+F$16)+F$13)))) -> 493053.95 | G52: =IF(G$5<=$B52,G18,MAX(0,F52*(1+G$15)-MAX(0,-(F28*(1+G$16)+G$13)))) -> 572498.27 | H52: =IF(H$5<=$B52,H18,MAX(0,G52*(1+H$15)-MAX(0,-(G28*(1+H$16)+H$13)))) -> 659098.13 | I52: =IF(I$5<=$B52,I18,MAX(0,H52*(1+I$15)-MAX(0,-(H28*(1+I$16)+I$13)))) -> 753441.98 | J52: =IF(J$5<=$B52,J18,MAX(0,I52*(1+J$15)-MAX(0,-(I28*(1+J$16)+J$13)))) -> 813717.34 | K52: =IF(K$5<=$B52,K18,MAX(0,J52*(1+K$15)-MAX(0,-(J28*(1+K$16)+K$13)))) -> 878814.73 | ... AF52: =IF(AF$5<=$B52,AF18,MAX(0,AE52*(1+AF$15)-MAX(0,-(AE28*(1+AF$16)+AF$13)))) -> 2655298.6
B53: 2033 | C53: =C18 -> 302223.8 | D53: =IF(D$5<=$B53,D18,MAX(0,C53*(1+D$15)-MAX(0,-(C29*(1+D$16)+D$13)))) -> 351383.7 | E53: =IF(E$5<=$B53,E18,MAX(0,D53*(1+E$15)-MAX(0,-(D29*(1+E$16)+E$13)))) -> 419494.4 | F53: =IF(F$5<=$B53,F18,MAX(0,E53*(1+F$15)-MAX(0,-(E29*(1+F$16)+F$13)))) -> 493053.95 | G53: =IF(G$5<=$B53,G18,MAX(0,F53*(1+G$15)-MAX(0,-(F29*(1+G$16)+G$13)))) -> 572498.27 | H53: =IF(H$5<=$B53,H18,MAX(0,G53*(1+H$15)-MAX(0,-(G29*(1+H$16)+H$13)))) -> 659098.13 | I53: =IF(I$5<=$B53,I18,MAX(0,H53*(1+I$15)-MAX(0,-(H29*(1+I$16)+I$13)))) -> 753441.98 | J53: =IF(J$5<=$B53,J18,MAX(0,I53*(1+J$15)-MAX(0,-(I29*(1+J$16)+J$13)))) -> 856165.66 | K53: =IF(K$5<=$B53,K18,MAX(0,J53*(1+K$15)-MAX(0,-(J29*(1+K$16)+K$13)))) -> 924658.91 | ... AF53: =IF(AF$5<=$B53,AF18,MAX(0,AE53*(1+AF$15)-MAX(0,-(AE29*(1+AF$16)+AF$13)))) -> 2793814.7
B54: 2034 | C54: =C18 -> 302223.8 | D54: =IF(D$5<=$B54,D18,MAX(0,C54*(1+D$15)-MAX(0,-(C30*(1+D$16)+D$13)))) -> 351383.7 | E54: =IF(E$5<=$B54,E18,MAX(0,D54*(1+E$15)-MAX(0,-(D30*(1+E$16)+E$13)))) -> 419494.4 | F54: =IF(F$5<=$B54,F18,MAX(0,E54*(1+F$15)-MAX(0,-(E30*(1+F$16)+F$13)))) -> 493053.95 | G54: =IF(G$5<=$B54,G18,MAX(0,F54*(1+G$15)-MAX(0,-(F30*(1+G$16)+G$13)))) -> 572498.27 | H54: =IF(H$5<=$B54,H18,MAX(0,G54*(1+H$15)-MAX(0,-(G30*(1+H$16)+H$13)))) -> 659098.13 | I54: =IF(I$5<=$B54,I18,MAX(0,H54*(1+I$15)-MAX(0,-(H30*(1+I$16)+I$13)))) -> 753441.98 | J54: =IF(J$5<=$B54,J18,MAX(0,I54*(1+J$15)-MAX(0,-(I30*(1+J$16)+J$13)))) -> 856165.66 | K54: =IF(K$5<=$B54,K18,MAX(0,J54*(1+K$15)-MAX(0,-(J30*(1+K$16)+K$13)))) -> 967956.2 | ... AF54: =IF(AF$5<=$B54,AF18,MAX(0,AE54*(1+AF$15)-MAX(0,-(AE30*(1+AF$16)+AF$13)))) -> 2924635.5
B55: 2035 | C55: =C18 -> 302223.8 | D55: =IF(D$5<=$B55,D18,MAX(0,C55*(1+D$15)-MAX(0,-(C31*(1+D$16)+D$13)))) -> 351383.7 | E55: =IF(E$5<=$B55,E18,MAX(0,D55*(1+E$15)-MAX(0,-(D31*(1+E$16)+E$13)))) -> 419494.4 | F55: =IF(F$5<=$B55,F18,MAX(0,E55*(1+F$15)-MAX(0,-(E31*(1+F$16)+F$13)))) -> 493053.95 | G55: =IF(G$5<=$B55,G18,MAX(0,F55*(1+G$15)-MAX(0,-(F31*(1+G$16)+G$13)))) -> 572498.27 | H55: =IF(H$5<=$B55,H18,MAX(0,G55*(1+H$15)-MAX(0,-(G31*(1+H$16)+H$13)))) -> 659098.13 | I55: =IF(I$5<=$B55,I18,MAX(0,H55*(1+I$15)-MAX(0,-(H31*(1+I$16)+I$13)))) -> 753441.98 | J55: =IF(J$5<=$B55,J18,MAX(0,I55*(1+J$15)-MAX(0,-(I31*(1+J$16)+J$13)))) -> 856165.66 | K55: =IF(K$5<=$B55,K18,MAX(0,J55*(1+K$15)-MAX(0,-(J31*(1+K$16)+K$13)))) -> 967956.2 | ... AF55: =IF(AF$5<=$B55,AF18,MAX(0,AE55*(1+AF$15)-MAX(0,-(AE31*(1+AF$16)+AF$13)))) -> 3048188.4
B56: 2036 | C56: =C18 -> 302223.8 | D56: =IF(D$5<=$B56,D18,MAX(0,C56*(1+D$15)-MAX(0,-(C32*(1+D$16)+D$13)))) -> 351383.7 | E56: =IF(E$5<=$B56,E18,MAX(0,D56*(1+E$15)-MAX(0,-(D32*(1+E$16)+E$13)))) -> 419494.4 | F56: =IF(F$5<=$B56,F18,MAX(0,E56*(1+F$15)-MAX(0,-(E32*(1+F$16)+F$13)))) -> 493053.95 | G56: =IF(G$5<=$B56,G18,MAX(0,F56*(1+G$15)-MAX(0,-(F32*(1+G$16)+G$13)))) -> 572498.27 | H56: =IF(H$5<=$B56,H18,MAX(0,G56*(1+H$15)-MAX(0,-(G32*(1+H$16)+H$13)))) -> 659098.13 | I56: =IF(I$5<=$B56,I18,MAX(0,H56*(1+I$15)-MAX(0,-(H32*(1+I$16)+I$13)))) -> 753441.98 | J56: =IF(J$5<=$B56,J18,MAX(0,I56*(1+J$15)-MAX(0,-(I32*(1+J$16)+J$13)))) -> 856165.66 | K56: =IF(K$5<=$B56,K18,MAX(0,J56*(1+K$15)-MAX(0,-(J32*(1+K$16)+K$13)))) -> 967956.2 | ... AF56: =IF(AF$5<=$B56,AF18,MAX(0,AE56*(1+AF$15)-MAX(0,-(AE32*(1+AF$16)+AF$13)))) -> 3164877.3
B57: 2037 | C57: =C18 -> 302223.8 | D57: =IF(D$5<=$B57,D18,MAX(0,C57*(1+D$15)-MAX(0,-(C33*(1+D$16)+D$13)))) -> 351383.7 | E57: =IF(E$5<=$B57,E18,MAX(0,D57*(1+E$15)-MAX(0,-(D33*(1+E$16)+E$13)))) -> 419494.4 | F57: =IF(F$5<=$B57,F18,MAX(0,E57*(1+F$15)-MAX(0,-(E33*(1+F$16)+F$13)))) -> 493053.95 | G57: =IF(G$5<=$B57,G18,MAX(0,F57*(1+G$15)-MAX(0,-(F33*(1+G$16)+G$13)))) -> 572498.27 | H57: =IF(H$5<=$B57,H18,MAX(0,G57*(1+H$15)-MAX(0,-(G33*(1+H$16)+H$13)))) -> 659098.13 | I57: =IF(I$5<=$B57,I18,MAX(0,H57*(1+I$15)-MAX(0,-(H33*(1+I$16)+I$13)))) -> 753441.98 | J57: =IF(J$5<=$B57,J18,MAX(0,I57*(1+J$15)-MAX(0,-(I33*(1+J$16)+J$13)))) -> 856165.66 | K57: =IF(K$5<=$B57,K18,MAX(0,J57*(1+K$15)-MAX(0,-(J33*(1+K$16)+K$13)))) -> 967956.2 | ... AF57: =IF(AF$5<=$B57,AF18,MAX(0,AE57*(1+AF$15)-MAX(0,-(AE33*(1+AF$16)+AF$13)))) -> 3275236.8
B58: 2038 | C58: =C18 -> 302223.8 | D58: =IF(D$5<=$B58,D18,MAX(0,C58*(1+D$15)-MAX(0,-(C34*(1+D$16)+D$13)))) -> 351383.7 | E58: =IF(E$5<=$B58,E18,MAX(0,D58*(1+E$15)-MAX(0,-(D34*(1+E$16)+E$13)))) -> 419494.4 | F58: =IF(F$5<=$B58,F18,MAX(0,E58*(1+F$15)-MAX(0,-(E34*(1+F$16)+F$13)))) -> 493053.95 | G58: =IF(G$5<=$B58,G18,MAX(0,F58*(1+G$15)-MAX(0,-(F34*(1+G$16)+G$13)))) -> 572498.27 | H58: =IF(H$5<=$B58,H18,MAX(0,G58*(1+H$15)-MAX(0,-(G34*(1+H$16)+H$13)))) -> 659098.13 | I58: =IF(I$5<=$B58,I18,MAX(0,H58*(1+I$15)-MAX(0,-(H34*(1+I$16)+I$13)))) -> 753441.98 | J58: =IF(J$5<=$B58,J18,MAX(0,I58*(1+J$15)-MAX(0,-(I34*(1+J$16)+J$13)))) -> 856165.66 | K58: =IF(K$5<=$B58,K18,MAX(0,J58*(1+K$15)-MAX(0,-(J34*(1+K$16)+K$13)))) -> 967956.2 | ... AF58: =IF(AF$5<=$B58,AF18,MAX(0,AE58*(1+AF$15)-MAX(0,-(AE34*(1+AF$16)+AF$13)))) -> 3379901.2
B59: 2039 | C59: =C18 -> 302223.8 | D59: =IF(D$5<=$B59,D18,MAX(0,C59*(1+D$15)-MAX(0,-(C35*(1+D$16)+D$13)))) -> 351383.7 | E59: =IF(E$5<=$B59,E18,MAX(0,D59*(1+E$15)-MAX(0,-(D35*(1+E$16)+E$13)))) -> 419494.4 | F59: =IF(F$5<=$B59,F18,MAX(0,E59*(1+F$15)-MAX(0,-(E35*(1+F$16)+F$13)))) -> 493053.95 | G59: =IF(G$5<=$B59,G18,MAX(0,F59*(1+G$15)-MAX(0,-(F35*(1+G$16)+G$13)))) -> 572498.27 | H59: =IF(H$5<=$B59,H18,MAX(0,G59*(1+H$15)-MAX(0,-(G35*(1+H$16)+H$13)))) -> 659098.13 | I59: =IF(I$5<=$B59,I18,MAX(0,H59*(1+I$15)-MAX(0,-(H35*(1+I$16)+I$13)))) -> 753441.98 | J59: =IF(J$5<=$B59,J18,MAX(0,I59*(1+J$15)-MAX(0,-(I35*(1+J$16)+J$13)))) -> 856165.66 | K59: =IF(K$5<=$B59,K18,MAX(0,J59*(1+K$15)-MAX(0,-(J35*(1+K$16)+K$13)))) -> 967956.2 | ... AF59: =IF(AF$5<=$B59,AF18,MAX(0,AE59*(1+AF$15)-MAX(0,-(AE35*(1+AF$16)+AF$13)))) -> 3479442.3
B60: 2040 | C60: =C18 -> 302223.8 | D60: =IF(D$5<=$B60,D18,MAX(0,C60*(1+D$15)-MAX(0,-(C36*(1+D$16)+D$13)))) -> 351383.7 | E60: =IF(E$5<=$B60,E18,MAX(0,D60*(1+E$15)-MAX(0,-(D36*(1+E$16)+E$13)))) -> 419494.4 | F60: =IF(F$5<=$B60,F18,MAX(0,E60*(1+F$15)-MAX(0,-(E36*(1+F$16)+F$13)))) -> 493053.95 | G60: =IF(G$5<=$B60,G18,MAX(0,F60*(1+G$15)-MAX(0,-(F36*(1+G$16)+G$13)))) -> 572498.27 | H60: =IF(H$5<=$B60,H18,MAX(0,G60*(1+H$15)-MAX(0,-(G36*(1+H$16)+H$13)))) -> 659098.13 | I60: =IF(I$5<=$B60,I18,MAX(0,H60*(1+I$15)-MAX(0,-(H36*(1+I$16)+I$13)))) -> 753441.98 | J60: =IF(J$5<=$B60,J18,MAX(0,I60*(1+J$15)-MAX(0,-(I36*(1+J$16)+J$13)))) -> 856165.66 | K60: =IF(K$5<=$B60,K18,MAX(0,J60*(1+K$15)-MAX(0,-(J36*(1+K$16)+K$13)))) -> 967956.2 | ... AF60: =IF(AF$5<=$B60,AF18,MAX(0,AE60*(1+AF$15)-MAX(0,-(AE36*(1+AF$16)+AF$13)))) -> 3574376.2
B61: 2041 | C61: =C18 -> 302223.8 | D61: =IF(D$5<=$B61,D18,MAX(0,C61*(1+D$15)-MAX(0,-(C37*(1+D$16)+D$13)))) -> 351383.7 | E61: =IF(E$5<=$B61,E18,MAX(0,D61*(1+E$15)-MAX(0,-(D37*(1+E$16)+E$13)))) -> 419494.4 | F61: =IF(F$5<=$B61,F18,MAX(0,E61*(1+F$15)-MAX(0,-(E37*(1+F$16)+F$13)))) -> 493053.95 | G61: =IF(G$5<=$B61,G18,MAX(0,F61*(1+G$15)-MAX(0,-(F37*(1+G$16)+G$13)))) -> 572498.27 | H61: =IF(H$5<=$B61,H18,MAX(0,G61*(1+H$15)-MAX(0,-(G37*(1+H$16)+H$13)))) -> 659098.13 | I61: =IF(I$5<=$B61,I18,MAX(0,H61*(1+I$15)-MAX(0,-(H37*(1+I$16)+I$13)))) -> 753441.98 | J61: =IF(J$5<=$B61,J18,MAX(0,I61*(1+J$15)-MAX(0,-(I37*(1+J$16)+J$13)))) -> 856165.66 | K61: =IF(K$5<=$B61,K18,MAX(0,J61*(1+K$15)-MAX(0,-(J37*(1+K$16)+K$13)))) -> 967956.2 | ... AF61: =IF(AF$5<=$B61,AF18,MAX(0,AE61*(1+AF$15)-MAX(0,-(AE37*(1+AF$16)+AF$13)))) -> 3665171
B62: 2042 | C62: =C18 -> 302223.8 | D62: =IF(D$5<=$B62,D18,MAX(0,C62*(1+D$15)-MAX(0,-(C38*(1+D$16)+D$13)))) -> 351383.7 | E62: =IF(E$5<=$B62,E18,MAX(0,D62*(1+E$15)-MAX(0,-(D38*(1+E$16)+E$13)))) -> 419494.4 | F62: =IF(F$5<=$B62,F18,MAX(0,E62*(1+F$15)-MAX(0,-(E38*(1+F$16)+F$13)))) -> 493053.95 | G62: =IF(G$5<=$B62,G18,MAX(0,F62*(1+G$15)-MAX(0,-(F38*(1+G$16)+G$13)))) -> 572498.27 | H62: =IF(H$5<=$B62,H18,MAX(0,G62*(1+H$15)-MAX(0,-(G38*(1+H$16)+H$13)))) -> 659098.13 | I62: =IF(I$5<=$B62,I18,MAX(0,H62*(1+I$15)-MAX(0,-(H38*(1+I$16)+I$13)))) -> 753441.98 | J62: =IF(J$5<=$B62,J18,MAX(0,I62*(1+J$15)-MAX(0,-(I38*(1+J$16)+J$13)))) -> 856165.66 | K62: =IF(K$5<=$B62,K18,MAX(0,J62*(1+K$15)-MAX(0,-(J38*(1+K$16)+K$13)))) -> 967956.2 | ... AF62: =IF(AF$5<=$B62,AF18,MAX(0,AE62*(1+AF$15)-MAX(0,-(AE38*(1+AF$16)+AF$13)))) -> 3752252.1
B63: 2043 | C63: =C18 -> 302223.8 | D63: =IF(D$5<=$B63,D18,MAX(0,C63*(1+D$15)-MAX(0,-(C39*(1+D$16)+D$13)))) -> 351383.7 | E63: =IF(E$5<=$B63,E18,MAX(0,D63*(1+E$15)-MAX(0,-(D39*(1+E$16)+E$13)))) -> 419494.4 | F63: =IF(F$5<=$B63,F18,MAX(0,E63*(1+F$15)-MAX(0,-(E39*(1+F$16)+F$13)))) -> 493053.95 | G63: =IF(G$5<=$B63,G18,MAX(0,F63*(1+G$15)-MAX(0,-(F39*(1+G$16)+G$13)))) -> 572498.27 | H63: =IF(H$5<=$B63,H18,MAX(0,G63*(1+H$15)-MAX(0,-(G39*(1+H$16)+H$13)))) -> 659098.13 | I63: =IF(I$5<=$B63,I18,MAX(0,H63*(1+I$15)-MAX(0,-(H39*(1+I$16)+I$13)))) -> 753441.98 | J63: =IF(J$5<=$B63,J18,MAX(0,I63*(1+J$15)-MAX(0,-(I39*(1+J$16)+J$13)))) -> 856165.66 | K63: =IF(K$5<=$B63,K18,MAX(0,J63*(1+K$15)-MAX(0,-(J39*(1+K$16)+K$13)))) -> 967956.2 | ... AF63: =IF(AF$5<=$B63,AF18,MAX(0,AE63*(1+AF$15)-MAX(0,-(AE39*(1+AF$16)+AF$13)))) -> 3836007.5
B64: 2044 | C64: =C18 -> 302223.8 | D64: =IF(D$5<=$B64,D18,MAX(0,C64*(1+D$15)-MAX(0,-(C40*(1+D$16)+D$13)))) -> 351383.7 | E64: =IF(E$5<=$B64,E18,MAX(0,D64*(1+E$15)-MAX(0,-(D40*(1+E$16)+E$13)))) -> 419494.4 | F64: =IF(F$5<=$B64,F18,MAX(0,E64*(1+F$15)-MAX(0,-(E40*(1+F$16)+F$13)))) -> 493053.95 | G64: =IF(G$5<=$B64,G18,MAX(0,F64*(1+G$15)-MAX(0,-(F40*(1+G$16)+G$13)))) -> 572498.27 | H64: =IF(H$5<=$B64,H18,MAX(0,G64*(1+H$15)-MAX(0,-(G40*(1+H$16)+H$13)))) -> 659098.13 | I64: =IF(I$5<=$B64,I18,MAX(0,H64*(1+I$15)-MAX(0,-(H40*(1+I$16)+I$13)))) -> 753441.98 | J64: =IF(J$5<=$B64,J18,MAX(0,I64*(1+J$15)-MAX(0,-(I40*(1+J$16)+J$13)))) -> 856165.66 | K64: =IF(K$5<=$B64,K18,MAX(0,J64*(1+K$15)-MAX(0,-(J40*(1+K$16)+K$13)))) -> 967956.2 | ... AF64: =IF(AF$5<=$B64,AF18,MAX(0,AE64*(1+AF$15)-MAX(0,-(AE40*(1+AF$16)+AF$13)))) -> 3916792.9
B65: 2045 | C65: =C18 -> 302223.8 | D65: =IF(D$5<=$B65,D18,MAX(0,C65*(1+D$15)-MAX(0,-(C41*(1+D$16)+D$13)))) -> 351383.7 | E65: =IF(E$5<=$B65,E18,MAX(0,D65*(1+E$15)-MAX(0,-(D41*(1+E$16)+E$13)))) -> 419494.4 | F65: =IF(F$5<=$B65,F18,MAX(0,E65*(1+F$15)-MAX(0,-(E41*(1+F$16)+F$13)))) -> 493053.95 | G65: =IF(G$5<=$B65,G18,MAX(0,F65*(1+G$15)-MAX(0,-(F41*(1+G$16)+G$13)))) -> 572498.27 | H65: =IF(H$5<=$B65,H18,MAX(0,G65*(1+H$15)-MAX(0,-(G41*(1+H$16)+H$13)))) -> 659098.13 | I65: =IF(I$5<=$B65,I18,MAX(0,H65*(1+I$15)-MAX(0,-(H41*(1+I$16)+I$13)))) -> 753441.98 | J65: =IF(J$5<=$B65,J18,MAX(0,I65*(1+J$15)-MAX(0,-(I41*(1+J$16)+J$13)))) -> 856165.66 | K65: =IF(K$5<=$B65,K18,MAX(0,J65*(1+K$15)-MAX(0,-(J41*(1+K$16)+K$13)))) -> 967956.2 | ... AF65: =IF(AF$5<=$B65,AF18,MAX(0,AE65*(1+AF$15)-MAX(0,-(AE41*(1+AF$16)+AF$13)))) -> 3994935.3
A68: GRID C — HOW FAR TOTAL LIQUID SAVINGS SIT ABOVE THE FLOOR (cells outside the test window are ignored)
B69: Year | C69: 2026 | D69: 2027 | E69: 2028 | F69: 2029 | G69: 2030 | H69: 2031 | I69: 2032 | J69: 2033 | K69: 2034 | L69: 2035 | M69: 2036 | N69: 2037 | O69: 2038 | P69: 2039 | Q69: 2040 | R69: 2041 | S69: 2042 | T69: 2043 | U69: 2044 | V69: 2045 | W69: 2046 | X69: 2047 | Y69: 2048 | Z69: 2049 | AA69: 2050 | AB69: 2051 | AC69: 2052 | AD69: 2053 | AE69: 2054 | AF69: 2055
B70: 2026 | C70: =IF(OR(C$5<=$B70,C$5>Assumptions!$C$109),1000000000000,C22+C46-C$14) -> 1000000000000 | D70: =IF(OR(D$5<=$B70,D$5>Assumptions!$C$109),1000000000000,D22+D46-D$14) -> 148825.1 | E70: =IF(OR(E$5<=$B70,E$5>Assumptions!$C$109),1000000000000,E22+E46-E$14) -> 140511.83 | F70: =IF(OR(F$5<=$B70,F$5>Assumptions!$C$109),1000000000000,F22+F46-F$14) -> 169114.21 | G70: =IF(OR(G$5<=$B70,G$5>Assumptions!$C$109),1000000000000,G22+G46-G$14) -> 183740.08 | H70: =IF(OR(H$5<=$B70,H$5>Assumptions!$C$109),1000000000000,H22+H46-H$14) -> 199737.96 | I70: =IF(OR(I$5<=$B70,I$5>Assumptions!$C$109),1000000000000,I22+I46-I$14) -> 226221.64 | J70: =IF(OR(J$5<=$B70,J$5>Assumptions!$C$109),1000000000000,J22+J46-J$14) -> 254972.61 | ... AF70: =IF(OR(AF$5<=$B70,AF$5>Assumptions!$C$109),1000000000000,AF22+AF46-AF$14) -> 1000000000000
B71: 2027 | C71: =IF(OR(C$5<=$B71,C$5>Assumptions!$C$109),1000000000000,C23+C47-C$14) -> 1000000000000 | D71: =IF(OR(D$5<=$B71,D$5>Assumptions!$C$109),1000000000000,D23+D47-D$14) -> 1000000000000 | E71: =IF(OR(E$5<=$B71,E$5>Assumptions!$C$109),1000000000000,E23+E47-E$14) -> 218425.84 | F71: =IF(OR(F$5<=$B71,F$5>Assumptions!$C$109),1000000000000,F23+F47-F$14) -> 253261.34 | G71: =IF(OR(G$5<=$B71,G$5>Assumptions!$C$109),1000000000000,G23+G47-G$14) -> 274618.98 | H71: =IF(OR(H$5<=$B71,H$5>Assumptions!$C$109),1000000000000,H23+H47-H$14) -> 297887.17 | I71: =IF(OR(I$5<=$B71,I$5>Assumptions!$C$109),1000000000000,I23+I47-I$14) -> 332222.79 | J71: =IF(OR(J$5<=$B71,J$5>Assumptions!$C$109),1000000000000,J23+J47-J$14) -> 369453.85 | ... AF71: =IF(OR(AF$5<=$B71,AF$5>Assumptions!$C$109),1000000000000,AF23+AF47-AF$14) -> 1000000000000
B72: 2028 | C72: =IF(OR(C$5<=$B72,C$5>Assumptions!$C$109),1000000000000,C24+C48-C$14) -> 1000000000000 | D72: =IF(OR(D$5<=$B72,D$5>Assumptions!$C$109),1000000000000,D24+D48-D$14) -> 1000000000000 | E72: =IF(OR(E$5<=$B72,E$5>Assumptions!$C$109),1000000000000,E24+E48-E$14) -> 1000000000000 | F72: =IF(OR(F$5<=$B72,F$5>Assumptions!$C$109),1000000000000,F24+F48-F$14) -> 336632.74 | G72: =IF(OR(G$5<=$B72,G$5>Assumptions!$C$109),1000000000000,G24+G48-G$14) -> 364660.1 | H72: =IF(OR(H$5<=$B72,H$5>Assumptions!$C$109),1000000000000,H24+H48-H$14) -> 395131.58 | I72: =IF(OR(I$5<=$B72,I$5>Assumptions!$C$109),1000000000000,I24+I48-I$14) -> 437246.75 | J72: =IF(OR(J$5<=$B72,J$5>Assumptions!$C$109),1000000000000,J24+J48-J$14) -> 482879.72 | ... AF72: =IF(OR(AF$5<=$B72,AF$5>Assumptions!$C$109),1000000000000,AF24+AF48-AF$14) -> 1000000000000
B73: 2029 | C73: =IF(OR(C$5<=$B73,C$5>Assumptions!$C$109),1000000000000,C25+C49-C$14) -> 1000000000000 | D73: =IF(OR(D$5<=$B73,D$5>Assumptions!$C$109),1000000000000,D25+D49-D$14) -> 1000000000000 | E73: =IF(OR(E$5<=$B73,E$5>Assumptions!$C$109),1000000000000,E25+E49-E$14) -> 1000000000000 | F73: =IF(OR(F$5<=$B73,F$5>Assumptions!$C$109),1000000000000,F25+F49-F$14) -> 1000000000000 | G73: =IF(OR(G$5<=$B73,G$5>Assumptions!$C$109),1000000000000,G25+G49-G$14) -> 450481.09 | H73: =IF(OR(H$5<=$B73,H$5>Assumptions!$C$109),1000000000000,H25+H49-H$14) -> 487478.72 | I73: =IF(OR(I$5<=$B73,I$5>Assumptions!$C$109),1000000000000,I25+I49-I$14) -> 536694.77 | J73: =IF(OR(J$5<=$B73,J$5>Assumptions!$C$109),1000000000000,J25+J49-J$14) -> 589978.05 | ... AF73: =IF(OR(AF$5<=$B73,AF$5>Assumptions!$C$109),1000000000000,AF25+AF49-AF$14) -> 1000000000000
B74: 2030 | C74: =IF(OR(C$5<=$B74,C$5>Assumptions!$C$109),1000000000000,C26+C50-C$14) -> 1000000000000 | D74: =IF(OR(D$5<=$B74,D$5>Assumptions!$C$109),1000000000000,D26+D50-D$14) -> 1000000000000 | E74: =IF(OR(E$5<=$B74,E$5>Assumptions!$C$109),1000000000000,E26+E50-E$14) -> 1000000000000 | F74: =IF(OR(F$5<=$B74,F$5>Assumptions!$C$109),1000000000000,F26+F50-F$14) -> 1000000000000 | G74: =IF(OR(G$5<=$B74,G$5>Assumptions!$C$109),1000000000000,G26+G50-G$14) -> 1000000000000 | H74: =IF(OR(H$5<=$B74,H$5>Assumptions!$C$109),1000000000000,H26+H50-H$14) -> 575947.43 | I74: =IF(OR(I$5<=$B74,I$5>Assumptions!$C$109),1000000000000,I26+I50-I$14) -> 631561.94 | J74: =IF(OR(J$5<=$B74,J$5>Assumptions!$C$109),1000000000000,J26+J50-J$14) -> 691711.43 | ... AF74: =IF(OR(AF$5<=$B74,AF$5>Assumptions!$C$109),1000000000000,AF26+AF50-AF$14) -> 1000000000000
B75: 2031 | C75: =IF(OR(C$5<=$B75,C$5>Assumptions!$C$109),1000000000000,C27+C51-C$14) -> 1000000000000 | D75: =IF(OR(D$5<=$B75,D$5>Assumptions!$C$109),1000000000000,D27+D51-D$14) -> 1000000000000 | E75: =IF(OR(E$5<=$B75,E$5>Assumptions!$C$109),1000000000000,E27+E51-E$14) -> 1000000000000 | F75: =IF(OR(F$5<=$B75,F$5>Assumptions!$C$109),1000000000000,F27+F51-F$14) -> 1000000000000 | G75: =IF(OR(G$5<=$B75,G$5>Assumptions!$C$109),1000000000000,G27+G51-G$14) -> 1000000000000 | H75: =IF(OR(H$5<=$B75,H$5>Assumptions!$C$109),1000000000000,H27+H51-H$14) -> 1000000000000 | I75: =IF(OR(I$5<=$B75,I$5>Assumptions!$C$109),1000000000000,I27+I51-I$14) -> 721800.03 | J75: =IF(OR(J$5<=$B75,J$5>Assumptions!$C$109),1000000000000,J27+J51-J$14) -> 788475.95 | ... AF75: =IF(OR(AF$5<=$B75,AF$5>Assumptions!$C$109),1000000000000,AF27+AF51-AF$14) -> 1000000000000
B76: 2032 | C76: =IF(OR(C$5<=$B76,C$5>Assumptions!$C$109),1000000000000,C28+C52-C$14) -> 1000000000000 | D76: =IF(OR(D$5<=$B76,D$5>Assumptions!$C$109),1000000000000,D28+D52-D$14) -> 1000000000000 | E76: =IF(OR(E$5<=$B76,E$5>Assumptions!$C$109),1000000000000,E28+E52-E$14) -> 1000000000000 | F76: =IF(OR(F$5<=$B76,F$5>Assumptions!$C$109),1000000000000,F28+F52-F$14) -> 1000000000000 | G76: =IF(OR(G$5<=$B76,G$5>Assumptions!$C$109),1000000000000,G28+G52-G$14) -> 1000000000000 | H76: =IF(OR(H$5<=$B76,H$5>Assumptions!$C$109),1000000000000,H28+H52-H$14) -> 1000000000000 | I76: =IF(OR(I$5<=$B76,I$5>Assumptions!$C$109),1000000000000,I28+I52-I$14) -> 1000000000000 | J76: =IF(OR(J$5<=$B76,J$5>Assumptions!$C$109),1000000000000,J28+J52-J$14) -> 880518.79 | ... AF76: =IF(OR(AF$5<=$B76,AF$5>Assumptions!$C$109),1000000000000,AF28+AF52-AF$14) -> 1000000000000
B77: 2033 | C77: =IF(OR(C$5<=$B77,C$5>Assumptions!$C$109),1000000000000,C29+C53-C$14) -> 1000000000000 | D77: =IF(OR(D$5<=$B77,D$5>Assumptions!$C$109),1000000000000,D29+D53-D$14) -> 1000000000000 | E77: =IF(OR(E$5<=$B77,E$5>Assumptions!$C$109),1000000000000,E29+E53-E$14) -> 1000000000000 | F77: =IF(OR(F$5<=$B77,F$5>Assumptions!$C$109),1000000000000,F29+F53-F$14) -> 1000000000000 | G77: =IF(OR(G$5<=$B77,G$5>Assumptions!$C$109),1000000000000,G29+G53-G$14) -> 1000000000000 | H77: =IF(OR(H$5<=$B77,H$5>Assumptions!$C$109),1000000000000,H29+H53-H$14) -> 1000000000000 | I77: =IF(OR(I$5<=$B77,I$5>Assumptions!$C$109),1000000000000,I29+I53-I$14) -> 1000000000000 | J77: =IF(OR(J$5<=$B77,J$5>Assumptions!$C$109),1000000000000,J29+J53-J$14) -> 1000000000000 | ... AF77: =IF(OR(AF$5<=$B77,AF$5>Assumptions!$C$109),1000000000000,AF29+AF53-AF$14) -> 1000000000000
B78: 2034 | C78: =IF(OR(C$5<=$B78,C$5>Assumptions!$C$109),1000000000000,C30+C54-C$14) -> 1000000000000 | D78: =IF(OR(D$5<=$B78,D$5>Assumptions!$C$109),1000000000000,D30+D54-D$14) -> 1000000000000 | E78: =IF(OR(E$5<=$B78,E$5>Assumptions!$C$109),1000000000000,E30+E54-E$14) -> 1000000000000 | F78: =IF(OR(F$5<=$B78,F$5>Assumptions!$C$109),1000000000000,F30+F54-F$14) -> 1000000000000 | G78: =IF(OR(G$5<=$B78,G$5>Assumptions!$C$109),1000000000000,G30+G54-G$14) -> 1000000000000 | H78: =IF(OR(H$5<=$B78,H$5>Assumptions!$C$109),1000000000000,H30+H54-H$14) -> 1000000000000 | I78: =IF(OR(I$5<=$B78,I$5>Assumptions!$C$109),1000000000000,I30+I54-I$14) -> 1000000000000 | J78: =IF(OR(J$5<=$B78,J$5>Assumptions!$C$109),1000000000000,J30+J54-J$14) -> 1000000000000 | ... AF78: =IF(OR(AF$5<=$B78,AF$5>Assumptions!$C$109),1000000000000,AF30+AF54-AF$14) -> 1000000000000
B79: 2035 | C79: =IF(OR(C$5<=$B79,C$5>Assumptions!$C$109),1000000000000,C31+C55-C$14) -> 1000000000000 | D79: =IF(OR(D$5<=$B79,D$5>Assumptions!$C$109),1000000000000,D31+D55-D$14) -> 1000000000000 | E79: =IF(OR(E$5<=$B79,E$5>Assumptions!$C$109),1000000000000,E31+E55-E$14) -> 1000000000000 | F79: =IF(OR(F$5<=$B79,F$5>Assumptions!$C$109),1000000000000,F31+F55-F$14) -> 1000000000000 | G79: =IF(OR(G$5<=$B79,G$5>Assumptions!$C$109),1000000000000,G31+G55-G$14) -> 1000000000000 | H79: =IF(OR(H$5<=$B79,H$5>Assumptions!$C$109),1000000000000,H31+H55-H$14) -> 1000000000000 | I79: =IF(OR(I$5<=$B79,I$5>Assumptions!$C$109),1000000000000,I31+I55-I$14) -> 1000000000000 | J79: =IF(OR(J$5<=$B79,J$5>Assumptions!$C$109),1000000000000,J31+J55-J$14) -> 1000000000000 | ... AF79: =IF(OR(AF$5<=$B79,AF$5>Assumptions!$C$109),1000000000000,AF31+AF55-AF$14) -> 1000000000000
B80: 2036 | C80: =IF(OR(C$5<=$B80,C$5>Assumptions!$C$109),1000000000000,C32+C56-C$14) -> 1000000000000 | D80: =IF(OR(D$5<=$B80,D$5>Assumptions!$C$109),1000000000000,D32+D56-D$14) -> 1000000000000 | E80: =IF(OR(E$5<=$B80,E$5>Assumptions!$C$109),1000000000000,E32+E56-E$14) -> 1000000000000 | F80: =IF(OR(F$5<=$B80,F$5>Assumptions!$C$109),1000000000000,F32+F56-F$14) -> 1000000000000 | G80: =IF(OR(G$5<=$B80,G$5>Assumptions!$C$109),1000000000000,G32+G56-G$14) -> 1000000000000 | H80: =IF(OR(H$5<=$B80,H$5>Assumptions!$C$109),1000000000000,H32+H56-H$14) -> 1000000000000 | I80: =IF(OR(I$5<=$B80,I$5>Assumptions!$C$109),1000000000000,I32+I56-I$14) -> 1000000000000 | J80: =IF(OR(J$5<=$B80,J$5>Assumptions!$C$109),1000000000000,J32+J56-J$14) -> 1000000000000 | ... AF80: =IF(OR(AF$5<=$B80,AF$5>Assumptions!$C$109),1000000000000,AF32+AF56-AF$14) -> 1000000000000
B81: 2037 | C81: =IF(OR(C$5<=$B81,C$5>Assumptions!$C$109),1000000000000,C33+C57-C$14) -> 1000000000000 | D81: =IF(OR(D$5<=$B81,D$5>Assumptions!$C$109),1000000000000,D33+D57-D$14) -> 1000000000000 | E81: =IF(OR(E$5<=$B81,E$5>Assumptions!$C$109),1000000000000,E33+E57-E$14) -> 1000000000000 | F81: =IF(OR(F$5<=$B81,F$5>Assumptions!$C$109),1000000000000,F33+F57-F$14) -> 1000000000000 | G81: =IF(OR(G$5<=$B81,G$5>Assumptions!$C$109),1000000000000,G33+G57-G$14) -> 1000000000000 | H81: =IF(OR(H$5<=$B81,H$5>Assumptions!$C$109),1000000000000,H33+H57-H$14) -> 1000000000000 | I81: =IF(OR(I$5<=$B81,I$5>Assumptions!$C$109),1000000000000,I33+I57-I$14) -> 1000000000000 | J81: =IF(OR(J$5<=$B81,J$5>Assumptions!$C$109),1000000000000,J33+J57-J$14) -> 1000000000000 | ... AF81: =IF(OR(AF$5<=$B81,AF$5>Assumptions!$C$109),1000000000000,AF33+AF57-AF$14) -> 1000000000000
... B89: 2045 | C89: =IF(OR(C$5<=$B89,C$5>Assumptions!$C$109),1000000000000,C41+C65-C$14) -> 1000000000000 | D89: =IF(OR(D$5<=$B89,D$5>Assumptions!$C$109),1000000000000,D41+D65-D$14) -> 1000000000000 | E89: =IF(OR(E$5<=$B89,E$5>Assumptions!$C$109),1000000000000,E41+E65-E$14) -> 1000000000000 | F89: =IF(OR(F$5<=$B89,F$5>Assumptions!$C$109),1000000000000,F41+F65-F$14) -> 1000000000000 | G89: =IF(OR(G$5<=$B89,G$5>Assumptions!$C$109),1000000000000,G41+G65-G$14) -> 1000000000000 | H89: =IF(OR(H$5<=$B89,H$5>Assumptions!$C$109),1000000000000,H41+H65-H$14) -> 1000000000000 | I89: =IF(OR(I$5<=$B89,I$5>Assumptions!$C$109),1000000000000,I41+I65-I$14) -> 1000000000000 | J89: =IF(OR(J$5<=$B89,J$5>Assumptions!$C$109),1000000000000,J41+J65-J$14) -> 1000000000000 | ... AF89: =IF(OR(AF$5<=$B89,AF$5>Assumptions!$C$109),1000000000000,AF41+AF65-AF$14) -> 1000000000000
A91: VERDICT — FOR EVERY POSSIBLE YEAR DM COULD STOP
B92: DM's last full working year | C92: DM's age | D92: Liquid savings at that point | E92: Buffer required (12 months + business capital) | F92: TEST 2 | G92: Worst margin before MM turns 57 | H92: in year | I92: TEST 1 | J92: Pensions when MM turns 57 | K92: Required pot | L92: TEST 3 | M92: ALL THREE PASS | N92: ...AND EVERY LATER YEAR TOO
B93: 2026 | C93: =Assumptions!$D$24+$B93-Assumptions!$C$6 -> 44 | D93: =INDEX(Household_Base!$C$65:$AF$65,MATCH($B93,Household_Base!$C$5:$AF$5,0)) -> 302223.8 | E93: =INDEX(Household_Base!$C$22:$AF$22,MATCH($B93,Household_Base!$C$5:$AF$5,0))*Assumptions!$C$111/12+Assumptions!$C$112*INDEX(Assumptions!$C$9:$AF$9,MATCH($B93,Assumptions!$C$6:$AF$6,0)) -> 225400 | F93: =IF($D93>=$E93,1,0) -> 1 | G93: =MIN($C70:$AF70) -> 140511.83 | H93: =IF($G93>=1000000000000,"n/a",INDEX($C$5:$AF$5,MATCH($G93,$C70:$AF70,0))) -> 2028 | I93: =IF($G93>=0,1,0) -> 1 | J93: =INDEX(Household_Base!$C$62:$AF$62,MATCH($B93,Household_Base!$C$5:$AF$5,0))*INDEX(Returns!$C$16:$AF$16,MATCH(Assumptions!$C$109,Returns!$C$5:$AF$5,0))/INDEX(Returns!$C$16:$AF$16,MATCH($B93,Returns!$C$5:$AF$5,0))+INDEX(Returns!$C$16:$AF$16,MATCH(Assumptions!$C$109,Returns!$C$5:$AF$5,0))*(INDEX(Returns!$C$22:$AF$22,MATCH(Assumptions!$C$109,Returns!$C$5:$AF$5,0))-INDEX(Returns!$C$22:$AF$22,MATCH($B93,Returns!$C$5:$AF$5,0)))+INDEX(Household_Base!$C$63:$AF$63,MATCH($B93,Household_Base!$C$5:$AF$5,0))*INDEX(Returns!$C$17:$AF$17,MATCH(Assumptions!$C$109,Returns!$C$5:$AF$5,0))/INDEX(Returns!$C$17:$AF$17,MATCH($B93,Returns!$C$5:$AF$5,0)) -> 7588996.9 | K93: =INDEX(Household_Base!$C$24:$AF$24,MATCH(Assumptions!$C$109,Household_Base!$C$5:$AF$5,0))/Assumptions!$C$113/(1-Assumptions!$C$114) -> 2764385.2 | L93: =IF($J93>=$K93,1,0) -> 1 | M93: =MIN($F93,$I93,$L93) -> 1 | N93: =MIN($M93:$M$112) -> 1
B94: 2027 | C94: =Assumptions!$D$24+$B94-Assumptions!$C$6 -> 45 | D94: =INDEX(Household_Base!$C$65:$AF$65,MATCH($B94,Household_Base!$C$5:$AF$5,0)) -> 351383.7 | E94: =INDEX(Household_Base!$C$22:$AF$22,MATCH($B94,Household_Base!$C$5:$AF$5,0))*Assumptions!$C$111/12+Assumptions!$C$112*INDEX(Assumptions!$C$9:$AF$9,MATCH($B94,Assumptions!$C$6:$AF$6,0)) -> 234416 | F94: =IF($D94>=$E94,1,0) -> 1 | G94: =MIN($C71:$AF71) -> 218425.84 | H94: =IF($G94>=1000000000000,"n/a",INDEX($C$5:$AF$5,MATCH($G94,$C71:$AF71,0))) -> 2028 | I94: =IF($G94>=0,1,0) -> 1 | J94: =INDEX(Household_Base!$C$62:$AF$62,MATCH($B94,Household_Base!$C$5:$AF$5,0))*INDEX(Returns!$C$16:$AF$16,MATCH(Assumptions!$C$109,Returns!$C$5:$AF$5,0))/INDEX(Returns!$C$16:$AF$16,MATCH($B94,Returns!$C$5:$AF$5,0))+INDEX(Returns!$C$16:$AF$16,MATCH(Assumptions!$C$109,Returns!$C$5:$AF$5,0))*(INDEX(Returns!$C$22:$AF$22,MATCH(Assumptions!$C$109,Returns!$C$5:$AF$5,0))-INDEX(Returns!$C$22:$AF$22,MATCH($B94,Returns!$C$5:$AF$5,0)))+INDEX(Household_Base!$C$63:$AF$63,MATCH($B94,Household_Base!$C$5:$AF$5,0))*INDEX(Returns!$C$17:$AF$17,MATCH(Assumptions!$C$109,Returns!$C$5:$AF$5,0))/INDEX(Returns!$C$17:$AF$17,MATCH($B94,Returns!$C$5:$AF$5,0)) -> 7966539 | K94: =INDEX(Household_Base!$C$24:$AF$24,MATCH(Assumptions!$C$109,Household_Base!$C$5:$AF$5,0))/Assumptions!$C$113/(1-Assumptions!$C$114) -> 2764385.2 | L94: =IF($J94>=$K94,1,0) -> 1 | M94: =MIN($F94,$I94,$L94) -> 1 | N94: =MIN($M94:$M$112) -> 1
B95: 2028 | C95: =Assumptions!$D$24+$B95-Assumptions!$C$6 -> 46 | D95: =INDEX(Household_Base!$C$65:$AF$65,MATCH($B95,Household_Base!$C$5:$AF$5,0)) -> 419574.05 | E95: =INDEX(Household_Base!$C$22:$AF$22,MATCH($B95,Household_Base!$C$5:$AF$5,0))*Assumptions!$C$111/12+Assumptions!$C$112*INDEX(Assumptions!$C$9:$AF$9,MATCH($B95,Assumptions!$C$6:$AF$6,0)) -> 232111.36 | F95: =IF($D95>=$E95,1,0) -> 1 | G95: =MIN($C72:$AF72) -> 336632.74 | H95: =IF($G95>=1000000000000,"n/a",INDEX($C$5:$AF$5,MATCH($G95,$C72:$AF72,0))) -> 2029 | I95: =IF($G95>=0,1,0) -> 1 | J95: =INDEX(Household_Base!$C$62:$AF$62,MATCH($B95,Household_Base!$C$5:$AF$5,0))*INDEX(Returns!$C$16:$AF$16,MATCH(Assumptions!$C$109,Returns!$C$5:$AF$5,0))/INDEX(Returns!$C$16:$AF$16,MATCH($B95,Returns!$C$5:$AF$5,0))+INDEX(Returns!$C$16:$AF$16,MATCH(Assumptions!$C$109,Returns!$C$5:$AF$5,0))*(INDEX(Returns!$C$22:$AF$22,MATCH(Assumptions!$C$109,Returns!$C$5:$AF$5,0))-INDEX(Returns!$C$22:$AF$22,MATCH($B95,Returns!$C$5:$AF$5,0)))+INDEX(Household_Base!$C$63:$AF$63,MATCH($B95,Household_Base!$C$5:$AF$5,0))*INDEX(Returns!$C$17:$AF$17,MATCH(Assumptions!$C$109,Returns!$C$5:$AF$5,0))/INDEX(Returns!$C$17:$AF$17,MATCH($B95,Returns!$C$5:$AF$5,0)) -> 8312132.7 | K95: =INDEX(Household_Base!$C$24:$AF$24,MATCH(Assumptions!$C$109,Household_Base!$C$5:$AF$5,0))/Assumptions!$C$113/(1-Assumptions!$C$114) -> 2764385.2 | L95: =IF($J95>=$K95,1,0) -> 1 | M95: =MIN($F95,$I95,$L95) -> 1 | N95: =MIN($M95:$M$112) -> 1
B96: 2029 | C96: =Assumptions!$D$24+$B96-Assumptions!$C$6 -> 47 | D96: =INDEX(Household_Base!$C$65:$AF$65,MATCH($B96,Household_Base!$C$5:$AF$5,0)) -> 519058.37 | E96: =INDEX(Household_Base!$C$22:$AF$22,MATCH($B96,Household_Base!$C$5:$AF$5,0))*Assumptions!$C$111/12+Assumptions!$C$112*INDEX(Assumptions!$C$9:$AF$9,MATCH($B96,Assumptions!$C$6:$AF$6,0)) -> 212923.78 | F96: =IF($D96>=$E96,1,0) -> 1 | G96: =MIN($C73:$AF73) -> 450481.09 | H96: =IF($G96>=1000000000000,"n/a",INDEX($C$5:$AF$5,MATCH($G96,$C73:$AF73,0))) -> 2030 | I96: =IF($G96>=0,1,0) -> 1 | J96: =INDEX(Household_Base!$C$62:$AF$62,MATCH($B96,Household_Base!$C$5:$AF$5,0))*INDEX(Returns!$C$16:$AF$16,MATCH(Assumptions!$C$109,Returns!$C$5:$AF$5,0))/INDEX(Returns!$C$16:$AF$16,MATCH($B96,Returns!$C$5:$AF$5,0))+INDEX(Returns!$C$16:$AF$16,MATCH(Assumptions!$C$109,Returns!$C$5:$AF$5,0))*(INDEX(Returns!$C$22:$AF$22,MATCH(Assumptions!$C$109,Returns!$C$5:$AF$5,0))-INDEX(Returns!$C$22:$AF$22,MATCH($B96,Returns!$C$5:$AF$5,0)))+INDEX(Household_Base!$C$63:$AF$63,MATCH($B96,Household_Base!$C$5:$AF$5,0))*INDEX(Returns!$C$17:$AF$17,MATCH(Assumptions!$C$109,Returns!$C$5:$AF$5,0))/INDEX(Returns!$C$17:$AF$17,MATCH($B96,Returns!$C$5:$AF$5,0)) -> 8630209.4 | K96: =INDEX(Household_Base!$C$24:$AF$24,MATCH(Assumptions!$C$109,Household_Base!$C$5:$AF$5,0))/Assumptions!$C$113/(1-Assumptions!$C$114) -> 2764385.2 | L96: =IF($J96>=$K96,1,0) -> 1 | M96: =MIN($F96,$I96,$L96) -> 1 | N96: =MIN($M96:$M$112) -> 1
B97: 2030 | C97: =Assumptions!$D$24+$B97-Assumptions!$C$6 -> 48 | D97: =INDEX(Household_Base!$C$65:$AF$65,MATCH($B97,Household_Base!$C$5:$AF$5,0)) -> 637639.51 | E97: =INDEX(Household_Base!$C$22:$AF$22,MATCH($B97,Household_Base!$C$5:$AF$5,0))*Assumptions!$C$111/12+Assumptions!$C$112*INDEX(Assumptions!$C$9:$AF$9,MATCH($B97,Assumptions!$C$6:$AF$6,0)) -> 217182.25 | F97: =IF($D97>=$E97,1,0) -> 1 | G97: =MIN($C74:$AF74) -> 575947.43 | H97: =IF($G97>=1000000000000,"n/a",INDEX($C$5:$AF$5,MATCH($G97,$C74:$AF74,0))) -> 2031 | I97: =IF($G97>=0,1,0) -> 1 | J97: =INDEX(Household_Base!$C$62:$AF$62,MATCH($B97,Household_Base!$C$5:$AF$5,0))*INDEX(Returns!$C$16:$AF$16,MATCH(Assumptions!$C$109,Returns!$C$5:$AF$5,0))/INDEX(Returns!$C$16:$AF$16,MATCH($B97,Returns!$C$5:$AF$5,0))+INDEX(Returns!$C$16:$AF$16,MATCH(Assumptions!$C$109,Returns!$C$5:$AF$5,0))*(INDEX(Returns!$C$22:$AF$22,MATCH(Assumptions!$C$109,Returns!$C$5:$AF$5,0))-INDEX(Returns!$C$22:$AF$22,MATCH($B97,Returns!$C$5:$AF$5,0)))+INDEX(Household_Base!$C$63:$AF$63,MATCH($B97,Household_Base!$C$5:$AF$5,0))*INDEX(Returns!$C$17:$AF$17,MATCH(Assumptions!$C$109,Returns!$C$5:$AF$5,0))/INDEX(Returns!$C$17:$AF$17,MATCH($B97,Returns!$C$5:$AF$5,0)) -> 8922914.1 | K97: =INDEX(Household_Base!$C$24:$AF$24,MATCH(Assumptions!$C$109,Household_Base!$C$5:$AF$5,0))/Assumptions!$C$113/(1-Assumptions!$C$114) -> 2764385.2 | L97: =IF($J97>=$K97,1,0) -> 1 | M97: =MIN($F97,$I97,$L97) -> 1 | N97: =MIN($M97:$M$112) -> 1
B98: 2031 | C98: =Assumptions!$D$24+$B98-Assumptions!$C$6 -> 49 | D98: =INDEX(Household_Base!$C$65:$AF$65,MATCH($B98,Household_Base!$C$5:$AF$5,0)) -> 766849.01 | E98: =INDEX(Household_Base!$C$22:$AF$22,MATCH($B98,Household_Base!$C$5:$AF$5,0))*Assumptions!$C$111/12+Assumptions!$C$112*INDEX(Assumptions!$C$9:$AF$9,MATCH($B98,Assumptions!$C$6:$AF$6,0)) -> 221525.9 | F98: =IF($D98>=$E98,1,0) -> 1 | G98: =MIN($C75:$AF75) -> 721800.03 | H98: =IF($G98>=1000000000000,"n/a",INDEX($C$5:$AF$5,MATCH($G98,$C75:$AF75,0))) -> 2032 | I98: =IF($G98>=0,1,0) -> 1 | J98: =INDEX(Household_Base!$C$62:$AF$62,MATCH($B98,Household_Base!$C$5:$AF$5,0))*INDEX(Returns!$C$16:$AF$16,MATCH(Assumptions!$C$109,Returns!$C$5:$AF$5,0))/INDEX(Returns!$C$16:$AF$16,MATCH($B98,Returns!$C$5:$AF$5,0))+INDEX(Returns!$C$16:$AF$16,MATCH(Assumptions!$C$109,Returns!$C$5:$AF$5,0))*(INDEX(Returns!$C$22:$AF$22,MATCH(Assumptions!$C$109,Returns!$C$5:$AF$5,0))-INDEX(Returns!$C$22:$AF$22,MATCH($B98,Returns!$C$5:$AF$5,0)))+INDEX(Household_Base!$C$63:$AF$63,MATCH($B98,Household_Base!$C$5:$AF$5,0))*INDEX(Returns!$C$17:$AF$17,MATCH(Assumptions!$C$109,Returns!$C$5:$AF$5,0))/INDEX(Returns!$C$17:$AF$17,MATCH($B98,Returns!$C$5:$AF$5,0)) -> 9199357.3 | K98: =INDEX(Household_Base!$C$24:$AF$24,MATCH(Assumptions!$C$109,Household_Base!$C$5:$AF$5,0))/Assumptions!$C$113/(1-Assumptions!$C$114) -> 2764385.2 | L98: =IF($J98>=$K98,1,0) -> 1 | M98: =MIN($F98,$I98,$L98) -> 1 | N98: =MIN($M98:$M$112) -> 1
B99: 2032 | C99: =Assumptions!$D$24+$B99-Assumptions!$C$6 -> 50 | D99: =INDEX(Household_Base!$C$65:$AF$65,MATCH($B99,Household_Base!$C$5:$AF$5,0)) -> 916519.64 | E99: =INDEX(Household_Base!$C$22:$AF$22,MATCH($B99,Household_Base!$C$5:$AF$5,0))*Assumptions!$C$111/12+Assumptions!$C$112*INDEX(Assumptions!$C$9:$AF$9,MATCH($B99,Assumptions!$C$6:$AF$6,0)) -> 225956.41 | F99: =IF($D99>=$E99,1,0) -> 1 | G99: =MIN($C76:$AF76) -> 880518.79 | H99: =IF($G99>=1000000000000,"n/a",INDEX($C$5:$AF$5,MATCH($G99,$C76:$AF76,0))) -> 2033 | I99: =IF($G99>=0,1,0) -> 1 | J99: =INDEX(Household_Base!$C$62:$AF$62,MATCH($B99,Household_Base!$C$5:$AF$5,0))*INDEX(Returns!$C$16:$AF$16,MATCH(Assumptions!$C$109,Returns!$C$5:$AF$5,0))/INDEX(Returns!$C$16:$AF$16,MATCH($B99,Returns!$C$5:$AF$5,0))+INDEX(Returns!$C$16:$AF$16,MATCH(Assumptions!$C$109,Returns!$C$5:$AF$5,0))*(INDEX(Returns!$C$22:$AF$22,MATCH(Assumptions!$C$109,Returns!$C$5:$AF$5,0))-INDEX(Returns!$C$22:$AF$22,MATCH($B99,Returns!$C$5:$AF$5,0)))+INDEX(Household_Base!$C$63:$AF$63,MATCH($B99,Household_Base!$C$5:$AF$5,0))*INDEX(Returns!$C$17:$AF$17,MATCH(Assumptions!$C$109,Returns!$C$5:$AF$5,0))/INDEX(Returns!$C$17:$AF$17,MATCH($B99,Returns!$C$5:$AF$5,0)) -> 9460442.6 | K99: =INDEX(Household_Base!$C$24:$AF$24,MATCH(Assumptions!$C$109,Household_Base!$C$5:$AF$5,0))/Assumptions!$C$113/(1-Assumptions!$C$114) -> 2764385.2 | L99: =IF($J99>=$K99,1,0) -> 1 | M99: =MIN($F99,$I99,$L99) -> 1 | N99: =MIN($M99:$M$112) -> 1
B100: 2033 | C100: =Assumptions!$D$24+$B100-Assumptions!$C$6 -> 51 | D100: =INDEX(Household_Base!$C$65:$AF$65,MATCH($B100,Household_Base!$C$5:$AF$5,0)) -> 1079132.8 | E100: =INDEX(Household_Base!$C$22:$AF$22,MATCH($B100,Household_Base!$C$5:$AF$5,0))*Assumptions!$C$111/12+Assumptions!$C$112*INDEX(Assumptions!$C$9:$AF$9,MATCH($B100,Assumptions!$C$6:$AF$6,0)) -> 230475.54 | F100: =IF($D100>=$E100,1,0) -> 1 | G100: =MIN($C77:$AF77) -> 1096955.2 | H100: =IF($G100>=1000000000000,"n/a",INDEX($C$5:$AF$5,MATCH($G100,$C77:$AF77,0))) -> 2034 | I100: =IF($G100>=0,1,0) -> 1 | J100: =INDEX(Household_Base!$C$62:$AF$62,MATCH($B100,Household_Base!$C$5:$AF$5,0))*INDEX(Returns!$C$16:$AF$16,MATCH(Assumptions!$C$109,Returns!$C$5:$AF$5,0))/INDEX(Returns!$C$16:$AF$16,MATCH($B100,Returns!$C$5:$AF$5,0))+INDEX(Returns!$C$16:$AF$16,MATCH(Assumptions!$C$109,Returns!$C$5:$AF$5,0))*(INDEX(Returns!$C$22:$AF$22,MATCH(Assumptions!$C$109,Returns!$C$5:$AF$5,0))-INDEX(Returns!$C$22:$AF$22,MATCH($B100,Returns!$C$5:$AF$5,0)))+INDEX(Household_Base!$C$63:$AF$63,MATCH($B100,Household_Base!$C$5:$AF$5,0))*INDEX(Returns!$C$17:$AF$17,MATCH(Assumptions!$C$109,Returns!$C$5:$AF$5,0))/INDEX(Returns!$C$17:$AF$17,MATCH($B100,Returns!$C$5:$AF$5,0)) -> 9707406.6 | K100: =INDEX(Household_Base!$C$24:$AF$24,MATCH(Assumptions!$C$109,Household_Base!$C$5:$AF$5,0))/Assumptions!$C$113/(1-Assumptions!$C$114) -> 2764385.2 | L100: =IF($J100>=$K100,1,0) -> 1 | M100: =MIN($F100,$I100,$L100) -> 1 | N100: =MIN($M100:$M$112) -> 1
B101: 2034 | C101: =Assumptions!$D$24+$B101-Assumptions!$C$6 -> 52 | D101: =INDEX(Household_Base!$C$65:$AF$65,MATCH($B101,Household_Base!$C$5:$AF$5,0)) -> 1277616.5 | E101: =INDEX(Household_Base!$C$22:$AF$22,MATCH($B101,Household_Base!$C$5:$AF$5,0))*Assumptions!$C$111/12+Assumptions!$C$112*INDEX(Assumptions!$C$9:$AF$9,MATCH($B101,Assumptions!$C$6:$AF$6,0)) -> 213160.02 | F101: =IF($D101>=$E101,1,0) -> 1 | G101: =MIN($C78:$AF78) -> 1308713.9 | H101: =IF($G101>=1000000000000,"n/a",INDEX($C$5:$AF$5,MATCH($G101,$C78:$AF78,0))) -> 2035 | I101: =IF($G101>=0,1,0) -> 1 | J101: =INDEX(Household_Base!$C$62:$AF$62,MATCH($B101,Household_Base!$C$5:$AF$5,0))*INDEX(Returns!$C$16:$AF$16,MATCH(Assumptions!$C$109,Returns!$C$5:$AF$5,0))/INDEX(Returns!$C$16:$AF$16,MATCH($B101,Returns!$C$5:$AF$5,0))+INDEX(Returns!$C$16:$AF$16,MATCH(Assumptions!$C$109,Returns!$C$5:$AF$5,0))*(INDEX(Returns!$C$22:$AF$22,MATCH(Assumptions!$C$109,Returns!$C$5:$AF$5,0))-INDEX(Returns!$C$22:$AF$22,MATCH($B101,Returns!$C$5:$AF$5,0)))+INDEX(Household_Base!$C$63:$AF$63,MATCH($B101,Household_Base!$C$5:$AF$5,0))*INDEX(Returns!$C$17:$AF$17,MATCH(Assumptions!$C$109,Returns!$C$5:$AF$5,0))/INDEX(Returns!$C$17:$AF$17,MATCH($B101,Returns!$C$5:$AF$5,0)) -> 9941378.4 | K101: =INDEX(Household_Base!$C$24:$AF$24,MATCH(Assumptions!$C$109,Household_Base!$C$5:$AF$5,0))/Assumptions!$C$113/(1-Assumptions!$C$114) -> 2764385.2 | L101: =IF($J101>=$K101,1,0) -> 1 | M101: =MIN($F101,$I101,$L101) -> 1 | N101: =MIN($M101:$M$112) -> 1
B102: 2035 | C102: =Assumptions!$D$24+$B102-Assumptions!$C$6 -> 53 | D102: =INDEX(Household_Base!$C$65:$AF$65,MATCH($B102,Household_Base!$C$5:$AF$5,0)) -> 1492988.4 | E102: =INDEX(Household_Base!$C$22:$AF$22,MATCH($B102,Household_Base!$C$5:$AF$5,0))*Assumptions!$C$111/12+Assumptions!$C$112*INDEX(Assumptions!$C$9:$AF$9,MATCH($B102,Assumptions!$C$6:$AF$6,0)) -> 217423.22 | F102: =IF($D102>=$E102,1,0) -> 1 | G102: =MIN($C79:$AF79) -> 1538579.6 | H102: =IF($G102>=1000000000000,"n/a",INDEX($C$5:$AF$5,MATCH($G102,$C79:$AF79,0))) -> 2036 | I102: =IF($G102>=0,1,0) -> 1 | J102: =INDEX(Household_Base!$C$62:$AF$62,MATCH($B102,Household_Base!$C$5:$AF$5,0))*INDEX(Returns!$C$16:$AF$16,MATCH(Assumptions!$C$109,Returns!$C$5:$AF$5,0))/INDEX(Returns!$C$16:$AF$16,MATCH($B102,Returns!$C$5:$AF$5,0))+INDEX(Returns!$C$16:$AF$16,MATCH(Assumptions!$C$109,Returns!$C$5:$AF$5,0))*(INDEX(Returns!$C$22:$AF$22,MATCH(Assumptions!$C$109,Returns!$C$5:$AF$5,0))-INDEX(Returns!$C$22:$AF$22,MATCH($B102,Returns!$C$5:$AF$5,0)))+INDEX(Household_Base!$C$63:$AF$63,MATCH($B102,Household_Base!$C$5:$AF$5,0))*INDEX(Returns!$C$17:$AF$17,MATCH(Assumptions!$C$109,Returns!$C$5:$AF$5,0))/INDEX(Returns!$C$17:$AF$17,MATCH($B102,Returns!$C$5:$AF$5,0)) -> 10163392 | K102: =INDEX(Household_Base!$C$24:$AF$24,MATCH(Assumptions!$C$109,Household_Base!$C$5:$AF$5,0))/Assumptions!$C$113/(1-Assumptions!$C$114) -> 2764385.2 | L102: =IF($J102>=$K102,1,0) -> 1 | M102: =MIN($F102,$I102,$L102) -> 1 | N102: =MIN($M102:$M$112) -> 1
B103: 2036 | C103: =Assumptions!$D$24+$B103-Assumptions!$C$6 -> 54 | D103: =INDEX(Household_Base!$C$65:$AF$65,MATCH($B103,Household_Base!$C$5:$AF$5,0)) -> 1726539.6 | E103: =INDEX(Household_Base!$C$22:$AF$22,MATCH($B103,Household_Base!$C$5:$AF$5,0))*Assumptions!$C$111/12+Assumptions!$C$112*INDEX(Assumptions!$C$9:$AF$9,MATCH($B103,Assumptions!$C$6:$AF$6,0)) -> 221771.69 | F103: =IF($D103>=$E103,1,0) -> 1 | G103: =MIN($C80:$AF80) -> 1785349.1 | H103: =IF($G103>=1000000000000,"n/a",INDEX($C$5:$AF$5,MATCH($G103,$C80:$AF80,0))) -> 2037 | I103: =IF($G103>=0,1,0) -> 1 | J103: =INDEX(Household_Base!$C$62:$AF$62,MATCH($B103,Household_Base!$C$5:$AF$5,0))*INDEX(Returns!$C$16:$AF$16,MATCH(Assumptions!$C$109,Returns!$C$5:$AF$5,0))/INDEX(Returns!$C$16:$AF$16,MATCH($B103,Returns!$C$5:$AF$5,0))+INDEX(Returns!$C$16:$AF$16,MATCH(Assumptions!$C$109,Returns!$C$5:$AF$5,0))*(INDEX(Returns!$C$22:$AF$22,MATCH(Assumptions!$C$109,Returns!$C$5:$AF$5,0))-INDEX(Returns!$C$22:$AF$22,MATCH($B103,Returns!$C$5:$AF$5,0)))+INDEX(Household_Base!$C$63:$AF$63,MATCH($B103,Household_Base!$C$5:$AF$5,0))*INDEX(Returns!$C$17:$AF$17,MATCH(Assumptions!$C$109,Returns!$C$5:$AF$5,0))/INDEX(Returns!$C$17:$AF$17,MATCH($B103,Returns!$C$5:$AF$5,0)) -> 10374396 | K103: =INDEX(Household_Base!$C$24:$AF$24,MATCH(Assumptions!$C$109,Household_Base!$C$5:$AF$5,0))/Assumptions!$C$113/(1-Assumptions!$C$114) -> 2764385.2 | L103: =IF($J103>=$K103,1,0) -> 1 | M103: =MIN($F103,$I103,$L103) -> 1 | N103: =MIN($M103:$M$112) -> 1
B104: 2037 | C104: =Assumptions!$D$24+$B104-Assumptions!$C$6 -> 55 | D104: =INDEX(Household_Base!$C$65:$AF$65,MATCH($B104,Household_Base!$C$5:$AF$5,0)) -> 1977068.3 | E104: =INDEX(Household_Base!$C$22:$AF$22,MATCH($B104,Household_Base!$C$5:$AF$5,0))*Assumptions!$C$111/12+Assumptions!$C$112*INDEX(Assumptions!$C$9:$AF$9,MATCH($B104,Assumptions!$C$6:$AF$6,0)) -> 226207.12 | F104: =IF($D104>=$E104,1,0) -> 1 | G104: =MIN($C81:$AF81) -> 2046599.9 | H104: =IF($G104>=1000000000000,"n/a",INDEX($C$5:$AF$5,MATCH($G104,$C81:$AF81,0))) -> 2038 | I104: =IF($G104>=0,1,0) -> 1 | J104: =INDEX(Household_Base!$C$62:$AF$62,MATCH($B104,Household_Base!$C$5:$AF$5,0))*INDEX(Returns!$C$16:$AF$16,MATCH(Assumptions!$C$109,Returns!$C$5:$AF$5,0))/INDEX(Returns!$C$16:$AF$16,MATCH($B104,Returns!$C$5:$AF$5,0))+INDEX(Returns!$C$16:$AF$16,MATCH(Assumptions!$C$109,Returns!$C$5:$AF$5,0))*(INDEX(Returns!$C$22:$AF$22,MATCH(Assumptions!$C$109,Returns!$C$5:$AF$5,0))-INDEX(Returns!$C$22:$AF$22,MATCH($B104,Returns!$C$5:$AF$5,0)))+INDEX(Household_Base!$C$63:$AF$63,MATCH($B104,Household_Base!$C$5:$AF$5,0))*INDEX(Returns!$C$17:$AF$17,MATCH(Assumptions!$C$109,Returns!$C$5:$AF$5,0))/INDEX(Returns!$C$17:$AF$17,MATCH($B104,Returns!$C$5:$AF$5,0)) -> 10575263 | K104: =INDEX(Household_Base!$C$24:$AF$24,MATCH(Assumptions!$C$109,Household_Base!$C$5:$AF$5,0))/Assumptions!$C$113/(1-Assumptions!$C$114) -> 2764385.2 | L104: =IF($J104>=$K104,1,0) -> 1 | M104: =MIN($F104,$I104,$L104) -> 1 | N104: =MIN($M104:$M$112) -> 1
... B112: 2045 | C112: =Assumptions!$D$24+$B112-Assumptions!$C$6 -> 63 | D112: =INDEX(Household_Base!$C$65:$AF$65,MATCH($B112,Household_Base!$C$5:$AF$5,0)) -> 4478415.8 | E112: =INDEX(Household_Base!$C$22:$AF$22,MATCH($B112,Household_Base!$C$5:$AF$5,0))*Assumptions!$C$111/12+Assumptions!$C$112*INDEX(Assumptions!$C$9:$AF$9,MATCH($B112,Assumptions!$C$6:$AF$6,0)) -> 229598.37 | F112: =IF($D112>=$E112,1,0) -> 1 | G112: =MIN($C89:$AF89) -> 4672814.4 | H112: =IF($G112>=1000000000000,"n/a",INDEX($C$5:$AF$5,MATCH($G112,$C89:$AF89,0))) -> 2046 | I112: =IF($G112>=0,1,0) -> 1 | J112: =INDEX(Household_Base!$C$62:$AF$62,MATCH($B112,Household_Base!$C$5:$AF$5,0))*INDEX(Returns!$C$16:$AF$16,MATCH(Assumptions!$C$109,Returns!$C$5:$AF$5,0))/INDEX(Returns!$C$16:$AF$16,MATCH($B112,Returns!$C$5:$AF$5,0))+INDEX(Returns!$C$16:$AF$16,MATCH(Assumptions!$C$109,Returns!$C$5:$AF$5,0))*(INDEX(Returns!$C$22:$AF$22,MATCH(Assumptions!$C$109,Returns!$C$5:$AF$5,0))-INDEX(Returns!$C$22:$AF$22,MATCH($B112,Returns!$C$5:$AF$5,0)))+INDEX(Household_Base!$C$63:$AF$63,MATCH($B112,Household_Base!$C$5:$AF$5,0))*INDEX(Returns!$C$17:$AF$17,MATCH(Assumptions!$C$109,Returns!$C$5:$AF$5,0))/INDEX(Returns!$C$17:$AF$17,MATCH($B112,Returns!$C$5:$AF$5,0)) -> 11905903 | K112: =INDEX(Household_Base!$C$24:$AF$24,MATCH(Assumptions!$C$109,Household_Base!$C$5:$AF$5,0))/Assumptions!$C$113/(1-Assumptions!$C$114) -> 2764385.2 | L112: =IF($J112>=$K112,1,0) -> 1 | M112: =MIN($F112,$I112,$L112) -> 1 | N112: =MIN($M112:$M$112) -> 1
A114: THE ANSWER
B115: RUNG 1 — earliest DM can stop and still pass all three tests, for good | C115: =IFERROR(INDEX($B93:$B112,MATCH(1,$N93:$N112,0)),"never") -> 2026
B116: DM's age at that point | C116: =IF(ISNUMBER($C115),Assumptions!$D$24+$C115-Assumptions!$C$6,"n/a") -> 44
B117: RUNG 2 — earliest DM can stop with MM's pay covering everything, no drawdown at all | C117: =IFERROR(INDEX($C$5:$AF$5,MATCH(1,$C$9:$AF$9,0))-1,"never") -> 2031
B118: DM's age at that point | C118: =IF(ISNUMBER($C117),Assumptions!$D$24+$C117-Assumptions!$C$6,"n/a") -> 49
B119: RUNG 3 — earliest DM can stop with MM's pay also clearing the comfort bar | C119: =IFERROR(INDEX($C$5:$AF$5,MATCH(1,$C$10:$AF$10,0))-1,"never") -> 2033
B120: DM's age at that point | C120: =IF(ISNUMBER($C119),Assumptions!$D$24+$C119-Assumptions!$C$6,"n/a") -> 51

Sheet Scen_3rd_Child
A1: SCENARIO — A THIRD CHILD BORN JULY 2027
A2: MM takes nine months' leave from July 2027: six months at full base salary (£110,000 rate), three months at half pay, returning in April 2028 on total income of £180,000. Pension contributions are modelled on full base salary throughout the leave. Nursery for the third child runs September 2028 to August 2031; nannies are unchanged because EM turning 10 in December 2033 is the later constraint.
A4: MM — INCOME THROUGH MATERNITY LEAVE AND AFTER
B5: Year | C5: 2026 | D5: 2027 | E5: 2028 | F5: 2029 | G5: 2030 | H5: 2031 | I5: 2032 | J5: 2033 | K5: 2034 | L5: 2035 | M5: 2036 | N5: 2037 | O5: 2038 | P5: 2039 | Q5: 2040 | R5: 2041 | S5: 2042 | T5: 2043 | U5: 2044 | V5: 2045 | W5: 2046 | X5: 2047 | Y5: 2048 | Z5: 2049 | AA5: 2050 | AB5: 2051 | AC5: 2052 | AD5: 2053 | AE5: 2054 | AF5: 2055
B6: Inflation index | C6: =Assumptions!C$9 -> 1 | D6: =Assumptions!D$9 -> 1.04 | E6: =Assumptions!E$9 -> 1.0816 | F6: =Assumptions!F$9 -> 1.103232 | G6: =Assumptions!G$9 -> 1.1252966 | H6: =Assumptions!H$9 -> 1.1478026 | I6: =Assumptions!I$9 -> 1.1707586 | J6: =Assumptions!J$9 -> 1.1941738 | ... AF6: =Assumptions!AF$9 -> 1.8461684
B8: MM — total gross income | C8: =IF(C5<Assumptions!$C$98,Assumptions!$C$21*C6,IF(C5=Assumptions!$C$98,(Assumptions!$C$99-1)/12*Assumptions!$C$21*C6+Assumptions!$C$100/12*Assumptions!$C$101,IF(C5=Assumptions!$C$104,Assumptions!$C$102/12*Assumptions!$C$101*0.5+Assumptions!$C$105/12*Assumptions!$C$103,Assumptions!$C$103*C6/Assumptions!$E$9))) -> 170000 | D8: =IF(D5<Assumptions!$C$98,Assumptions!$C$21*D6,IF(D5=Assumptions!$C$98,(Assumptions!$C$99-1)/12*Assumptions!$C$21*D6+Assumptions!$C$100/12*Assumptions!$C$101,IF(D5=Assumptions!$C$104,Assumptions!$C$102/12*Assumptions!$C$101*0.5+Assumptions!$C$105/12*Assumptions!$C$103,Assumptions!$C$103*D6/Assumptions!$E$9))) -> 143400 | E8: =IF(E5<Assumptions!$C$98,Assumptions!$C$21*E6,IF(E5=Assumptions!$C$98,(Assumptions!$C$99-1)/12*Assumptions!$C$21*E6+Assumptions!$C$100/12*Assumptions!$C$101,IF(E5=Assumptions!$C$104,Assumptions!$C$102/12*Assumptions!$C$101*0.5+Assumptions!$C$105/12*Assumptions!$C$103,Assumptions!$C$103*E6/Assumptions!$E$9))) -> 148750 | F8: =IF(F5<Assumptions!$C$98,Assumptions!$C$21*F6,IF(F5=Assumptions!$C$98,(Assumptions!$C$99-1)/12*Assumptions!$C$21*F6+Assumptions!$C$100/12*Assumptions!$C$101,IF(F5=Assumptions!$C$104,Assumptions!$C$102/12*Assumptions!$C$101*0.5+Assumptions!$C$105/12*Assumptions!$C$103,Assumptions!$C$103*F6/Assumptions!$E$9))) -> 183600 | G8: =IF(G5<Assumptions!$C$98,Assumptions!$C$21*G6,IF(G5=Assumptions!$C$98,(Assumptions!$C$99-1)/12*Assumptions!$C$21*G6+Assumptions!$C$100/12*Assumptions!$C$101,IF(G5=Assumptions!$C$104,Assumptions!$C$102/12*Assumptions!$C$101*0.5+Assumptions!$C$105/12*Assumptions!$C$103,Assumptions!$C$103*G6/Assumptions!$E$9))) -> 187272 | H8: =IF(H5<Assumptions!$C$98,Assumptions!$C$21*H6,IF(H5=Assumptions!$C$98,(Assumptions!$C$99-1)/12*Assumptions!$C$21*H6+Assumptions!$C$100/12*Assumptions!$C$101,IF(H5=Assumptions!$C$104,Assumptions!$C$102/12*Assumptions!$C$101*0.5+Assumptions!$C$105/12*Assumptions!$C$103,Assumptions!$C$103*H6/Assumptions!$E$9))) -> 191017.44 | I8: =IF(I5<Assumptions!$C$98,Assumptions!$C$21*I6,IF(I5=Assumptions!$C$98,(Assumptions!$C$99-1)/12*Assumptions!$C$21*I6+Assumptions!$C$100/12*Assumptions!$C$101,IF(I5=Assumptions!$C$104,Assumptions!$C$102/12*Assumptions!$C$101*0.5+Assumptions!$C$105/12*Assumptions!$C$103,Assumptions!$C$103*I6/Assumptions!$E$9))) -> 194837.79 | J8: =IF(J5<Assumptions!$C$98,Assumptions!$C$21*J6,IF(J5=Assumptions!$C$98,(Assumptions!$C$99-1)/12*Assumptions!$C$21*J6+Assumptions!$C$100/12*Assumptions!$C$101,IF(J5=Assumptions!$C$104,Assumptions!$C$102/12*Assumptions!$C$101*0.5+Assumptions!$C$105/12*Assumptions!$C$103,Assumptions!$C$103*J6/Assumptions!$E$9))) -> 198734.54 | ... AF8: =IF(AF5<Assumptions!$C$98,Assumptions!$C$21*AF6,IF(AF5=Assumptions!$C$98,(Assumptions!$C$99-1)/12*Assumptions!$C$21*AF6+Assumptions!$C$100/12*Assumptions!$C$101,IF(AF5=Assumptions!$C$104,Assumptions!$C$102/12*Assumptions!$C$101*0.5+Assumptions!$C$105/12*Assumptions!$C$103,Assumptions!$C$103*AF6/Assumptions!$E$9))) -> 307239.57
B9: MM — base salary (pension is paid on full base throughout the leave) | C9: =MM_Income!C$9 -> 100000 | D9: =MM_Income!D$9 -> 110000 | E9: =MM_Income!E$9 -> 114400 | F9: =MM_Income!F$9 -> 116688 | G9: =MM_Income!G$9 -> 119021.76 | H9: =MM_Income!H$9 -> 121402.2 | I9: =MM_Income!I$9 -> 123830.24 | J9: =MM_Income!J$9 -> 126306.84 | ... AF9: =MM_Income!AF$9 -> 195267.81
B10: Employee workplace pension contribution | C10: =C9*Assumptions!$C$28 -> 7000 | D10: =D9*Assumptions!$C$28 -> 7700 | E10: =E9*Assumptions!$C$28 -> 8008 | F10: =F9*Assumptions!$C$28 -> 8168.16 | G10: =G9*Assumptions!$C$28 -> 8331.5232 | H10: =H9*Assumptions!$C$28 -> 8498.1537 | I10: =I9*Assumptions!$C$28 -> 8668.1167 | J10: =J9*Assumptions!$C$28 -> 8841.4791 | ... AF10: =AF9*Assumptions!$C$28 -> 13668.747
